Workbook
Name SKU_1: Lists!$A$2:$A$2
Name SKU_10: Lists!$J$2:$J$2
Name SKU_11: Lists!$K$2:$K$2
Name SKU_12: Lists!$L$2:$L$3
Name SKU_13: Lists!$M$2:$M$2
Name SKU_14: Lists!$N$2:$N$2
Name SKU_15: Lists!$O$2:$O$2
Name SKU_16: Lists!$P$2:$P$2
Name SKU_17: Lists!$Q$2:$Q$2
Name SKU_18: Lists!$R$2:$R$2
Name SKU_19: Lists!$S$2:$S$2
Name SKU_2: Lists!$B$2:$B$2
Name SKU_20: Lists!$T$2:$T$3
Name SKU_21: Lists!$U$2:$U$2
Name SKU_22: Lists!$V$2:$V$3
Name SKU_23: Lists!$W$2:$W$3
Name SKU_24: Lists!$X$2:$X$4
Name SKU_25: Lists!$Y$2:$Y$2
Name SKU_26: Lists!$Z$2:$Z$2
Name SKU_27: Lists!$AA$2:$AA$3
Name SKU_28: Lists!$AB$2:$AB$3
Name SKU_29: Lists!$AC$2:$AC$2
Name SKU_3: Lists!$C$2:$C$2
Name SKU_30: Lists!$AD$2:$AD$4
Name SKU_31: Lists!$AE$2:$AE$4
Name SKU_32: Lists!$AF$2:$AF$2
Name SKU_33: Lists!$AG$2:$AG$4
Name SKU_34: Lists!$AH$2:$AH$2
Name SKU_35: Lists!$AI$2:$AI$2
Name SKU_36: Lists!$AJ$2:$AJ$2
Name SKU_37: Lists!$AK$2:$AK$3
Name SKU_38: Lists!$AL$2:$AL$2
Name SKU_39: Lists!$AM$2:$AM$2
Name SKU_4: Lists!$D$2:$D$15
Name SKU_40: Lists!$AN$2:$AN$3
Name SKU_41: Lists!$AO$2:$AO$4
Name SKU_42: Lists!$AP$2:$AP$2
Name SKU_43: Lists!$AQ$2:$AQ$2
Name SKU_44: Lists!$AR$2:$AR$3
Name SKU_45: Lists!$AS$2:$AS$4
Name SKU_46: Lists!$AT$2:$AT$4
Name SKU_47: Lists!$AU$2:$AU$2
Name SKU_48: Lists!$AV$2:$AV$2
Name SKU_49: Lists!$AW$2:$AW$3
Name SKU_5: Lists!$E$2:$E$4
Name SKU_50: Lists!$AX$2:$AX$2
Name SKU_51: Lists!$AY$2:$AY$2
Name SKU_52: Lists!$AZ$2:$AZ$2
Name SKU_53: Lists!$BA$2:$BA$2
Name SKU_54: Lists!$BB$2:$BB$2
Name SKU_55: Lists!$BC$2:$BC$3
Name SKU_56: Lists!$BD$2:$BD$2
Name SKU_57: Lists!$BE$2:$BE$2
Name SKU_58: Lists!$BF$2:$BF$2
Name SKU_59: Lists!$BG$2:$BG$2
Name SKU_6: Lists!$F$2:$F$9
Name SKU_7: Lists!$G$2:$G$2
Name SKU_8: Lists!$H$2:$H$2
Name SKU_9: Lists!$I$2:$I$9

Sheet Start Here
A1: Unified Data Platform | Azure cost model & BOM
A3: Topic | B3: Instructions / interpretation
A4: Scope | B4: One workbook: tagged scripts\udp.yml + all 15 example configurations. Source snapshot 2026-10-19. All declared targets included; one target active per scenario.
A5: 1. Choose scenario / target | B5: Open a BOM tab, select target in B2, and optionally filter Target to that value. Scenario Summary links to every BOM; Category Summary separates infrastructure, security, storage, Fabric, AI and other known costs.
A6: 2. Select Fabric capacity | B6: Every capacity starts as SELECT SKU, as requested. Choose F2-F8192 in the Shared Fabric capacity row for your target. Capacity is an existing dependency, not deployed by these YAMLs.
A7: 3. Change sizing | B7: Yellow cells are editable. Select a capability-specific SKU; edit quantity, size/monthly usage and PAYG utilization. Units are shown per line. Quantity=0 excludes a line.
A8: 4. Compare purchase plans | B8: Assumptions B7 chooses PAYG / 1Y / 3Y. A line can override via Purchase plan. Eligible compute uses actual reservation prices; consumption-only services remain PAYG under all plans. Missing reservation prices remain UNPRICED.
A9: 5. Interpret results | B9: Known monthly subtotal is NOT a complete estimate when unpriced active lines > 0. INCOMPLETE is deliberate. Annual run rate = monthly x 12, not a cash payment schedule. Plan comparison columns each have their own gap count.
A10: 6. Recommended baseline | B10: User requested ENABLED: ADLS where absent, Key Vault where absent, Sentinel, monitoring, private endpoints/DNS, egress, Azure OpenAI token usage, AI Search and Defender for Storage V2 (quote required). Every added line says Recommended baseline. Assumptions B10=0 excludes ALL such rows.
A11: 7. Resolve gaps | B11: Missing SKU, exact meter or usage is UNPRICED, never a zero-cost fallback. Enter Manual monthly rate USD/unit with quote source in the row note. Override rate is already normalized to the displayed monthly size unit; it bypasses utilization and is held constant in all plan comparisons. Remove it to resume SKU-derived pricing.
A12: Capacity accounting | B12: Compute pool billed ONCE per selected scenario. Fabric items (notebooks, Spark, pipelines, eventhouses, BI, data agents) appear in inventory as covered compute, not individual charges. OneLake is a pooled physical storage assumption. External Azure services billed separately.
A13: Capacity caveats | B13: Baseline CU price comes from the official Compute Pool Capacity Usage CU meter; reservation CU totals multiplied by SKU CUs. Validate F-SKU sizing/availability with Fabric estimator and your agreement. Opt-in Spark autoscale, overages and workload-specific serverless charges are NOT covered by reserved/shared capacity and require additional allowance.
A14: Reservation math | B14: 1Y total / 12; 3Y total / 36. Reserved compute is fully committed even when PAYG utilization <100%. No assumed discount or automatic substitution. DBU commitments, savings plans and storage reservations are not modeled.
... A27: Retail API documentation | B27: https://learn.microsoft.com/en-us/rest/api/cost-management/retail-prices/azure-retail-prices

Sheet Scenario Summary
A1: Unified Data Platform | scenario comparison
A2: Alternatives, NOT additive. Each subtotal excludes UNPRICED lines. Select Fabric SKU on each BOM to complete capacity costing.
A5: Scenario | B5: Selected target | C5: Known monthly subtotal (USD) | D5: Annual run rate (USD) | E5: Unpriced active lines | F5: Estimate status | G5: YAML / dependency USD | H5: Recommended baseline USD | I5: PAYG known subtotal USD | J5: 1Y known subtotal USD | K5: 3Y known subtotal USD | L5: PAYG gaps | M5: 1Y gaps | N5: 3Y gaps
A6: Base udp.yml | B6: ='Base udp.yml'!B2 -> prod | C6: ='Base udp.yml'!H2 -> 330.434 | D6: =C6*Assumptions!$B$8 -> 3965.208 | E6: ='Base udp.yml'!K2 -> 3 | F6: ='Base udp.yml'!N2 -> INCOMPLETE | G6: =SUMIFS('Base udp.yml'!O6:O26,'Base udp.yml'!C6:C26,"<>Recommended baseline") -> 0 | H6: =SUMIF('Base udp.yml'!C6:C26,"Recommended baseline",'Base udp.yml'!O6:O26) -> 330.434 | I6: =SUM('Base udp.yml'!V6:V26) -> 330.434 | J6: =SUM('Base udp.yml'!W6:W26) -> 330.434 | K6: =SUM('Base udp.yml'!X6:X26) -> 330.434 | L6: =COUNTIF('Base udp.yml'!V6:V26,"UNPRICED") -> 3 | M6: =COUNTIF('Base udp.yml'!W6:W26,"UNPRICED") -> 3 | N6: =COUNTIF('Base udp.yml'!X6:X26,"UNPRICED") -> 3
A7: BOM 00-default | B7: ='BOM 00-default'!B2 -> dev | C7: ='BOM 00-default'!H2 -> 12281.034 | D7: =C7*Assumptions!$B$8 -> 147372.41 | E7: ='BOM 00-default'!K2 -> 34 | F7: ='BOM 00-default'!N2 -> INCOMPLETE | G7: =SUMIFS('BOM 00-default'!O6:O1473,'BOM 00-default'!C6:C1473,"<>Recommended baseline") -> 12175.304 | H7: =SUMIF('BOM 00-default'!C6:C1473,"Recommended baseline",'BOM 00-default'!O6:O1473) -> 105.73 | I7: =SUM('BOM 00-default'!V6:V1473) -> 12281.034 | J7: =SUM('BOM 00-default'!W6:W1473) -> 8453.9874 | K7: =SUM('BOM 00-default'!X6:X1473) -> 8215.543 | L7: =COUNTIF('BOM 00-default'!V6:V1473,"UNPRICED") -> 34 | M7: =COUNTIF('BOM 00-default'!W6:W1473,"UNPRICED") -> 34 | N7: =COUNTIF('BOM 00-default'!X6:X1473,"UNPRICED") -> 34
A8: BOM 01-minimal | B8: ='BOM 01-minimal'!B2 -> dev | C8: ='BOM 01-minimal'!H2 -> 8766.658 | D8: =C8*Assumptions!$B$8 -> 105199.9 | E8: ='BOM 01-minimal'!K2 -> 2 | F8: ='BOM 01-minimal'!N2 -> INCOMPLETE | G8: =SUMIFS('BOM 01-minimal'!O6:O25,'BOM 01-minimal'!C6:C25,"<>Recommended baseline") -> 8436.224 | H8: =SUMIF('BOM 01-minimal'!C6:C25,"Recommended baseline",'BOM 01-minimal'!O6:O25) -> 330.434 | I8: =SUM('BOM 01-minimal'!V6:V25) -> 8766.658 | J8: =SUM('BOM 01-minimal'!W6:W25) -> 5359.7247 | K8: =SUM('BOM 01-minimal'!X6:X25) -> 5359.7247 | L8: =COUNTIF('BOM 01-minimal'!V6:V25,"UNPRICED") -> 2 | M8: =COUNTIF('BOM 01-minimal'!W6:W25,"UNPRICED") -> 2 | N8: =COUNTIF('BOM 01-minimal'!X6:X25,"UNPRICED") -> 2
A9: BOM 02-medallion-lakehouse | B9: ='BOM 02-medallion-lakehouse'!B2 -> dev | C9: ='BOM 02-medallion-lakehouse'!H2 -> 357.058 | D9: =C9*Assumptions!$B$8 -> 4284.696 | E9: ='BOM 02-medallion-lakehouse'!K2 -> 3 | F9: ='BOM 02-medallion-lakehouse'!N2 -> INCOMPLETE | G9: =SUMIFS('BOM 02-medallion-lakehouse'!O6:O95,'BOM 02-medallion-lakehouse'!C6:C95,"<>Recommended baseline") -> 26.624 | H9: =SUMIF('BOM 02-medallion-lakehouse'!C6:C95,"Recommended baseline",'BOM 02-medallion-lakehouse'!O6:O95) -> 330.434 | I9: =SUM('BOM 02-medallion-lakehouse'!V6:V95) -> 357.058 | J9: =SUM('BOM 02-medallion-lakehouse'!W6:W95) -> 357.058 | K9: =SUM('BOM 02-medallion-lakehouse'!X6:X95) -> 357.058 | L9: =COUNTIF('BOM 02-medallion-lakehouse'!V6:V95,"UNPRICED") -> 3 | M9: =COUNTIF('BOM 02-medallion-lakehouse'!W6:W95,"UNPRICED") -> 3 | N9: =COUNTIF('BOM 02-medallion-lakehouse'!X6:X95,"UNPRICED") -> 3
A10: BOM 03-real-time-intelligence | B10: ='BOM 03-real-time-intelligence'!B2 -> dev | C10: ='BOM 03-real-time-intelligence'!H2 -> 357.058 | D10: =C10*Assumptions!$B$8 -> 4284.696 | E10: ='BOM 03-real-time-intelligence'!K2 -> 3 | F10: ='BOM 03-real-time-intelligence'!N2 -> INCOMPLETE | G10: =SUMIFS('BOM 03-real-time-intelligence'!O6:O53,'BOM 03-real-time-intelligence'!C6:C53,"<>Recommended baseline") -> 26.624 | H10: =SUMIF('BOM 03-real-time-intelligence'!C6:C53,"Recommended baseline",'BOM 03-real-time-intelligence'!O6:O53) -> 330.434 | I10: =SUM('BOM 03-real-time-intelligence'!V6:V53) -> 357.058 | J10: =SUM('BOM 03-real-time-intelligence'!W6:W53) -> 357.058 | K10: =SUM('BOM 03-real-time-intelligence'!X6:X53) -> 357.058 | L10: =COUNTIF('BOM 03-real-time-intelligence'!V6:V53,"UNPRICED") -> 3 | M10: =COUNTIF('BOM 03-real-time-intelligence'!W6:W53,"UNPRICED") -> 3 | N10: =COUNTIF('BOM 03-real-time-intelligence'!X6:X53,"UNPRICED") -> 3
A11: BOM 04-data-science | B11: ='BOM 04-data-science'!B2 -> dev | C11: ='BOM 04-data-science'!H2 -> 357.058 | D11: =C11*Assumptions!$B$8 -> 4284.696 | E11: ='BOM 04-data-science'!K2 -> 3 | F11: ='BOM 04-data-science'!N2 -> INCOMPLETE | G11: =SUMIFS('BOM 04-data-science'!O6:O59,'BOM 04-data-science'!C6:C59,"<>Recommended baseline") -> 26.624 | H11: =SUMIF('BOM 04-data-science'!C6:C59,"Recommended baseline",'BOM 04-data-science'!O6:O59) -> 330.434 | I11: =SUM('BOM 04-data-science'!V6:V59) -> 357.058 | J11: =SUM('BOM 04-data-science'!W6:W59) -> 357.058 | K11: =SUM('BOM 04-data-science'!X6:X59) -> 357.058 | L11: =COUNTIF('BOM 04-data-science'!V6:V59,"UNPRICED") -> 3 | M11: =COUNTIF('BOM 04-data-science'!W6:W59,"UNPRICED") -> 3 | N11: =COUNTIF('BOM 04-data-science'!X6:X59,"UNPRICED") -> 3
A12: BOM 05-multi-environment | B12: ='BOM 05-multi-environment'!B2 -> dev | C12: ='BOM 05-multi-environment'!H2 -> 357.058 | D12: =C12*Assumptions!$B$8 -> 4284.696 | E12: ='BOM 05-multi-environment'!K2 -> 3 | F12: ='BOM 05-multi-environment'!N2 -> INCOMPLETE | G12: =SUMIFS('BOM 05-multi-environment'!O6:O80,'BOM 05-multi-environment'!C6:C80,"<>Recommended baseline") -> 26.624 | H12: =SUMIF('BOM 05-multi-environment'!C6:C80,"Recommended baseline",'BOM 05-multi-environment'!O6:O80) -> 330.434 | I12: =SUM('BOM 05-multi-environment'!V6:V80) -> 357.058 | J12: =SUM('BOM 05-multi-environment'!W6:W80) -> 357.058 | K12: =SUM('BOM 05-multi-environment'!X6:X80) -> 357.058 | L12: =COUNTIF('BOM 05-multi-environment'!V6:V80,"UNPRICED") -> 3 | M12: =COUNTIF('BOM 05-multi-environment'!W6:W80,"UNPRICED") -> 3 | N12: =COUNTIF('BOM 05-multi-environment'!X6:X80,"UNPRICED") -> 3
A13: BOM 06-shortcuts-and-connectio | B13: ='BOM 06-shortcuts-and-connectio'!B2 -> dev | C13: ='BOM 06-shortcuts-and-connectio'!H2 -> 357.058 | D13: =C13*Assumptions!$B$8 -> 4284.696 | E13: ='BOM 06-shortcuts-and-connectio'!K2 -> 3 | F13: ='BOM 06-shortcuts-and-connectio'!N2 -> INCOMPLETE | G13: =SUMIFS('BOM 06-shortcuts-and-connectio'!O6:O26,'BOM 06-shortcuts-and-connectio'!C6:C26,"<>Recommended baseline") -> 26.624 | H13: =SUMIF('BOM 06-shortcuts-and-connectio'!C6:C26,"Recommended baseline",'BOM 06-shortcuts-and-connectio'!O6:O26) -> 330.434 | I13: =SUM('BOM 06-shortcuts-and-connectio'!V6:V26) -> 357.058 | J13: =SUM('BOM 06-shortcuts-and-connectio'!W6:W26) -> 357.058 | K13: =SUM('BOM 06-shortcuts-and-connectio'!X6:X26) -> 357.058 | L13: =COUNTIF('BOM 06-shortcuts-and-connectio'!V6:V26,"UNPRICED") -> 3 | M13: =COUNTIF('BOM 06-shortcuts-and-connectio'!W6:W26,"UNPRICED") -> 3 | N13: =COUNTIF('BOM 06-shortcuts-and-connectio'!X6:X26,"UNPRICED") -> 3
A14: BOM 07-shortcut-transformation | B14: ='BOM 07-shortcut-transformation'!B2 -> dev | C14: ='BOM 07-shortcut-transformation'!H2 -> 357.058 | D14: =C14*Assumptions!$B$8 -> 4284.696 | E14: ='BOM 07-shortcut-transformation'!K2 -> 3 | F14: ='BOM 07-shortcut-transformation'!N2 -> INCOMPLETE | G14: =SUMIFS('BOM 07-shortcut-transformation'!O6:O26,'BOM 07-shortcut-transformation'!C6:C26,"<>Recommended baseline") -> 26.624 | H14: =SUMIF('BOM 07-shortcut-transformation'!C6:C26,"Recommended baseline",'BOM 07-shortcut-transformation'!O6:O26) -> 330.434 | I14: =SUM('BOM 07-shortcut-transformation'!V6:V26) -> 357.058 | J14: =SUM('BOM 07-shortcut-transformation'!W6:W26) -> 357.058 | K14: =SUM('BOM 07-shortcut-transformation'!X6:X26) -> 357.058 | L14: =COUNTIF('BOM 07-shortcut-transformation'!V6:V26,"UNPRICED") -> 3 | M14: =COUNTIF('BOM 07-shortcut-transformation'!W6:W26,"UNPRICED") -> 3 | N14: =COUNTIF('BOM 07-shortcut-transformation'!X6:X26,"UNPRICED") -> 3
A15: BOM 08-all-resource-types | B15: ='BOM 08-all-resource-types'!B2 -> dev | C15: ='BOM 08-all-resource-types'!H2 -> 357.058 | D15: =C15*Assumptions!$B$8 -> 4284.696 | E15: ='BOM 08-all-resource-types'!K2 -> 3 | F15: ='BOM 08-all-resource-types'!N2 -> INCOMPLETE | G15: =SUMIFS('BOM 08-all-resource-types'!O6:O135,'BOM 08-all-resource-types'!C6:C135,"<>Recommended baseline") -> 26.624 | H15: =SUMIF('BOM 08-all-resource-types'!C6:C135,"Recommended baseline",'BOM 08-all-resource-types'!O6:O135) -> 330.434 | I15: =SUM('BOM 08-all-resource-types'!V6:V135) -> 357.058 | J15: =SUM('BOM 08-all-resource-types'!W6:W135) -> 357.058 | K15: =SUM('BOM 08-all-resource-types'!X6:X135) -> 357.058 | L15: =COUNTIF('BOM 08-all-resource-types'!V6:V135,"UNPRICED") -> 3 | M15: =COUNTIF('BOM 08-all-resource-types'!W6:W135,"UNPRICED") -> 3 | N15: =COUNTIF('BOM 08-all-resource-types'!X6:X135,"UNPRICED") -> 3
A16: BOM 09-tenant-settings | B16: ='BOM 09-tenant-settings'!B2 -> prod | C16: ='BOM 09-tenant-settings'!H2 -> 330.434 | D16: =C16*Assumptions!$B$8 -> 3965.208 | E16: ='BOM 09-tenant-settings'!K2 -> 3 | F16: ='BOM 09-tenant-settings'!N2 -> INCOMPLETE | G16: =SUMIFS('BOM 09-tenant-settings'!O6:O26,'BOM 09-tenant-settings'!C6:C26,"<>Recommended baseline") -> 0 | H16: =SUMIF('BOM 09-tenant-settings'!C6:C26,"Recommended baseline",'BOM 09-tenant-settings'!O6:O26) -> 330.434 | I16: =SUM('BOM 09-tenant-settings'!V6:V26) -> 330.434 | J16: =SUM('BOM 09-tenant-settings'!W6:W26) -> 330.434 | K16: =SUM('BOM 09-tenant-settings'!X6:X26) -> 330.434 | L16: =COUNTIF('BOM 09-tenant-settings'!V6:V26,"UNPRICED") -> 3 | M16: =COUNTIF('BOM 09-tenant-settings'!W6:W26,"UNPRICED") -> 3 | N16: =COUNTIF('BOM 09-tenant-settings'!X6:X26,"UNPRICED") -> 3
A17: BOM 10-azure-and-entra | B17: ='BOM 10-azure-and-entra'!B2 -> dev | C17: ='BOM 10-azure-and-entra'!H2 -> 356.6932 | D17: =C17*Assumptions!$B$8 -> 4280.3184 | E17: ='BOM 10-azure-and-entra'!K2 -> 3 | F17: ='BOM 10-azure-and-entra'!N2 -> INCOMPLETE | G17: =SUMIFS('BOM 10-azure-and-entra'!O6:O27,'BOM 10-azure-and-entra'!C6:C27,"<>Recommended baseline") -> 48.7632 | H17: =SUMIF('BOM 10-azure-and-entra'!C6:C27,"Recommended baseline",'BOM 10-azure-and-entra'!O6:O27) -> 307.93 | I17: =SUM('BOM 10-azure-and-entra'!V6:V27) -> 356.6932 | J17: =SUM('BOM 10-azure-and-entra'!W6:W27) -> 356.6932 | K17: =SUM('BOM 10-azure-and-entra'!X6:X27) -> 356.6932 | L17: =COUNTIF('BOM 10-azure-and-entra'!V6:V27,"UNPRICED") -> 3 | M17: =COUNTIF('BOM 10-azure-and-entra'!W6:W27,"UNPRICED") -> 3 | N17: =COUNTIF('BOM 10-azure-and-entra'!X6:X27,"UNPRICED") -> 3
A18: BOM 11-azure-data-services | B18: ='BOM 11-azure-data-services'!B2 -> dev | C18: ='BOM 11-azure-data-services'!H2 -> 2423.1384 | D18: =C18*Assumptions!$B$8 -> 29077.661 | E18: ='BOM 11-azure-data-services'!K2 -> 16 | F18: ='BOM 11-azure-data-services'!N2 -> INCOMPLETE | G18: =SUMIFS('BOM 11-azure-data-services'!O6:O60,'BOM 11-azure-data-services'!C6:C60,"<>Recommended baseline") -> 2114.9084 | H18: =SUMIF('BOM 11-azure-data-services'!C6:C60,"Recommended baseline",'BOM 11-azure-data-services'!O6:O60) -> 308.23 | I18: =SUM('BOM 11-azure-data-services'!V6:V60) -> 2423.1384 | J18: =SUM('BOM 11-azure-data-services'!W6:W60) -> 2003.0252 | K18: =SUM('BOM 11-azure-data-services'!X6:X60) -> 1764.5807 | L18: =COUNTIF('BOM 11-azure-data-services'!V6:V60,"UNPRICED") -> 16 | M18: =COUNTIF('BOM 11-azure-data-services'!W6:W60,"UNPRICED") -> 16 | N18: =COUNTIF('BOM 11-azure-data-services'!X6:X60,"UNPRICED") -> 16
A19: BOM 12-azure-platform-services | B19: ='BOM 12-azure-platform-services'!B2 -> dev | C19: ='BOM 12-azure-platform-services'!H2 -> 1630.224 | D19: =C19*Assumptions!$B$8 -> 19562.688 | E19: ='BOM 12-azure-platform-services'!K2 -> 15 | F19: ='BOM 12-azure-platform-services'!N2 -> INCOMPLETE | G19: =SUMIFS('BOM 12-azure-platform-services'!O6:O61,'BOM 12-azure-platform-services'!C6:C61,"<>Recommended baseline") -> 1502.29 | H19: =SUMIF('BOM 12-azure-platform-services'!C6:C61,"Recommended baseline",'BOM 12-azure-platform-services'!O6:O61) -> 127.934 | I19: =SUM('BOM 12-azure-platform-services'!V6:V61) -> 1630.224 | J19: =SUM('BOM 12-azure-platform-services'!W6:W61) -> 1630.224 | K19: =SUM('BOM 12-azure-platform-services'!X6:X61) -> 1630.224 | L19: =COUNTIF('BOM 12-azure-platform-services'!V6:V61,"UNPRICED") -> 15 | M19: =COUNTIF('BOM 12-azure-platform-services'!W6:W61,"UNPRICED") -> 15 | N19: =COUNTIF('BOM 12-azure-platform-services'!X6:X61,"UNPRICED") -> 15
A20: BOM 13-realtime-governance | B20: ='BOM 13-realtime-governance'!B2 -> dev | C20: ='BOM 13-realtime-governance'!H2 -> 327.658 | D20: =C20*Assumptions!$B$8 -> 3931.896 | E20: ='BOM 13-realtime-governance'!K2 -> 3 | F20: ='BOM 13-realtime-governance'!N2 -> INCOMPLETE | G20: =SUMIFS('BOM 13-realtime-governance'!O6:O33,'BOM 13-realtime-governance'!C6:C33,"<>Recommended baseline") -> 195.524 | H20: =SUMIF('BOM 13-realtime-governance'!C6:C33,"Recommended baseline",'BOM 13-realtime-governance'!O6:O33) -> 132.134 | I20: =SUM('BOM 13-realtime-governance'!V6:V33) -> 327.658 | J20: =SUM('BOM 13-realtime-governance'!W6:W33) -> 327.658 | K20: =SUM('BOM 13-realtime-governance'!X6:X33) -> 327.658 | L20: =COUNTIF('BOM 13-realtime-governance'!V6:V33,"UNPRICED") -> 3 | M20: =COUNTIF('BOM 13-realtime-governance'!W6:W33,"UNPRICED") -> 3 | N20: =COUNTIF('BOM 13-realtime-governance'!X6:X33,"UNPRICED") -> 3
A21: BOM 14-streaming-lakehouse-gov | B21: ='BOM 14-streaming-lakehouse-gov'!B2 -> dev | C21: ='BOM 14-streaming-lakehouse-gov'!H2 -> 824.158 | D21: =C21*Assumptions!$B$8 -> 9889.896 | E21: ='BOM 14-streaming-lakehouse-gov'!K2 -> 4 | F21: ='BOM 14-streaming-lakehouse-gov'!N2 -> INCOMPLETE | G21: =SUMIFS('BOM 14-streaming-lakehouse-gov'!O6:O33,'BOM 14-streaming-lakehouse-gov'!C6:C33,"<>Recommended baseline") -> 692.024 | H21: =SUMIF('BOM 14-streaming-lakehouse-gov'!C6:C33,"Recommended baseline",'BOM 14-streaming-lakehouse-gov'!O6:O33) -> 132.134 | I21: =SUM('BOM 14-streaming-lakehouse-gov'!V6:V33) -> 824.158 | J21: =SUM('BOM 14-streaming-lakehouse-gov'!W6:W33) -> 716.838 | K21: =SUM('BOM 14-streaming-lakehouse-gov'!X6:X33) -> 654.56022 | L21: =COUNTIF('BOM 14-streaming-lakehouse-gov'!V6:V33,"UNPRICED") -> 4 | M21: =COUNTIF('BOM 14-streaming-lakehouse-gov'!W6:W33,"UNPRICED") -> 4 | N21: =COUNTIF('BOM 14-streaming-lakehouse-gov'!X6:X33,"UNPRICED") -> 4

Sheet Category Summary
A1: Known monthly costs by category | USD
A2: Costs exclude UNPRICED lines. Fabric starts unpriced; all subtotals remain partial until pricing gaps are resolved on the BOM.
A5: Scenario | B5: Target | C5: Fabric | D5: Infrastructure | E5: Security | F5: Storage | G5: AI | H5: AI / Compute | I5: Integration | J5: Database | K5: Monitoring | L5: Governance | M5: Review | N5: Unpriced lines
A6: Base udp.yml | B6: ='Base udp.yml'!B2 -> prod | C6: =SUMIF('Base udp.yml'!B6:B26,C$5,'Base udp.yml'!O6:O26) -> 0 | D6: =SUMIF('Base udp.yml'!B6:B26,D$5,'Base udp.yml'!O6:O26) -> 33.5 | E6: =SUMIF('Base udp.yml'!B6:B26,E$5,'Base udp.yml'!O6:O26) -> 129.3 | F6: =SUMIF('Base udp.yml'!B6:B26,F$5,'Base udp.yml'!O6:O26) -> 22.204 | G6: =SUMIF('Base udp.yml'!B6:B26,G$5,'Base udp.yml'!O6:O26) -> 76.43 | H6: =SUMIF('Base udp.yml'!B6:B26,H$5,'Base udp.yml'!O6:O26) -> 0 | I6: =SUMIF('Base udp.yml'!B6:B26,I$5,'Base udp.yml'!O6:O26) -> 0 | J6: =SUMIF('Base udp.yml'!B6:B26,J$5,'Base udp.yml'!O6:O26) -> 0 | K6: =SUMIF('Base udp.yml'!B6:B26,K$5,'Base udp.yml'!O6:O26) -> 69 | L6: =SUMIF('Base udp.yml'!B6:B26,L$5,'Base udp.yml'!O6:O26) -> 0 | M6: =SUMIF('Base udp.yml'!B6:B26,M$5,'Base udp.yml'!O6:O26) -> 0 | N6: ='Base udp.yml'!K2 -> 3
A7: BOM 00-default | B7: ='BOM 00-default'!B2 -> dev | C7: =SUMIF('BOM 00-default'!B6:B1473,C$5,'BOM 00-default'!O6:O1473) -> 8409.6 | D7: =SUMIF('BOM 00-default'!B6:B1473,D$5,'BOM 00-default'!O6:O1473) -> 959.83 | E7: =SUMIF('BOM 00-default'!B6:B1473,E$5,'BOM 00-default'!O6:O1473) -> 1058 | F7: =SUMIF('BOM 00-default'!B6:B1473,F$5,'BOM 00-default'!O6:O1473) -> 208.0688 | G7: =SUMIF('BOM 00-default'!B6:B1473,G$5,'BOM 00-default'!O6:O1473) -> 81.83 | H7: =SUMIF('BOM 00-default'!B6:B1473,H$5,'BOM 00-default'!O6:O1473) -> 620.5 | I7: =SUMIF('BOM 00-default'!B6:B1473,I$5,'BOM 00-default'!O6:O1473) -> 163.08 | J7: =SUMIF('BOM 00-default'!B6:B1473,J$5,'BOM 00-default'!O6:O1473) -> 708.12518 | K7: =SUMIF('BOM 00-default'!B6:B1473,K$5,'BOM 00-default'!O6:O1473) -> 72 | L7: =SUMIF('BOM 00-default'!B6:B1473,L$5,'BOM 00-default'!O6:O1473) -> 0 | M7: =SUMIF('BOM 00-default'!B6:B1473,M$5,'BOM 00-default'!O6:O1473) -> 0 | N7: ='BOM 00-default'!K2 -> 34
A8: BOM 01-minimal | B8: ='BOM 01-minimal'!B2 -> dev | C8: =SUMIF('BOM 01-minimal'!B6:B25,C$5,'BOM 01-minimal'!O6:O25) -> 8409.6 | D8: =SUMIF('BOM 01-minimal'!B6:B25,D$5,'BOM 01-minimal'!O6:O25) -> 33.5 | E8: =SUMIF('BOM 01-minimal'!B6:B25,E$5,'BOM 01-minimal'!O6:O25) -> 129.3 | F8: =SUMIF('BOM 01-minimal'!B6:B25,F$5,'BOM 01-minimal'!O6:O25) -> 48.828 | G8: =SUMIF('BOM 01-minimal'!B6:B25,G$5,'BOM 01-minimal'!O6:O25) -> 76.43 | H8: =SUMIF('BOM 01-minimal'!B6:B25,H$5,'BOM 01-minimal'!O6:O25) -> 0 | I8: =SUMIF('BOM 01-minimal'!B6:B25,I$5,'BOM 01-minimal'!O6:O25) -> 0 | J8: =SUMIF('BOM 01-minimal'!B6:B25,J$5,'BOM 01-minimal'!O6:O25) -> 0 | K8: =SUMIF('BOM 01-minimal'!B6:B25,K$5,'BOM 01-minimal'!O6:O25) -> 69 | L8: =SUMIF('BOM 01-minimal'!B6:B25,L$5,'BOM 01-minimal'!O6:O25) -> 0 | M8: =SUMIF('BOM 01-minimal'!B6:B25,M$5,'BOM 01-minimal'!O6:O25) -> 0 | N8: ='BOM 01-minimal'!K2 -> 2
A9: BOM 02-medallion-lakehouse | B9: ='BOM 02-medallion-lakehouse'!B2 -> dev | C9: =SUMIF('BOM 02-medallion-lakehouse'!B6:B95,C$5,'BOM 02-medallion-lakehouse'!O6:O95) -> 0 | D9: =SUMIF('BOM 02-medallion-lakehouse'!B6:B95,D$5,'BOM 02-medallion-lakehouse'!O6:O95) -> 33.5 | E9: =SUMIF('BOM 02-medallion-lakehouse'!B6:B95,E$5,'BOM 02-medallion-lakehouse'!O6:O95) -> 129.3 | F9: =SUMIF('BOM 02-medallion-lakehouse'!B6:B95,F$5,'BOM 02-medallion-lakehouse'!O6:O95) -> 48.828 | G9: =SUMIF('BOM 02-medallion-lakehouse'!B6:B95,G$5,'BOM 02-medallion-lakehouse'!O6:O95) -> 76.43 | H9: =SUMIF('BOM 02-medallion-lakehouse'!B6:B95,H$5,'BOM 02-medallion-lakehouse'!O6:O95) -> 0 | I9: =SUMIF('BOM 02-medallion-lakehouse'!B6:B95,I$5,'BOM 02-medallion-lakehouse'!O6:O95) -> 0 | J9: =SUMIF('BOM 02-medallion-lakehouse'!B6:B95,J$5,'BOM 02-medallion-lakehouse'!O6:O95) -> 0 | K9: =SUMIF('BOM 02-medallion-lakehouse'!B6:B95,K$5,'BOM 02-medallion-lakehouse'!O6:O95) -> 69 | L9: =SUMIF('BOM 02-medallion-lakehouse'!B6:B95,L$5,'BOM 02-medallion-lakehouse'!O6:O95) -> 0 | M9: =SUMIF('BOM 02-medallion-lakehouse'!B6:B95,M$5,'BOM 02-medallion-lakehouse'!O6:O95) -> 0 | N9: ='BOM 02-medallion-lakehouse'!K2 -> 3
A10: BOM 03-real-time-intelligence | B10: ='BOM 03-real-time-intelligence'!B2 -> dev | C10: =SUMIF('BOM 03-real-time-intelligence'!B6:B53,C$5,'BOM 03-real-time-intelligence'!O6:O53) -> 0 | D10: =SUMIF('BOM 03-real-time-intelligence'!B6:B53,D$5,'BOM 03-real-time-intelligence'!O6:O53) -> 33.5 | E10: =SUMIF('BOM 03-real-time-intelligence'!B6:B53,E$5,'BOM 03-real-time-intelligence'!O6:O53) -> 129.3 | F10: =SUMIF('BOM 03-real-time-intelligence'!B6:B53,F$5,'BOM 03-real-time-intelligence'!O6:O53) -> 48.828 | G10: =SUMIF('BOM 03-real-time-intelligence'!B6:B53,G$5,'BOM 03-real-time-intelligence'!O6:O53) -> 76.43 | H10: =SUMIF('BOM 03-real-time-intelligence'!B6:B53,H$5,'BOM 03-real-time-intelligence'!O6:O53) -> 0 | I10: =SUMIF('BOM 03-real-time-intelligence'!B6:B53,I$5,'BOM 03-real-time-intelligence'!O6:O53) -> 0 | J10: =SUMIF('BOM 03-real-time-intelligence'!B6:B53,J$5,'BOM 03-real-time-intelligence'!O6:O53) -> 0 | K10: =SUMIF('BOM 03-real-time-intelligence'!B6:B53,K$5,'BOM 03-real-time-intelligence'!O6:O53) -> 69 | L10: =SUMIF('BOM 03-real-time-intelligence'!B6:B53,L$5,'BOM 03-real-time-intelligence'!O6:O53) -> 0 | M10: =SUMIF('BOM 03-real-time-intelligence'!B6:B53,M$5,'BOM 03-real-time-intelligence'!O6:O53) -> 0 | N10: ='BOM 03-real-time-intelligence'!K2 -> 3
A11: BOM 04-data-science | B11: ='BOM 04-data-science'!B2 -> dev | C11: =SUMIF('BOM 04-data-science'!B6:B59,C$5,'BOM 04-data-science'!O6:O59) -> 0 | D11: =SUMIF('BOM 04-data-science'!B6:B59,D$5,'BOM 04-data-science'!O6:O59) -> 33.5 | E11: =SUMIF('BOM 04-data-science'!B6:B59,E$5,'BOM 04-data-science'!O6:O59) -> 129.3 | F11: =SUMIF('BOM 04-data-science'!B6:B59,F$5,'BOM 04-data-science'!O6:O59) -> 48.828 | G11: =SUMIF('BOM 04-data-science'!B6:B59,G$5,'BOM 04-data-science'!O6:O59) -> 76.43 | H11: =SUMIF('BOM 04-data-science'!B6:B59,H$5,'BOM 04-data-science'!O6:O59) -> 0 | I11: =SUMIF('BOM 04-data-science'!B6:B59,I$5,'BOM 04-data-science'!O6:O59) -> 0 | J11: =SUMIF('BOM 04-data-science'!B6:B59,J$5,'BOM 04-data-science'!O6:O59) -> 0 | K11: =SUMIF('BOM 04-data-science'!B6:B59,K$5,'BOM 04-data-science'!O6:O59) -> 69 | L11: =SUMIF('BOM 04-data-science'!B6:B59,L$5,'BOM 04-data-science'!O6:O59) -> 0 | M11: =SUMIF('BOM 04-data-science'!B6:B59,M$5,'BOM 04-data-science'!O6:O59) -> 0 | N11: ='BOM 04-data-science'!K2 -> 3
A12: BOM 05-multi-environment | B12: ='BOM 05-multi-environment'!B2 -> dev | C12: =SUMIF('BOM 05-multi-environment'!B6:B80,C$5,'BOM 05-multi-environment'!O6:O80) -> 0 | D12: =SUMIF('BOM 05-multi-environment'!B6:B80,D$5,'BOM 05-multi-environment'!O6:O80) -> 33.5 | E12: =SUMIF('BOM 05-multi-environment'!B6:B80,E$5,'BOM 05-multi-environment'!O6:O80) -> 129.3 | F12: =SUMIF('BOM 05-multi-environment'!B6:B80,F$5,'BOM 05-multi-environment'!O6:O80) -> 48.828 | G12: =SUMIF('BOM 05-multi-environment'!B6:B80,G$5,'BOM 05-multi-environment'!O6:O80) -> 76.43 | H12: =SUMIF('BOM 05-multi-environment'!B6:B80,H$5,'BOM 05-multi-environment'!O6:O80) -> 0 | I12: =SUMIF('BOM 05-multi-environment'!B6:B80,I$5,'BOM 05-multi-environment'!O6:O80) -> 0 | J12: =SUMIF('BOM 05-multi-environment'!B6:B80,J$5,'BOM 05-multi-environment'!O6:O80) -> 0 | K12: =SUMIF('BOM 05-multi-environment'!B6:B80,K$5,'BOM 05-multi-environment'!O6:O80) -> 69 | L12: =SUMIF('BOM 05-multi-environment'!B6:B80,L$5,'BOM 05-multi-environment'!O6:O80) -> 0 | M12: =SUMIF('BOM 05-multi-environment'!B6:B80,M$5,'BOM 05-multi-environment'!O6:O80) -> 0 | N12: ='BOM 05-multi-environment'!K2 -> 3
A13: BOM 06-shortcuts-and-connectio | B13: ='BOM 06-shortcuts-and-connectio'!B2 -> dev | C13: =SUMIF('BOM 06-shortcuts-and-connectio'!B6:B26,C$5,'BOM 06-shortcuts-and-connectio'!O6:O26) -> 0 | D13: =SUMIF('BOM 06-shortcuts-and-connectio'!B6:B26,D$5,'BOM 06-shortcuts-and-connectio'!O6:O26) -> 33.5 | E13: =SUMIF('BOM 06-shortcuts-and-connectio'!B6:B26,E$5,'BOM 06-shortcuts-and-connectio'!O6:O26) -> 129.3 | F13: =SUMIF('BOM 06-shortcuts-and-connectio'!B6:B26,F$5,'BOM 06-shortcuts-and-connectio'!O6:O26) -> 48.828 | G13: =SUMIF('BOM 06-shortcuts-and-connectio'!B6:B26,G$5,'BOM 06-shortcuts-and-connectio'!O6:O26) -> 76.43 | H13: =SUMIF('BOM 06-shortcuts-and-connectio'!B6:B26,H$5,'BOM 06-shortcuts-and-connectio'!O6:O26) -> 0 | I13: =SUMIF('BOM 06-shortcuts-and-connectio'!B6:B26,I$5,'BOM 06-shortcuts-and-connectio'!O6:O26) -> 0 | J13: =SUMIF('BOM 06-shortcuts-and-connectio'!B6:B26,J$5,'BOM 06-shortcuts-and-connectio'!O6:O26) -> 0 | K13: =SUMIF('BOM 06-shortcuts-and-connectio'!B6:B26,K$5,'BOM 06-shortcuts-and-connectio'!O6:O26) -> 69 | L13: =SUMIF('BOM 06-shortcuts-and-connectio'!B6:B26,L$5,'BOM 06-shortcuts-and-connectio'!O6:O26) -> 0 | M13: =SUMIF('BOM 06-shortcuts-and-connectio'!B6:B26,M$5,'BOM 06-shortcuts-and-connectio'!O6:O26) -> 0 | N13: ='BOM 06-shortcuts-and-connectio'!K2 -> 3
A14: BOM 07-shortcut-transformation | B14: ='BOM 07-shortcut-transformation'!B2 -> dev | C14: =SUMIF('BOM 07-shortcut-transformation'!B6:B26,C$5,'BOM 07-shortcut-transformation'!O6:O26) -> 0 | D14: =SUMIF('BOM 07-shortcut-transformation'!B6:B26,D$5,'BOM 07-shortcut-transformation'!O6:O26) -> 33.5 | E14: =SUMIF('BOM 07-shortcut-transformation'!B6:B26,E$5,'BOM 07-shortcut-transformation'!O6:O26) -> 129.3 | F14: =SUMIF('BOM 07-shortcut-transformation'!B6:B26,F$5,'BOM 07-shortcut-transformation'!O6:O26) -> 48.828 | G14: =SUMIF('BOM 07-shortcut-transformation'!B6:B26,G$5,'BOM 07-shortcut-transformation'!O6:O26) -> 76.43 | H14: =SUMIF('BOM 07-shortcut-transformation'!B6:B26,H$5,'BOM 07-shortcut-transformation'!O6:O26) -> 0 | I14: =SUMIF('BOM 07-shortcut-transformation'!B6:B26,I$5,'BOM 07-shortcut-transformation'!O6:O26) -> 0 | J14: =SUMIF('BOM 07-shortcut-transformation'!B6:B26,J$5,'BOM 07-shortcut-transformation'!O6:O26) -> 0 | K14: =SUMIF('BOM 07-shortcut-transformation'!B6:B26,K$5,'BOM 07-shortcut-transformation'!O6:O26) -> 69 | L14: =SUMIF('BOM 07-shortcut-transformation'!B6:B26,L$5,'BOM 07-shortcut-transformation'!O6:O26) -> 0 | M14: =SUMIF('BOM 07-shortcut-transformation'!B6:B26,M$5,'BOM 07-shortcut-transformation'!O6:O26) -> 0 | N14: ='BOM 07-shortcut-transformation'!K2 -> 3
A15: BOM 08-all-resource-types | B15: ='BOM 08-all-resource-types'!B2 -> dev | C15: =SUMIF('BOM 08-all-resource-types'!B6:B135,C$5,'BOM 08-all-resource-types'!O6:O135) -> 0 | D15: =SUMIF('BOM 08-all-resource-types'!B6:B135,D$5,'BOM 08-all-resource-types'!O6:O135) -> 33.5 | E15: =SUMIF('BOM 08-all-resource-types'!B6:B135,E$5,'BOM 08-all-resource-types'!O6:O135) -> 129.3 | F15: =SUMIF('BOM 08-all-resource-types'!B6:B135,F$5,'BOM 08-all-resource-types'!O6:O135) -> 48.828 | G15: =SUMIF('BOM 08-all-resource-types'!B6:B135,G$5,'BOM 08-all-resource-types'!O6:O135) -> 76.43 | H15: =SUMIF('BOM 08-all-resource-types'!B6:B135,H$5,'BOM 08-all-resource-types'!O6:O135) -> 0 | I15: =SUMIF('BOM 08-all-resource-types'!B6:B135,I$5,'BOM 08-all-resource-types'!O6:O135) -> 0 | J15: =SUMIF('BOM 08-all-resource-types'!B6:B135,J$5,'BOM 08-all-resource-types'!O6:O135) -> 0 | K15: =SUMIF('BOM 08-all-resource-types'!B6:B135,K$5,'BOM 08-all-resource-types'!O6:O135) -> 69 | L15: =SUMIF('BOM 08-all-resource-types'!B6:B135,L$5,'BOM 08-all-resource-types'!O6:O135) -> 0 | M15: =SUMIF('BOM 08-all-resource-types'!B6:B135,M$5,'BOM 08-all-resource-types'!O6:O135) -> 0 | N15: ='BOM 08-all-resource-types'!K2 -> 3
A16: BOM 09-tenant-settings | B16: ='BOM 09-tenant-settings'!B2 -> prod | C16: =SUMIF('BOM 09-tenant-settings'!B6:B26,C$5,'BOM 09-tenant-settings'!O6:O26) -> 0 | D16: =SUMIF('BOM 09-tenant-settings'!B6:B26,D$5,'BOM 09-tenant-settings'!O6:O26) -> 33.5 | E16: =SUMIF('BOM 09-tenant-settings'!B6:B26,E$5,'BOM 09-tenant-settings'!O6:O26) -> 129.3 | F16: =SUMIF('BOM 09-tenant-settings'!B6:B26,F$5,'BOM 09-tenant-settings'!O6:O26) -> 22.204 | G16: =SUMIF('BOM 09-tenant-settings'!B6:B26,G$5,'BOM 09-tenant-settings'!O6:O26) -> 76.43 | H16: =SUMIF('BOM 09-tenant-settings'!B6:B26,H$5,'BOM 09-tenant-settings'!O6:O26) -> 0 | I16: =SUMIF('BOM 09-tenant-settings'!B6:B26,I$5,'BOM 09-tenant-settings'!O6:O26) -> 0 | J16: =SUMIF('BOM 09-tenant-settings'!B6:B26,J$5,'BOM 09-tenant-settings'!O6:O26) -> 0 | K16: =SUMIF('BOM 09-tenant-settings'!B6:B26,K$5,'BOM 09-tenant-settings'!O6:O26) -> 69 | L16: =SUMIF('BOM 09-tenant-settings'!B6:B26,L$5,'BOM 09-tenant-settings'!O6:O26) -> 0 | M16: =SUMIF('BOM 09-tenant-settings'!B6:B26,M$5,'BOM 09-tenant-settings'!O6:O26) -> 0 | N16: ='BOM 09-tenant-settings'!K2 -> 3
A17: BOM 10-azure-and-entra | B17: ='BOM 10-azure-and-entra'!B2 -> dev | C17: =SUMIF('BOM 10-azure-and-entra'!B6:B27,C$5,'BOM 10-azure-and-entra'!O6:O27) -> 0 | D17: =SUMIF('BOM 10-azure-and-entra'!B6:B27,D$5,'BOM 10-azure-and-entra'!O6:O27) -> 33.5 | E17: =SUMIF('BOM 10-azure-and-entra'!B6:B27,E$5,'BOM 10-azure-and-entra'!O6:O27) -> 129.3 | F17: =SUMIF('BOM 10-azure-and-entra'!B6:B27,F$5,'BOM 10-azure-and-entra'!O6:O27) -> 48.4632 | G17: =SUMIF('BOM 10-azure-and-entra'!B6:B27,G$5,'BOM 10-azure-and-entra'!O6:O27) -> 76.43 | H17: =SUMIF('BOM 10-azure-and-entra'!B6:B27,H$5,'BOM 10-azure-and-entra'!O6:O27) -> 0 | I17: =SUMIF('BOM 10-azure-and-entra'!B6:B27,I$5,'BOM 10-azure-and-entra'!O6:O27) -> 0 | J17: =SUMIF('BOM 10-azure-and-entra'!B6:B27,J$5,'BOM 10-azure-and-entra'!O6:O27) -> 0 | K17: =SUMIF('BOM 10-azure-and-entra'!B6:B27,K$5,'BOM 10-azure-and-entra'!O6:O27) -> 69 | L17: =SUMIF('BOM 10-azure-and-entra'!B6:B27,L$5,'BOM 10-azure-and-entra'!O6:O27) -> 0 | M17: =SUMIF('BOM 10-azure-and-entra'!B6:B27,M$5,'BOM 10-azure-and-entra'!O6:O27) -> 0 | N17: ='BOM 10-azure-and-entra'!K2 -> 3
A18: BOM 11-azure-data-services | B18: ='BOM 11-azure-data-services'!B2 -> dev | C18: =SUMIF('BOM 11-azure-data-services'!B6:B60,C$5,'BOM 11-azure-data-services'!O6:O60) -> 0 | D18: =SUMIF('BOM 11-azure-data-services'!B6:B60,D$5,'BOM 11-azure-data-services'!O6:O60) -> 594.14 | E18: =SUMIF('BOM 11-azure-data-services'!B6:B60,E$5,'BOM 11-azure-data-services'!O6:O60) -> 129.3 | F18: =SUMIF('BOM 11-azure-data-services'!B6:B60,F$5,'BOM 11-azure-data-services'!O6:O60) -> 147.2432 | G18: =SUMIF('BOM 11-azure-data-services'!B6:B60,G$5,'BOM 11-azure-data-services'!O6:O60) -> 76.43 | H18: =SUMIF('BOM 11-azure-data-services'!B6:B60,H$5,'BOM 11-azure-data-services'!O6:O60) -> 620.5 | I18: =SUMIF('BOM 11-azure-data-services'!B6:B60,I$5,'BOM 11-azure-data-services'!O6:O60) -> 163.08 | J18: =SUMIF('BOM 11-azure-data-services'!B6:B60,J$5,'BOM 11-azure-data-services'!O6:O60) -> 623.44518 | K18: =SUMIF('BOM 11-azure-data-services'!B6:B60,K$5,'BOM 11-azure-data-services'!O6:O60) -> 69 | L18: =SUMIF('BOM 11-azure-data-services'!B6:B60,L$5,'BOM 11-azure-data-services'!O6:O60) -> 0 | M18: =SUMIF('BOM 11-azure-data-services'!B6:B60,M$5,'BOM 11-azure-data-services'!O6:O60) -> 0 | N18: ='BOM 11-azure-data-services'!K2 -> 16
A19: BOM 12-azure-platform-services | B19: ='BOM 12-azure-platform-services'!B2 -> dev | C19: =SUMIF('BOM 12-azure-platform-services'!B6:B61,C$5,'BOM 12-azure-platform-services'!O6:O61) -> 0 | D19: =SUMIF('BOM 12-azure-platform-services'!B6:B61,D$5,'BOM 12-azure-platform-services'!O6:O61) -> 399.19 | E19: =SUMIF('BOM 12-azure-platform-services'!B6:B61,E$5,'BOM 12-azure-platform-services'!O6:O61) -> 1058 | F19: =SUMIF('BOM 12-azure-platform-services'!B6:B61,F$5,'BOM 12-azure-platform-services'!O6:O61) -> 22.204 | G19: =SUMIF('BOM 12-azure-platform-services'!B6:B61,G$5,'BOM 12-azure-platform-services'!O6:O61) -> 81.83 | H19: =SUMIF('BOM 12-azure-platform-services'!B6:B61,H$5,'BOM 12-azure-platform-services'!O6:O61) -> 0 | I19: =SUMIF('BOM 12-azure-platform-services'!B6:B61,I$5,'BOM 12-azure-platform-services'!O6:O61) -> 0 | J19: =SUMIF('BOM 12-azure-platform-services'!B6:B61,J$5,'BOM 12-azure-platform-services'!O6:O61) -> 0 | K19: =SUMIF('BOM 12-azure-platform-services'!B6:B61,K$5,'BOM 12-azure-platform-services'!O6:O61) -> 69 | L19: =SUMIF('BOM 12-azure-platform-services'!B6:B61,L$5,'BOM 12-azure-platform-services'!O6:O61) -> 0 | M19: =SUMIF('BOM 12-azure-platform-services'!B6:B61,M$5,'BOM 12-azure-platform-services'!O6:O61) -> 0 | N19: ='BOM 12-azure-platform-services'!K2 -> 15
A20: BOM 13-realtime-governance | B20: ='BOM 13-realtime-governance'!B2 -> dev | C20: =SUMIF('BOM 13-realtime-governance'!B6:B33,C$5,'BOM 13-realtime-governance'!O6:O33) -> 0 | D20: =SUMIF('BOM 13-realtime-governance'!B6:B33,D$5,'BOM 13-realtime-governance'!O6:O33) -> 33.5 | E20: =SUMIF('BOM 13-realtime-governance'!B6:B33,E$5,'BOM 13-realtime-governance'!O6:O33) -> 143.9 | F20: =SUMIF('BOM 13-realtime-governance'!B6:B33,F$5,'BOM 13-realtime-governance'!O6:O33) -> 48.828 | G20: =SUMIF('BOM 13-realtime-governance'!B6:B33,G$5,'BOM 13-realtime-governance'!O6:O33) -> 76.43 | H20: =SUMIF('BOM 13-realtime-governance'!B6:B33,H$5,'BOM 13-realtime-governance'!O6:O33) -> 0 | I20: =SUMIF('BOM 13-realtime-governance'!B6:B33,I$5,'BOM 13-realtime-governance'!O6:O33) -> 25 | J20: =SUMIF('BOM 13-realtime-governance'!B6:B33,J$5,'BOM 13-realtime-governance'!O6:O33) -> 0 | K20: =SUMIF('BOM 13-realtime-governance'!B6:B33,K$5,'BOM 13-realtime-governance'!O6:O33) -> 0 | L20: =SUMIF('BOM 13-realtime-governance'!B6:B33,L$5,'BOM 13-realtime-governance'!O6:O33) -> 0 | M20: =SUMIF('BOM 13-realtime-governance'!B6:B33,M$5,'BOM 13-realtime-governance'!O6:O33) -> 0 | N20: ='BOM 13-realtime-governance'!K2 -> 3
A21: BOM 14-streaming-lakehouse-gov | B21: ='BOM 14-streaming-lakehouse-gov'!B2 -> dev | C21: =SUMIF('BOM 14-streaming-lakehouse-gov'!B6:B33,C$5,'BOM 14-streaming-lakehouse-gov'!O6:O33) -> 0 | D21: =SUMIF('BOM 14-streaming-lakehouse-gov'!B6:B33,D$5,'BOM 14-streaming-lakehouse-gov'!O6:O33) -> 313.82 | E21: =SUMIF('BOM 14-streaming-lakehouse-gov'!B6:B33,E$5,'BOM 14-streaming-lakehouse-gov'!O6:O33) -> 143.9 | F21: =SUMIF('BOM 14-streaming-lakehouse-gov'!B6:B33,F$5,'BOM 14-streaming-lakehouse-gov'!O6:O33) -> 48.828 | G21: =SUMIF('BOM 14-streaming-lakehouse-gov'!B6:B33,G$5,'BOM 14-streaming-lakehouse-gov'!O6:O33) -> 76.43 | H21: =SUMIF('BOM 14-streaming-lakehouse-gov'!B6:B33,H$5,'BOM 14-streaming-lakehouse-gov'!O6:O33) -> 219 | I21: =SUMIF('BOM 14-streaming-lakehouse-gov'!B6:B33,I$5,'BOM 14-streaming-lakehouse-gov'!O6:O33) -> 22.18 | J21: =SUMIF('BOM 14-streaming-lakehouse-gov'!B6:B33,J$5,'BOM 14-streaming-lakehouse-gov'!O6:O33) -> 0 | K21: =SUMIF('BOM 14-streaming-lakehouse-gov'!B6:B33,K$5,'BOM 14-streaming-lakehouse-gov'!O6:O33) -> 0 | L21: =SUMIF('BOM 14-streaming-lakehouse-gov'!B6:B33,L$5,'BOM 14-streaming-lakehouse-gov'!O6:O33) -> 0 | M21: =SUMIF('BOM 14-streaming-lakehouse-gov'!B6:B33,M$5,'BOM 14-streaming-lakehouse-gov'!O6:O33) -> 0 | N21: ='BOM 14-streaming-lakehouse-gov'!K2 -> 4

Sheet Assumptions
A1: Model assumptions | East US | USD
A3: Assumption | B3: Value | C3: Units / interpretation | D3: Source / caveat
A4: Currency | B4: USD | C4: All costs in USD | D4: User baseline; no currency conversion
A5: Active hours per month | B5: 730 | C5: Hours for continuously running PAYG compute | D5: Editable; reservation payments do not pause
A6: Days per modeled month | B6: =B5/24 -> 30.416667 | C6: Hours divided by 24 | D6: Used for daily meters; 730-hour modeling convention
A7: Default purchase plan | B7: PAYG | C7: PAYG / 1Y / 3Y | D7: Applies only to reservation-eligible SKUs
A8: Months in 1-year term | B8: 12 | C8: Months | D8: Reservation normalization
A9: Months in 3-year term | B9: 36 | C9: Months | D9: Reservation normalization
A10: Enable recommended baseline | B10: 1 | C10: 1 = enabled; 0 = YAML/dependency model only | D10: User requested enabled production planning baseline
A11: OneLake pooled storage | B11: 1024 | C11: GB-month per selected workspace | D11: Assumption; not multiplied by number of lakehouses
A12: Monitoring log ingestion | B12: 30 | C12: GB/month | D12: Gross billable usage; free allowances not deducted
A13: Azure OpenAI input | B13: 10 | C13: Million tokens/month | D13: GPT-4o-mini global deployment planning assumption
A14: Azure OpenAI output | B14: 2 | C14: Million tokens/month | D14: Output tokens billed separately
A15: ADLS / Blob capacity | B15: 1024 | C15: GB-month per account | D15: Assumption where YAML gives no volume
A16: Outbound network usage | B16: 100 | C16: Billable GB/month after free allowances | D16: Assumption; first paid band, no graduated-tier calculation
A17: Private endpoints | B17: 3 | C17: Endpoints | D17: Starter baseline: storage, Key Vault, AI; validate service support
A18: Private DNS zones | B18: 3 | C18: Zones | D18: Starter baseline; reuse existing declared zones
A19: Protected storage accounts | B19: 1 | C19: Accounts | D19: Defender for Storage baseline
... A24: Days per year | B24: 365 | C24: Days | D24: Reference only; no reservation discount is assumed

Sheet SKU Catalog
A1: SKU-driven rate catalog | normalized monthly rates
A3: Lookup key | B3: Capability | C3: Selectable SKU | D3: Category | E3: Size / usage unit | F3: Billing basis | G3: PAYG raw unit USD | H3: 1Y term USD | I3: 3Y term USD | J3: Reservation eligible | K3: PAYG monthly USD/unit | L3: 1Y monthly USD/unit | M3: 3Y monthly USD/unit | N3: Evidence / caveat
A4: Covered|Included / no separate meter | B4: Covered | C4: Included / no separate meter | D4: Fabric | E4: resource | F4: Usage | G4: 0 | H4: 0 | I4: 0 | J4: 0 | K4: =IF(ISNUMBER(G4),G4,"UNPRICED") -> 0 | L4: =IF(J4=0,K4,IF(ISNUMBER(H4),H4/Assumptions!$B$8,"UNPRICED")) -> 0 | M4: =IF(J4=0,K4,IF(ISNUMBER(I4),I4/Assumptions!$B$9,"UNPRICED")) -> 0 | N4: Fabric compute is covered by the capacity line, not free compute. Storage is pooled separately.
A5: Control plane|No direct provisioning charge | B5: Control plane | C5: No direct provisioning charge | D5: Governance | E5: resource | F5: Usage | G5: 0 | H5: 0 | I5: 0 | J5: 0 | K5: =IF(ISNUMBER(G5),G5,"UNPRICED") -> 0 | L5: =IF(J5=0,K5,IF(ISNUMBER(H5),H5/Assumptions!$B$8,"UNPRICED")) -> 0 | M5: =IF(J5=0,K5,IF(ISNUMBER(I5),I5/Assumptions!$B$9,"UNPRICED")) -> 0 | N5: No direct resource provisioning charge. Connected services, paid licenses, traffic, processing and exported logs are separate.
A6: Review|REVIEW REQUIRED | B6: Review | C6: REVIEW REQUIRED | D6: Review | E6: quoted unit | F6: Usage | G6: UNPRICED | H6: UNPRICED | I6: UNPRICED | J6: 0 | K6: =IF(ISNUMBER(G6),G6,"UNPRICED") -> UNPRICED | L6: =IF(J6=0,K6,IF(ISNUMBER(H6),H6/Assumptions!$B$8,"UNPRICED")) -> UNPRICED | M6: =IF(J6=0,K6,IF(ISNUMBER(I6),I6/Assumptions!$B$9,"UNPRICED")) -> UNPRICED | N6: Missing service/SKU/sizing or retired service. Enter a justified manual rate; do not interpret as zero.
A7: Fabric capacity|SELECT SKU | B7: Fabric capacity | C7: SELECT SKU | D7: Fabric | E7: capacity | F7: Hourly | G7: UNPRICED | H7: UNPRICED | I7: UNPRICED | J7: 1 | K7: =IF(ISNUMBER(G7),G7*Assumptions!$B$5,"UNPRICED") -> UNPRICED | L7: =IF(J7=0,K7,IF(ISNUMBER(H7),H7/Assumptions!$B$8,"UNPRICED")) -> UNPRICED | M7: =IF(J7=0,K7,IF(ISNUMBER(I7),I7/Assumptions!$B$9,"UNPRICED")) -> UNPRICED | N7: YAML specifies capacity ID, not F SKU. Select F2-F8192; not a sizing recommendation.
A8: Fabric capacity|F2 | B8: Fabric capacity | C8: F2 | D8: Fabric | E8: capacity | F8: Hourly | G8: ='Price Evidence'!I4*2 -> 0.36 | H8: ='Price Evidence'!I5*2 -> 1876 | I8: ='Price Evidence'!I6*2 -> 5628 | J8: 1 | K8: =IF(ISNUMBER(G8),G8*Assumptions!$B$5,"UNPRICED") -> 262.8 | L8: =IF(J8=0,K8,IF(ISNUMBER(H8),H8/Assumptions!$B$8,"UNPRICED")) -> 156.33333 | M8: =IF(J8=0,K8,IF(ISNUMBER(I8),I8/Assumptions!$B$9,"UNPRICED")) -> 156.33333 | N8: Standard CU-hour pool rate x F-SKU CUs. Reservations are full-term CU commitments; all workloads share the pool.
A9: Fabric capacity|F4 | B9: Fabric capacity | C9: F4 | D9: Fabric | E9: capacity | F9: Hourly | G9: ='Price Evidence'!I4*4 -> 0.72 | H9: ='Price Evidence'!I5*4 -> 3752 | I9: ='Price Evidence'!I6*4 -> 11256 | J9: 1 | K9: =IF(ISNUMBER(G9),G9*Assumptions!$B$5,"UNPRICED") -> 525.6 | L9: =IF(J9=0,K9,IF(ISNUMBER(H9),H9/Assumptions!$B$8,"UNPRICED")) -> 312.66667 | M9: =IF(J9=0,K9,IF(ISNUMBER(I9),I9/Assumptions!$B$9,"UNPRICED")) -> 312.66667 | N9: Standard CU-hour pool rate x F-SKU CUs. Reservations are full-term CU commitments; all workloads share the pool.
A10: Fabric capacity|F8 | B10: Fabric capacity | C10: F8 | D10: Fabric | E10: capacity | F10: Hourly | G10: ='Price Evidence'!I4*8 -> 1.44 | H10: ='Price Evidence'!I5*8 -> 7504 | I10: ='Price Evidence'!I6*8 -> 22512 | J10: 1 | K10: =IF(ISNUMBER(G10),G10*Assumptions!$B$5,"UNPRICED") -> 1051.2 | L10: =IF(J10=0,K10,IF(ISNUMBER(H10),H10/Assumptions!$B$8,"UNPRICED")) -> 625.33333 | M10: =IF(J10=0,K10,IF(ISNUMBER(I10),I10/Assumptions!$B$9,"UNPRICED")) -> 625.33333 | N10: Standard CU-hour pool rate x F-SKU CUs. Reservations are full-term CU commitments; all workloads share the pool.
A11: Fabric capacity|F16 | B11: Fabric capacity | C11: F16 | D11: Fabric | E11: capacity | F11: Hourly | G11: ='Price Evidence'!I4*16 -> 2.88 | H11: ='Price Evidence'!I5*16 -> 15008 | I11: ='Price Evidence'!I6*16 -> 45024 | J11: 1 | K11: =IF(ISNUMBER(G11),G11*Assumptions!$B$5,"UNPRICED") -> 2102.4 | L11: =IF(J11=0,K11,IF(ISNUMBER(H11),H11/Assumptions!$B$8,"UNPRICED")) -> 1250.6667 | M11: =IF(J11=0,K11,IF(ISNUMBER(I11),I11/Assumptions!$B$9,"UNPRICED")) -> 1250.6667 | N11: Standard CU-hour pool rate x F-SKU CUs. Reservations are full-term CU commitments; all workloads share the pool.
A12: Fabric capacity|F32 | B12: Fabric capacity | C12: F32 | D12: Fabric | E12: capacity | F12: Hourly | G12: ='Price Evidence'!I4*32 -> 5.76 | H12: ='Price Evidence'!I5*32 -> 30016 | I12: ='Price Evidence'!I6*32 -> 90048 | J12: 1 | K12: =IF(ISNUMBER(G12),G12*Assumptions!$B$5,"UNPRICED") -> 4204.8 | L12: =IF(J12=0,K12,IF(ISNUMBER(H12),H12/Assumptions!$B$8,"UNPRICED")) -> 2501.3333 | M12: =IF(J12=0,K12,IF(ISNUMBER(I12),I12/Assumptions!$B$9,"UNPRICED")) -> 2501.3333 | N12: Standard CU-hour pool rate x F-SKU CUs. Reservations are full-term CU commitments; all workloads share the pool.
A13: Fabric capacity|F64 | B13: Fabric capacity | C13: F64 | D13: Fabric | E13: capacity | F13: Hourly | G13: ='Price Evidence'!I4*64 -> 11.52 | H13: ='Price Evidence'!I5*64 -> 60032 | I13: ='Price Evidence'!I6*64 -> 180096 | J13: 1 | K13: =IF(ISNUMBER(G13),G13*Assumptions!$B$5,"UNPRICED") -> 8409.6 | L13: =IF(J13=0,K13,IF(ISNUMBER(H13),H13/Assumptions!$B$8,"UNPRICED")) -> 5002.6667 | M13: =IF(J13=0,K13,IF(ISNUMBER(I13),I13/Assumptions!$B$9,"UNPRICED")) -> 5002.6667 | N13: Standard CU-hour pool rate x F-SKU CUs. Reservations are full-term CU commitments; all workloads share the pool.
A14: Fabric capacity|F128 | B14: Fabric capacity | C14: F128 | D14: Fabric | E14: capacity | F14: Hourly | G14: ='Price Evidence'!I4*128 -> 23.04 | H14: ='Price Evidence'!I5*128 -> 120064 | I14: ='Price Evidence'!I6*128 -> 360192 | J14: 1 | K14: =IF(ISNUMBER(G14),G14*Assumptions!$B$5,"UNPRICED") -> 16819.2 | L14: =IF(J14=0,K14,IF(ISNUMBER(H14),H14/Assumptions!$B$8,"UNPRICED")) -> 10005.333 | M14: =IF(J14=0,K14,IF(ISNUMBER(I14),I14/Assumptions!$B$9,"UNPRICED")) -> 10005.333 | N14: Standard CU-hour pool rate x F-SKU CUs. Reservations are full-term CU commitments; all workloads share the pool.
A15: Fabric capacity|F256 | B15: Fabric capacity | C15: F256 | D15: Fabric | E15: capacity | F15: Hourly | G15: ='Price Evidence'!I4*256 -> 46.08 | H15: ='Price Evidence'!I5*256 -> 240128 | I15: ='Price Evidence'!I6*256 -> 720384 | J15: 1 | K15: =IF(ISNUMBER(G15),G15*Assumptions!$B$5,"UNPRICED") -> 33638.4 | L15: =IF(J15=0,K15,IF(ISNUMBER(H15),H15/Assumptions!$B$8,"UNPRICED")) -> 20010.667 | M15: =IF(J15=0,K15,IF(ISNUMBER(I15),I15/Assumptions!$B$9,"UNPRICED")) -> 20010.667 | N15: Standard CU-hour pool rate x F-SKU CUs. Reservations are full-term CU commitments; all workloads share the pool.
A16: Fabric capacity|F512 | B16: Fabric capacity | C16: F512 | D16: Fabric | E16: capacity | F16: Hourly | G16: ='Price Evidence'!I4*512 -> 92.16 | H16: ='Price Evidence'!I5*512 -> 480256 | I16: ='Price Evidence'!I6*512 -> 1440768 | J16: 1 | K16: =IF(ISNUMBER(G16),G16*Assumptions!$B$5,"UNPRICED") -> 67276.8 | L16: =IF(J16=0,K16,IF(ISNUMBER(H16),H16/Assumptions!$B$8,"UNPRICED")) -> 40021.333 | M16: =IF(J16=0,K16,IF(ISNUMBER(I16),I16/Assumptions!$B$9,"UNPRICED")) -> 40021.333 | N16: Standard CU-hour pool rate x F-SKU CUs. Reservations are full-term CU commitments; all workloads share the pool.
A17: Fabric capacity|F1024 | B17: Fabric capacity | C17: F1024 | D17: Fabric | E17: capacity | F17: Hourly | G17: ='Price Evidence'!I4*1024 -> 184.32 | H17: ='Price Evidence'!I5*1024 -> 960512 | I17: ='Price Evidence'!I6*1024 -> 2881536 | J17: 1 | K17: =IF(ISNUMBER(G17),G17*Assumptions!$B$5,"UNPRICED") -> 134553.6 | L17: =IF(J17=0,K17,IF(ISNUMBER(H17),H17/Assumptions!$B$8,"UNPRICED")) -> 80042.667 | M17: =IF(J17=0,K17,IF(ISNUMBER(I17),I17/Assumptions!$B$9,"UNPRICED")) -> 80042.667 | N17: Standard CU-hour pool rate x F-SKU CUs. Reservations are full-term CU commitments; all workloads share the pool.
A18: Fabric capacity|F2048 | B18: Fabric capacity | C18: F2048 | D18: Fabric | E18: capacity | F18: Hourly | G18: ='Price Evidence'!I4*2048 -> 368.64 | H18: ='Price Evidence'!I5*2048 -> 1921024 | I18: ='Price Evidence'!I6*2048 -> 5763072 | J18: 1 | K18: =IF(ISNUMBER(G18),G18*Assumptions!$B$5,"UNPRICED") -> 269107.2 | L18: =IF(J18=0,K18,IF(ISNUMBER(H18),H18/Assumptions!$B$8,"UNPRICED")) -> 160085.33 | M18: =IF(J18=0,K18,IF(ISNUMBER(I18),I18/Assumptions!$B$9,"UNPRICED")) -> 160085.33 | N18: Standard CU-hour pool rate x F-SKU CUs. Reservations are full-term CU commitments; all workloads share the pool.
A19: Fabric capacity|F4096 | B19: Fabric capacity | C19: F4096 | D19: Fabric | E19: capacity | F19: Hourly | G19: ='Price Evidence'!I4*4096 -> 737.28 | H19: ='Price Evidence'!I5*4096 -> 3842048 | I19: ='Price Evidence'!I6*4096 -> 11526144 | J19: 1 | K19: =IF(ISNUMBER(G19),G19*Assumptions!$B$5,"UNPRICED") -> 538214.4 | L19: =IF(J19=0,K19,IF(ISNUMBER(H19),H19/Assumptions!$B$8,"UNPRICED")) -> 320170.67 | M19: =IF(J19=0,K19,IF(ISNUMBER(I19),I19/Assumptions!$B$9,"UNPRICED")) -> 320170.67 | N19: Standard CU-hour pool rate x F-SKU CUs. Reservations are full-term CU commitments; all workloads share the pool.
A20: Fabric capacity|F8192 | B20: Fabric capacity | C20: F8192 | D20: Fabric | E20: capacity | F20: Hourly | G20: ='Price Evidence'!I4*8192 -> 1474.56 | H20: ='Price Evidence'!I5*8192 -> 7684096 | I20: ='Price Evidence'!I6*8192 -> 23052288 | J20: 1 | K20: =IF(ISNUMBER(G20),G20*Assumptions!$B$5,"UNPRICED") -> 1076428.8 | L20: =IF(J20=0,K20,IF(ISNUMBER(H20),H20/Assumptions!$B$8,"UNPRICED")) -> 640341.33 | M20: =IF(J20=0,K20,IF(ISNUMBER(I20),I20/Assumptions!$B$9,"UNPRICED")) -> 640341.33 | N20: Standard CU-hour pool rate x F-SKU CUs. Reservations are full-term CU commitments; all workloads share the pool.
A21: OneLake storage|Hot | B21: OneLake storage | C21: Hot | D21: Storage | E21: GB-month | F21: Usage | G21: ='Price Evidence'!I7 -> 0.026 | H21: UNPRICED | I21: UNPRICED | J21: 0 | K21: =IF(ISNUMBER(G21),G21,"UNPRICED") -> 0.026 | L21: =IF(J21=0,K21,IF(ISNUMBER(H21),H21/Assumptions!$B$8,"UNPRICED")) -> 0.026 | M21: =IF(J21=0,K21,IF(ISNUMBER(I21),I21/Assumptions!$B$9,"UNPRICED")) -> 0.026 | N21: Pooled physical storage only; no shortcut source duplication; no mirroring allowance deduction.
A22: OneLake storage|Cool | B22: OneLake storage | C22: Cool | D22: Storage | E22: GB-month | F22: Usage | G22: ='Price Evidence'!I8 -> 0.019 | H22: UNPRICED | I22: UNPRICED | J22: 0 | K22: =IF(ISNUMBER(G22),G22,"UNPRICED") -> 0.019 | L22: =IF(J22=0,K22,IF(ISNUMBER(H22),H22/Assumptions!$B$8,"UNPRICED")) -> 0.019 | M22: =IF(J22=0,K22,IF(ISNUMBER(I22),I22/Assumptions!$B$9,"UNPRICED")) -> 0.019 | N22: Pooled physical storage only; no shortcut source duplication; no mirroring allowance deduction.
A23: OneLake storage|Cold | B23: OneLake storage | C23: Cold | D23: Storage | E23: GB-month | F23: Usage | G23: ='Price Evidence'!I9 -> 0.004 | H23: UNPRICED | I23: UNPRICED | J23: 0 | K23: =IF(ISNUMBER(G23),G23,"UNPRICED") -> 0.004 | L23: =IF(J23=0,K23,IF(ISNUMBER(H23),H23/Assumptions!$B$8,"UNPRICED")) -> 0.004 | M23: =IF(J23=0,K23,IF(ISNUMBER(I23),I23/Assumptions!$B$9,"UNPRICED")) -> 0.004 | N23: Pooled physical storage only; no shortcut source duplication; no mirroring allowance deduction.
A24: Blob storage|Hot LRS | B24: Blob storage | C24: Hot LRS | D24: Storage | E24: GB-month | F24: Usage | G24: ='Price Evidence'!I10 -> 0.0208 | H24: UNPRICED | I24: UNPRICED | J24: 0 | K24: =IF(ISNUMBER(G24),G24,"UNPRICED") -> 0.0208 | L24: =IF(J24=0,K24,IF(ISNUMBER(H24),H24/Assumptions!$B$8,"UNPRICED")) -> 0.0208 | M24: =IF(J24=0,K24,IF(ISNUMBER(I24),I24/Assumptions!$B$9,"UNPRICED")) -> 0.0208 | N24: First storage band; replication included in selected redundancy; retrieval and transaction meters are separate.
A25: Blob storage|Hot GRS | B25: Blob storage | C25: Hot GRS | D25: Storage | E25: GB-month | F25: Usage | G25: ='Price Evidence'!I11 -> 0.0458 | H25: UNPRICED | I25: UNPRICED | J25: 0 | K25: =IF(ISNUMBER(G25),G25,"UNPRICED") -> 0.0458 | L25: =IF(J25=0,K25,IF(ISNUMBER(H25),H25/Assumptions!$B$8,"UNPRICED")) -> 0.0458 | M25: =IF(J25=0,K25,IF(ISNUMBER(I25),I25/Assumptions!$B$9,"UNPRICED")) -> 0.0458 | N25: First storage band; replication included in selected redundancy; retrieval and transaction meters are separate.
A26: Blob storage|Hot ZRS | B26: Blob storage | C26: Hot ZRS | D26: Storage | E26: GB-month | F26: Usage | G26: ='Price Evidence'!I12 -> 0.026 | H26: UNPRICED | I26: UNPRICED | J26: 0 | K26: =IF(ISNUMBER(G26),G26,"UNPRICED") -> 0.026 | L26: =IF(J26=0,K26,IF(ISNUMBER(H26),H26/Assumptions!$B$8,"UNPRICED")) -> 0.026 | M26: =IF(J26=0,K26,IF(ISNUMBER(I26),I26/Assumptions!$B$9,"UNPRICED")) -> 0.026 | N26: First storage band; replication included in selected redundancy; retrieval and transaction meters are separate.
A27: Blob storage|Hot RA-GRS | B27: Blob storage | C27: Hot RA-GRS | D27: Storage | E27: GB-month | F27: Usage | G27: ='Price Evidence'!I13 -> 0.0589 | H27: UNPRICED | I27: UNPRICED | J27: 0 | K27: =IF(ISNUMBER(G27),G27,"UNPRICED") -> 0.0589 | L27: =IF(J27=0,K27,IF(ISNUMBER(H27),H27/Assumptions!$B$8,"UNPRICED")) -> 0.0589 | M27: =IF(J27=0,K27,IF(ISNUMBER(I27),I27/Assumptions!$B$9,"UNPRICED")) -> 0.0589 | N27: First storage band; replication included in selected redundancy; retrieval and transaction meters are separate.
A28: Blob storage|Cool LRS | B28: Blob storage | C28: Cool LRS | D28: Storage | E28: GB-month | F28: Usage | G28: ='Price Evidence'!I14 -> 0.0152 | H28: UNPRICED | I28: UNPRICED | J28: 0 | K28: =IF(ISNUMBER(G28),G28,"UNPRICED") -> 0.0152 | L28: =IF(J28=0,K28,IF(ISNUMBER(H28),H28/Assumptions!$B$8,"UNPRICED")) -> 0.0152 | M28: =IF(J28=0,K28,IF(ISNUMBER(I28),I28/Assumptions!$B$9,"UNPRICED")) -> 0.0152 | N28: First storage band; replication included in selected redundancy; retrieval and transaction meters are separate.
A29: Blob storage|Cool GRS | B29: Blob storage | C29: Cool GRS | D29: Storage | E29: GB-month | F29: Usage | G29: ='Price Evidence'!I15 -> 0.0334 | H29: UNPRICED | I29: UNPRICED | J29: 0 | K29: =IF(ISNUMBER(G29),G29,"UNPRICED") -> 0.0334 | L29: =IF(J29=0,K29,IF(ISNUMBER(H29),H29/Assumptions!$B$8,"UNPRICED")) -> 0.0334 | M29: =IF(J29=0,K29,IF(ISNUMBER(I29),I29/Assumptions!$B$9,"UNPRICED")) -> 0.0334 | N29: First storage band; replication included in selected redundancy; retrieval and transaction meters are separate.
A30: Blob storage|Cool ZRS | B30: Blob storage | C30: Cool ZRS | D30: Storage | E30: GB-month | F30: Usage | G30: ='Price Evidence'!I16 -> 0.019 | H30: UNPRICED | I30: UNPRICED | J30: 0 | K30: =IF(ISNUMBER(G30),G30,"UNPRICED") -> 0.019 | L30: =IF(J30=0,K30,IF(ISNUMBER(H30),H30/Assumptions!$B$8,"UNPRICED")) -> 0.019 | M30: =IF(J30=0,K30,IF(ISNUMBER(I30),I30/Assumptions!$B$9,"UNPRICED")) -> 0.019 | N30: First storage band; replication included in selected redundancy; retrieval and transaction meters are separate.
A31: Blob storage|Cool RA-GRS | B31: Blob storage | C31: Cool RA-GRS | D31: Storage | E31: GB-month | F31: Usage | G31: ='Price Evidence'!I17 -> 0.0425 | H31: UNPRICED | I31: UNPRICED | J31: 0 | K31: =IF(ISNUMBER(G31),G31,"UNPRICED") -> 0.0425 | L31: =IF(J31=0,K31,IF(ISNUMBER(H31),H31/Assumptions!$B$8,"UNPRICED")) -> 0.0425 | M31: =IF(J31=0,K31,IF(ISNUMBER(I31),I31/Assumptions!$B$9,"UNPRICED")) -> 0.0425 | N31: First storage band; replication included in selected redundancy; retrieval and transaction meters are separate.
A32: Blob storage writes|Hot LRS | B32: Blob storage writes | C32: Hot LRS | D32: Storage | E32: 10K operations | F32: Usage | G32: ='Price Evidence'!I18 -> 0.05 | H32: UNPRICED | I32: UNPRICED | J32: 0 | K32: =IF(ISNUMBER(G32),G32,"UNPRICED") -> 0.05 | L32: =IF(J32=0,K32,IF(ISNUMBER(H32),H32/Assumptions!$B$8,"UNPRICED")) -> 0.05 | M32: =IF(J32=0,K32,IF(ISNUMBER(I32),I32/Assumptions!$B$9,"UNPRICED")) -> 0.05 | N32: Meter units in Price Evidence. Review read/write meter for the selected storage tier.
... A43: ADLS storage reads|Hot LRS | B43: ADLS storage reads | C43: Hot LRS | D43: Storage | E43: 10K operations | F43: Usage | G43: ='Price Evidence'!I29 -> 0.005 | H43: UNPRICED | I43: UNPRICED | J43: 0 | K43: =IF(ISNUMBER(G43),G43,"UNPRICED") -> 0.005 | L43: =IF(J43=0,K43,IF(ISNUMBER(H43),H43/Assumptions!$B$8,"UNPRICED")) -> 0.005 | M43: =IF(J43=0,K43,IF(ISNUMBER(I43),I43/Assumptions!$B$9,"UNPRICED")) -> 0.005 | N43: Meter units in Price Evidence. Review read/write meter for the selected storage tier.
A44: File storage|Hot LRS | B44: File storage | C44: Hot LRS | D44: Storage | E44: GB-month | F44: Usage | G44: ='Price Evidence'!I30 -> 0.0287 | H44: UNPRICED | I44: UNPRICED | J44: 0 | K44: =IF(ISNUMBER(G44),G44,"UNPRICED") -> 0.0287 | L44: =IF(J44=0,K44,IF(ISNUMBER(H44),H44/Assumptions!$B$8,"UNPRICED")) -> 0.0287 | M44: =IF(J44=0,K44,IF(ISNUMBER(I44),I44/Assumptions!$B$9,"UNPRICED")) -> 0.0287
A45: Queue storage|Standard LRS | B45: Queue storage | C45: Standard LRS | D45: Storage | E45: GB-month | F45: Usage | G45: ='Price Evidence'!I31 -> 0.045 | H45: UNPRICED | I45: UNPRICED | J45: 0 | K45: =IF(ISNUMBER(G45),G45,"UNPRICED") -> 0.045 | L45: =IF(J45=0,K45,IF(ISNUMBER(H45),H45/Assumptions!$B$8,"UNPRICED")) -> 0.045 | M45: =IF(J45=0,K45,IF(ISNUMBER(I45),I45/Assumptions!$B$9,"UNPRICED")) -> 0.045
A46: Table storage|Standard LRS | B46: Table storage | C46: Standard LRS | D46: Storage | E46: GB-month | F46: Usage | G46: ='Price Evidence'!I32 -> 0.045 | H46: UNPRICED | I46: UNPRICED | J46: 0 | K46: =IF(ISNUMBER(G46),G46,"UNPRICED") -> 0.045 | L46: =IF(J46=0,K46,IF(ISNUMBER(H46),H46/Assumptions!$B$8,"UNPRICED")) -> 0.045 | M46: =IF(J46=0,K46,IF(ISNUMBER(I46),I46/Assumptions!$B$9,"UNPRICED")) -> 0.045
A47: File storage|Premium LRS - quote required | B47: File storage | C47: Premium LRS - quote required | D47: Storage | E47: provisioned GiB-month | F47: Usage | G47: UNPRICED | H47: UNPRICED | I47: UNPRICED | J47: 0 | K47: =IF(ISNUMBER(G47),G47,"UNPRICED") -> UNPRICED | L47: =IF(J47=0,K47,IF(ISNUMBER(H47),H47/Assumptions!$B$8,"UNPRICED")) -> UNPRICED | M47: =IF(J47=0,K47,IF(ISNUMBER(I47),I47/Assumptions!$B$9,"UNPRICED")) -> UNPRICED | N47: Premium Files requires provisioned capacity/IOPS/throughput sizing. Do not substitute standard hot storage.
A48: Key Vault|Standard | B48: Key Vault | C48: Standard | D48: Security | E48: 10K operations | F48: Usage | G48: ='Price Evidence'!I33 -> 0.03 | H48: UNPRICED | I48: UNPRICED | J48: 0 | K48: =IF(ISNUMBER(G48),G48,"UNPRICED") -> 0.03 | L48: =IF(J48=0,K48,IF(ISNUMBER(H48),H48/Assumptions!$B$8,"UNPRICED")) -> 0.03 | M48: =IF(J48=0,K48,IF(ISNUMBER(I48),I48/Assumptions!$B$9,"UNPRICED")) -> 0.03
A49: Logs|Analytics Logs | B49: Logs | C49: Analytics Logs | D49: Monitoring | E49: GB ingested | F49: Usage | G49: ='Price Evidence'!I34 -> 2.3 | H49: UNPRICED | I49: UNPRICED | J49: 0 | K49: =IF(ISNUMBER(G49),G49,"UNPRICED") -> 2.3 | L49: =IF(J49=0,K49,IF(ISNUMBER(H49),H49/Assumptions!$B$8,"UNPRICED")) -> 2.3 | M49: =IF(J49=0,K49,IF(ISNUMBER(I49),I49/Assumptions!$B$9,"UNPRICED")) -> 2.3 | N49: Gross paid-band ingestion. Free allowance ignored conservatively; Sentinel data is modeled separately to avoid double counting.
A50: Log retention|Analytics Logs | B50: Log retention | C50: Analytics Logs | D50: Monitoring | E50: GB-month beyond included retention | F50: Usage | G50: ='Price Evidence'!I35 -> 0.1 | H50: UNPRICED | I50: UNPRICED | J50: 0 | K50: =IF(ISNUMBER(G50),G50,"UNPRICED") -> 0.1 | L50: =IF(J50=0,K50,IF(ISNUMBER(H50),H50/Assumptions!$B$8,"UNPRICED")) -> 0.1 | M50: =IF(J50=0,K50,IF(ISNUMBER(I50),I50/Assumptions!$B$9,"UNPRICED")) -> 0.1
A51: Sentinel|Pay-as-you-go | B51: Sentinel | C51: Pay-as-you-go | D51: Security | E51: GB analyzed | F51: Usage | G51: ='Price Evidence'!I36 -> 4.3 | H51: UNPRICED | I51: UNPRICED | J51: 0 | K51: =IF(ISNUMBER(G51),G51,"UNPRICED") -> 4.3 | L51: =IF(J51=0,K51,IF(ISNUMBER(H51),H51/Assumptions!$B$8,"UNPRICED")) -> 4.3 | M51: =IF(J51=0,K51,IF(ISNUMBER(I51),I51/Assumptions!$B$9,"UNPRICED")) -> 4.3 | N51: Current simplified Sentinel analytics meter includes log ingestion and analysis. Do not also charge Logs for this same data.
A52: Defender servers|Standard v2 | B52: Defender servers | C52: Standard v2 | D52: Security | E52: protected resource | F52: Hourly | G52: ='Price Evidence'!I37 -> 0.02 | H52: UNPRICED | I52: UNPRICED | J52: 0 | K52: =IF(ISNUMBER(G52),G52*Assumptions!$B$5,"UNPRICED") -> 14.6 | L52: =IF(J52=0,K52,IF(ISNUMBER(H52),H52/Assumptions!$B$8,"UNPRICED")) -> 14.6 | M52: =IF(J52=0,K52,IF(ISNUMBER(I52),I52/Assumptions!$B$9,"UNPRICED")) -> 14.6 | N52: Verify exact Defender plan coverage. Storage entry is transaction-era Standard, not the V2 per-account plan.
A53: Defender storage|Standard | B53: Defender storage | C53: Standard | D53: Security | E53: protected resource | F53: Hourly | G53: ='Price Evidence'!I38 -> 0.0134 | H53: UNPRICED | I53: UNPRICED | J53: 0 | K53: =IF(ISNUMBER(G53),G53*Assumptions!$B$5,"UNPRICED") -> 9.782 | L53: =IF(J53=0,K53,IF(ISNUMBER(H53),H53/Assumptions!$B$8,"UNPRICED")) -> 9.782 | M53: =IF(J53=0,K53,IF(ISNUMBER(I53),I53/Assumptions!$B$9,"UNPRICED")) -> 9.782 | N53: Verify exact Defender plan coverage. Storage entry is transaction-era Standard, not the V2 per-account plan.
A54: Defender Key Vault|Per node Std | B54: Defender Key Vault | C54: Per node Std | D54: Security | E54: protected resource | F54: Hourly | G54: ='Price Evidence'!I39 -> 0.00034 | H54: UNPRICED | I54: UNPRICED | J54: 0 | K54: =IF(ISNUMBER(G54),G54*Assumptions!$B$5,"UNPRICED") -> 0.2482 | L54: =IF(J54=0,K54,IF(ISNUMBER(H54),H54/Assumptions!$B$8,"UNPRICED")) -> 0.2482 | M54: =IF(J54=0,K54,IF(ISNUMBER(I54),I54/Assumptions!$B$9,"UNPRICED")) -> 0.2482 | N54: Verify exact Defender plan coverage. Storage entry is transaction-era Standard, not the V2 per-account plan.
A55: Defender storage|V2 per account - quote required | B55: Defender storage | C55: V2 per account - quote required | D55: Security | E55: protected storage account | F55: Usage | G55: UNPRICED | H55: UNPRICED | I55: UNPRICED | J55: 0 | K55: =IF(ISNUMBER(G55),G55,"UNPRICED") -> UNPRICED | L55: =IF(J55=0,K55,IF(ISNUMBER(H55),H55/Assumptions!$B$8,"UNPRICED")) -> UNPRICED | M55: =IF(J55=0,K55,IF(ISNUMBER(I55),I55/Assumptions!$B$9,"UNPRICED")) -> UNPRICED | N55: Recommended current DefenderForStorageV2 plan. Exact per-account price unavailable in retrieved API snapshot; obtain current quote. Malware scanning and transaction overages are additional.
A56: OpenAI input|GPT-4o-mini global | B56: OpenAI input | C56: GPT-4o-mini global | D56: AI | E56: million tokens | F56: Usage | G56: ='Price Evidence'!I40*Assumptions!$B$21 -> 0.15 | H56: UNPRICED | I56: UNPRICED | J56: 0 | K56: =IF(ISNUMBER(G56),G56,"UNPRICED") -> 0.15 | L56: =IF(J56=0,K56,IF(ISNUMBER(H56),H56/Assumptions!$B$8,"UNPRICED")) -> 0.15 | M56: =IF(J56=0,K56,IF(ISNUMBER(I56),I56/Assumptions!$B$9,"UNPRICED")) -> 0.15 | N56: Global deployment token rate; input/output separated. Cached, batch, PTU, training and agent tools excluded.
A57: OpenAI input|GPT-4o global | B57: OpenAI input | C57: GPT-4o global | D57: AI | E57: million tokens | F57: Usage | G57: ='Price Evidence'!I41*Assumptions!$B$21 -> 2.5 | H57: UNPRICED | I57: UNPRICED | J57: 0 | K57: =IF(ISNUMBER(G57),G57,"UNPRICED") -> 2.5 | L57: =IF(J57=0,K57,IF(ISNUMBER(H57),H57/Assumptions!$B$8,"UNPRICED")) -> 2.5 | M57: =IF(J57=0,K57,IF(ISNUMBER(I57),I57/Assumptions!$B$9,"UNPRICED")) -> 2.5 | N57: Global deployment token rate; input/output separated. Cached, batch, PTU, training and agent tools excluded.
A58: OpenAI output|GPT-4o-mini global | B58: OpenAI output | C58: GPT-4o-mini global | D58: AI | E58: million tokens | F58: Usage | G58: ='Price Evidence'!I42*Assumptions!$B$21 -> 0.6 | H58: UNPRICED | I58: UNPRICED | J58: 0 | K58: =IF(ISNUMBER(G58),G58,"UNPRICED") -> 0.6 | L58: =IF(J58=0,K58,IF(ISNUMBER(H58),H58/Assumptions!$B$8,"UNPRICED")) -> 0.6 | M58: =IF(J58=0,K58,IF(ISNUMBER(I58),I58/Assumptions!$B$9,"UNPRICED")) -> 0.6 | N58: Global deployment token rate; input/output separated. Cached, batch, PTU, training and agent tools excluded.
A59: OpenAI output|GPT-4o global | B59: OpenAI output | C59: GPT-4o global | D59: AI | E59: million tokens | F59: Usage | G59: ='Price Evidence'!I43*Assumptions!$B$21 -> 10 | H59: UNPRICED | I59: UNPRICED | J59: 0 | K59: =IF(ISNUMBER(G59),G59,"UNPRICED") -> 10 | L59: =IF(J59=0,K59,IF(ISNUMBER(H59),H59/Assumptions!$B$8,"UNPRICED")) -> 10 | M59: =IF(J59=0,K59,IF(ISNUMBER(I59),I59/Assumptions!$B$9,"UNPRICED")) -> 10 | N59: Global deployment token rate; input/output separated. Cached, batch, PTU, training and agent tools excluded.
A60: AI Search|Basic | B60: AI Search | C60: Basic | D60: AI | E60: search unit (replicas x partitions) | F60: Hourly | G60: ='Price Evidence'!I44 -> 0.101 | H60: UNPRICED | I60: UNPRICED | J60: 0 | K60: =IF(ISNUMBER(G60),G60*Assumptions!$B$5,"UNPRICED") -> 73.73 | L60: =IF(J60=0,K60,IF(ISNUMBER(H60),H60/Assumptions!$B$8,"UNPRICED")) -> 73.73 | M60: =IF(J60=0,K60,IF(ISNUMBER(I60),I60/Assumptions!$B$9,"UNPRICED")) -> 73.73 | N60: One unit is replicas x partitions. Validate minimum replicas for required SLA.
A61: AI Search|Standard S1 | B61: AI Search | C61: Standard S1 | D61: AI | E61: search unit (replicas x partitions) | F61: Hourly | G61: ='Price Evidence'!I45 -> 0.336 | H61: UNPRICED | I61: UNPRICED | J61: 0 | K61: =IF(ISNUMBER(G61),G61*Assumptions!$B$5,"UNPRICED") -> 245.28 | L61: =IF(J61=0,K61,IF(ISNUMBER(H61),H61/Assumptions!$B$8,"UNPRICED")) -> 245.28 | M61: =IF(J61=0,K61,IF(ISNUMBER(I61),I61/Assumptions!$B$9,"UNPRICED")) -> 245.28 | N61: One unit is replicas x partitions. Validate minimum replicas for required SLA.
A62: AI Search|Standard S2 | B62: AI Search | C62: Standard S2 | D62: AI | E62: search unit (replicas x partitions) | F62: Hourly | G62: ='Price Evidence'!I46 -> 1.344 | H62: UNPRICED | I62: UNPRICED | J62: 0 | K62: =IF(ISNUMBER(G62),G62*Assumptions!$B$5,"UNPRICED") -> 981.12 | L62: =IF(J62=0,K62,IF(ISNUMBER(H62),H62/Assumptions!$B$8,"UNPRICED")) -> 981.12 | M62: =IF(J62=0,K62,IF(ISNUMBER(I62),I62/Assumptions!$B$9,"UNPRICED")) -> 981.12 | N62: One unit is replicas x partitions. Validate minimum replicas for required SLA.
A63: Private endpoint|Standard | B63: Private endpoint | C63: Standard | D63: Infrastructure | E63: endpoint | F63: Hourly | G63: ='Price Evidence'!I47 -> 0.01 | H63: UNPRICED | I63: UNPRICED | J63: 0 | K63: =IF(ISNUMBER(G63),G63*Assumptions!$B$5,"UNPRICED") -> 7.3 | L63: =IF(J63=0,K63,IF(ISNUMBER(H63),H63/Assumptions!$B$8,"UNPRICED")) -> 7.3 | M63: =IF(J63=0,K63,IF(ISNUMBER(I63),I63/Assumptions!$B$9,"UNPRICED")) -> 7.3
A64: Private endpoint traffic|Standard | B64: Private endpoint traffic | C64: Standard | D64: Infrastructure | E64: GB processed | F64: Usage | G64: ='Price Evidence'!I48 -> 0.01 | H64: UNPRICED | I64: UNPRICED | J64: 0 | K64: =IF(ISNUMBER(G64),G64,"UNPRICED") -> 0.01 | L64: =IF(J64=0,K64,IF(ISNUMBER(H64),H64/Assumptions!$B$8,"UNPRICED")) -> 0.01 | M64: =IF(J64=0,K64,IF(ISNUMBER(I64),I64/Assumptions!$B$9,"UNPRICED")) -> 0.01 | N64: First paid band; enter aggregate applicable ingress + egress volume.
A65: DNS|Private | B65: DNS | C65: Private | D65: Infrastructure | E65: zone | F65: Usage | G65: ='Price Evidence'!I49 -> 0.5 | H65: UNPRICED | I65: UNPRICED | J65: 0 | K65: =IF(ISNUMBER(G65),G65,"UNPRICED") -> 0.5 | L65: =IF(J65=0,K65,IF(ISNUMBER(H65),H65/Assumptions!$B$8,"UNPRICED")) -> 0.5 | M65: =IF(J65=0,K65,IF(ISNUMBER(I65),I65/Assumptions!$B$9,"UNPRICED")) -> 0.5
A66: DNS queries|Private | B66: DNS queries | C66: Private | D66: Infrastructure | E66: million queries | F66: Usage | G66: ='Price Evidence'!I50 -> 0.4 | H66: UNPRICED | I66: UNPRICED | J66: 0 | K66: =IF(ISNUMBER(G66),G66,"UNPRICED") -> 0.4 | L66: =IF(J66=0,K66,IF(ISNUMBER(H66),H66/Assumptions!$B$8,"UNPRICED")) -> 0.4 | M66: =IF(J66=0,K66,IF(ISNUMBER(I66),I66/Assumptions!$B$9,"UNPRICED")) -> 0.4
A67: DNS|Public | B67: DNS | C67: Public | D67: Infrastructure | E67: zone | F67: Usage | G67: ='Price Evidence'!I51 -> 0.5 | H67: UNPRICED | I67: UNPRICED | J67: 0 | K67: =IF(ISNUMBER(G67),G67,"UNPRICED") -> 0.5 | L67: =IF(J67=0,K67,IF(ISNUMBER(H67),H67/Assumptions!$B$8,"UNPRICED")) -> 0.5 | M67: =IF(J67=0,K67,IF(ISNUMBER(I67),I67/Assumptions!$B$9,"UNPRICED")) -> 0.5
A68: DNS queries|Public | B68: DNS queries | C68: Public | D68: Infrastructure | E68: million queries | F68: Usage | G68: ='Price Evidence'!I52 -> 0.4 | H68: UNPRICED | I68: UNPRICED | J68: 0 | K68: =IF(ISNUMBER(G68),G68,"UNPRICED") -> 0.4 | L68: =IF(J68=0,K68,IF(ISNUMBER(H68),H68/Assumptions!$B$8,"UNPRICED")) -> 0.4 | M68: =IF(J68=0,K68,IF(ISNUMBER(I68),I68/Assumptions!$B$9,"UNPRICED")) -> 0.4
A69: Egress|Internet first paid band | B69: Egress | C69: Internet first paid band | D69: Infrastructure | E69: billable GB | F69: Usage | G69: ='Price Evidence'!I53 -> 0.087 | H69: UNPRICED | I69: UNPRICED | J69: 0 | K69: =IF(ISNUMBER(G69),G69,"UNPRICED") -> 0.087 | L69: =IF(J69=0,K69,IF(ISNUMBER(H69),H69/Assumptions!$B$8,"UNPRICED")) -> 0.087 | M69: =IF(J69=0,K69,IF(ISNUMBER(I69),I69/Assumptions!$B$9,"UNPRICED")) -> 0.087 | N69: Enter billable volume after free allowance. First paid band only, not a graduated-tier engine.
A70: Firewall|Basic | B70: Firewall | C70: Basic | D70: Security | E70: firewall | F70: Hourly | G70: ='Price Evidence'!I54 -> 0.395 | H70: UNPRICED | I70: UNPRICED | J70: 0 | K70: =IF(ISNUMBER(G70),G70*Assumptions!$B$5,"UNPRICED") -> 288.35 | L70: =IF(J70=0,K70,IF(ISNUMBER(H70),H70/Assumptions!$B$8,"UNPRICED")) -> 288.35 | M70: =IF(J70=0,K70,IF(ISNUMBER(I70),I70/Assumptions!$B$9,"UNPRICED")) -> 288.35
A71: Firewall traffic|Basic | B71: Firewall traffic | C71: Basic | D71: Security | E71: GB processed | F71: Usage | G71: ='Price Evidence'!I55 -> 0.065 | H71: UNPRICED | I71: UNPRICED | J71: 0 | K71: =IF(ISNUMBER(G71),G71,"UNPRICED") -> 0.065 | L71: =IF(J71=0,K71,IF(ISNUMBER(H71),H71/Assumptions!$B$8,"UNPRICED")) -> 0.065 | M71: =IF(J71=0,K71,IF(ISNUMBER(I71),I71/Assumptions!$B$9,"UNPRICED")) -> 0.065
A72: Firewall|Standard | B72: Firewall | C72: Standard | D72: Security | E72: firewall | F72: Hourly | G72: ='Price Evidence'!I56 -> 1.25 | H72: UNPRICED | I72: UNPRICED | J72: 0 | K72: =IF(ISNUMBER(G72),G72*Assumptions!$B$5,"UNPRICED") -> 912.5 | L72: =IF(J72=0,K72,IF(ISNUMBER(H72),H72/Assumptions!$B$8,"UNPRICED")) -> 912.5 | M72: =IF(J72=0,K72,IF(ISNUMBER(I72),I72/Assumptions!$B$9,"UNPRICED")) -> 912.5
A73: Firewall traffic|Standard | B73: Firewall traffic | C73: Standard | D73: Security | E73: GB processed | F73: Usage | G73: ='Price Evidence'!I57 -> 0.016 | H73: UNPRICED | I73: UNPRICED | J73: 0 | K73: =IF(ISNUMBER(G73),G73,"UNPRICED") -> 0.016 | L73: =IF(J73=0,K73,IF(ISNUMBER(H73),H73/Assumptions!$B$8,"UNPRICED")) -> 0.016 | M73: =IF(J73=0,K73,IF(ISNUMBER(I73),I73/Assumptions!$B$9,"UNPRICED")) -> 0.016
A74: Firewall|Premium | B74: Firewall | C74: Premium | D74: Security | E74: firewall | F74: Hourly | G74: ='Price Evidence'!I58 -> 1.75 | H74: UNPRICED | I74: UNPRICED | J74: 0 | K74: =IF(ISNUMBER(G74),G74*Assumptions!$B$5,"UNPRICED") -> 1277.5 | L74: =IF(J74=0,K74,IF(ISNUMBER(H74),H74/Assumptions!$B$8,"UNPRICED")) -> 1277.5 | M74: =IF(J74=0,K74,IF(ISNUMBER(I74),I74/Assumptions!$B$9,"UNPRICED")) -> 1277.5
A75: Firewall traffic|Premium | B75: Firewall traffic | C75: Premium | D75: Security | E75: GB processed | F75: Usage | G75: ='Price Evidence'!I59 -> 0.016 | H75: UNPRICED | I75: UNPRICED | J75: 0 | K75: =IF(ISNUMBER(G75),G75,"UNPRICED") -> 0.016 | L75: =IF(J75=0,K75,IF(ISNUMBER(H75),H75/Assumptions!$B$8,"UNPRICED")) -> 0.016 | M75: =IF(J75=0,K75,IF(ISNUMBER(I75),I75/Assumptions!$B$9,"UNPRICED")) -> 0.016
A76: Public IP|Standard IPv4 | B76: Public IP | C76: Standard IPv4 | D76: Infrastructure | E76: address | F76: Hourly | G76: ='Price Evidence'!I60 -> 0.005 | H76: UNPRICED | I76: UNPRICED | J76: 0 | K76: =IF(ISNUMBER(G76),G76*Assumptions!$B$5,"UNPRICED") -> 3.65 | L76: =IF(J76=0,K76,IF(ISNUMBER(H76),H76/Assumptions!$B$8,"UNPRICED")) -> 3.65 | M76: =IF(J76=0,K76,IF(ISNUMBER(I76),I76/Assumptions!$B$9,"UNPRICED")) -> 3.65
A77: VPN Gateway|VpnGw1 | B77: VPN Gateway | C77: VpnGw1 | D77: Infrastructure | E77: gateway | F77: Hourly | G77: ='Price Evidence'!I61 -> 0.19 | H77: UNPRICED | I77: UNPRICED | J77: 0 | K77: =IF(ISNUMBER(G77),G77*Assumptions!$B$5,"UNPRICED") -> 138.7 | L77: =IF(J77=0,K77,IF(ISNUMBER(H77),H77/Assumptions!$B$8,"UNPRICED")) -> 138.7 | M77: =IF(J77=0,K77,IF(ISNUMBER(I77),I77/Assumptions!$B$9,"UNPRICED")) -> 138.7
A78: VPN Gateway|VpnGw2 | B78: VPN Gateway | C78: VpnGw2 | D78: Infrastructure | E78: gateway | F78: Hourly | G78: ='Price Evidence'!I62 -> 0.49 | H78: UNPRICED | I78: UNPRICED | J78: 0 | K78: =IF(ISNUMBER(G78),G78*Assumptions!$B$5,"UNPRICED") -> 357.7 | L78: =IF(J78=0,K78,IF(ISNUMBER(H78),H78/Assumptions!$B$8,"UNPRICED")) -> 357.7 | M78: =IF(J78=0,K78,IF(ISNUMBER(I78),I78/Assumptions!$B$9,"UNPRICED")) -> 357.7
A79: VPN Gateway|VpnGw3 | B79: VPN Gateway | C79: VpnGw3 | D79: Infrastructure | E79: gateway | F79: Hourly | G79: ='Price Evidence'!I63 -> 1.25 | H79: UNPRICED | I79: UNPRICED | J79: 0 | K79: =IF(ISNUMBER(G79),G79*Assumptions!$B$5,"UNPRICED") -> 912.5 | L79: =IF(J79=0,K79,IF(ISNUMBER(H79),H79/Assumptions!$B$8,"UNPRICED")) -> 912.5 | M79: =IF(J79=0,K79,IF(ISNUMBER(I79),I79/Assumptions!$B$9,"UNPRICED")) -> 912.5
A80: Virtual WAN|Routing Infrastructure Unit | B80: Virtual WAN | C80: Routing Infrastructure Unit | D80: Infrastructure | E80: hub routing unit | F80: Hourly | G80: ='Price Evidence'!I64 -> 0.1 | H80: UNPRICED | I80: UNPRICED | J80: 0 | K80: =IF(ISNUMBER(G80),G80*Assumptions!$B$5,"UNPRICED") -> 73 | L80: =IF(J80=0,K80,IF(ISNUMBER(H80),H80/Assumptions!$B$8,"UNPRICED")) -> 73 | M80: =IF(J80=0,K80,IF(ISNUMBER(I80),I80/Assumptions!$B$9,"UNPRICED")) -> 73 | N80: Hub routing only. Connection, scale units and traffic require separate quoted components.
A81: Application Gateway|Standard v2 | B81: Application Gateway | C81: Standard v2 | D81: Infrastructure | E81: gateway | F81: Hourly | G81: ='Price Evidence'!I65 -> 0.2 | H81: UNPRICED | I81: UNPRICED | J81: 0 | K81: =IF(ISNUMBER(G81),G81*Assumptions!$B$5,"UNPRICED") -> 146 | L81: =IF(J81=0,K81,IF(ISNUMBER(H81),H81/Assumptions!$B$8,"UNPRICED")) -> 146 | M81: =IF(J81=0,K81,IF(ISNUMBER(I81),I81/Assumptions!$B$9,"UNPRICED")) -> 146
A82: Application Gateway capacity|Standard v2 | B82: Application Gateway capacity | C82: Standard v2 | D82: Infrastructure | E82: capacity unit | F82: Hourly | G82: ='Price Evidence'!I66 -> 0.008 | H82: UNPRICED | I82: UNPRICED | J82: 0 | K82: =IF(ISNUMBER(G82),G82*Assumptions!$B$5,"UNPRICED") -> 5.84 | L82: =IF(J82=0,K82,IF(ISNUMBER(H82),H82/Assumptions!$B$8,"UNPRICED")) -> 5.84 | M82: =IF(J82=0,K82,IF(ISNUMBER(I82),I82/Assumptions!$B$9,"UNPRICED")) -> 5.84
A83: Event Hubs|Standard | B83: Event Hubs | C83: Standard | D83: Integration | E83: throughput unit | F83: Hourly | G83: ='Price Evidence'!I67 -> 0.03 | H83: UNPRICED | I83: UNPRICED | J83: 0 | K83: =IF(ISNUMBER(G83),G83*Assumptions!$B$5,"UNPRICED") -> 21.9 | L83: =IF(J83=0,K83,IF(ISNUMBER(H83),H83/Assumptions!$B$8,"UNPRICED")) -> 21.9 | M83: =IF(J83=0,K83,IF(ISNUMBER(I83),I83/Assumptions!$B$9,"UNPRICED")) -> 21.9
A84: Event Hubs|Basic | B84: Event Hubs | C84: Basic | D84: Integration | E84: throughput unit | F84: Hourly | G84: ='Price Evidence'!I68 -> 0.015 | H84: UNPRICED | I84: UNPRICED | J84: 0 | K84: =IF(ISNUMBER(G84),G84*Assumptions!$B$5,"UNPRICED") -> 10.95 | L84: =IF(J84=0,K84,IF(ISNUMBER(H84),H84/Assumptions!$B$8,"UNPRICED")) -> 10.95 | M84: =IF(J84=0,K84,IF(ISNUMBER(I84),I84/Assumptions!$B$9,"UNPRICED")) -> 10.95
A85: Event Hubs events|Standard | B85: Event Hubs events | C85: Standard | D85: Integration | E85: million events | F85: Usage | G85: ='Price Evidence'!I69 -> 0.028 | H85: UNPRICED | I85: UNPRICED | J85: 0 | K85: =IF(ISNUMBER(G85),G85,"UNPRICED") -> 0.028 | L85: =IF(J85=0,K85,IF(ISNUMBER(H85),H85/Assumptions!$B$8,"UNPRICED")) -> 0.028 | M85: =IF(J85=0,K85,IF(ISNUMBER(I85),I85/Assumptions!$B$9,"UNPRICED")) -> 0.028
A86: Event Grid|Basic topic / Standard operations meter | B86: Event Grid | C86: Basic topic / Standard operations meter | D86: Integration | E86: 100K operations | F86: Usage | G86: ='Price Evidence'!I70 -> 0.06 | H86: UNPRICED | I86: UNPRICED | J86: 0 | K86: =IF(ISNUMBER(G86),G86,"UNPRICED") -> 0.06 | L86: =IF(J86=0,K86,IF(ISNUMBER(H86),H86/Assumptions!$B$8,"UNPRICED")) -> 0.06 | M86: =IF(J86=0,K86,IF(ISNUMBER(I86),I86/Assumptions!$B$9,"UNPRICED")) -> 0.06 | N86: Basic topics use paid Standard Operations meter. Enter paid operation blocks after free allowance; review billed event size.
A87: Stream Analytics|Standard | B87: Stream Analytics | C87: Standard | D87: Integration | E87: streaming unit | F87: Hourly | G87: ='Price Evidence'!I71 -> 0.11 | H87: UNPRICED | I87: UNPRICED | J87: 0 | K87: =IF(ISNUMBER(G87),G87*Assumptions!$B$5,"UNPRICED") -> 80.3 | L87: =IF(J87=0,K87,IF(ISNUMBER(H87),H87/Assumptions!$B$8,"UNPRICED")) -> 80.3 | M87: =IF(J87=0,K87,IF(ISNUMBER(I87),I87/Assumptions!$B$9,"UNPRICED")) -> 80.3
A88: Stream Analytics|Standard V2 | B88: Stream Analytics | C88: Standard V2 | D88: Integration | E88: streaming unit | F88: Hourly | G88: ='Price Evidence'!I72 -> 0.33 | H88: UNPRICED | I88: UNPRICED | J88: 0 | K88: =IF(ISNUMBER(G88),G88*Assumptions!$B$5,"UNPRICED") -> 240.9 | L88: =IF(J88=0,K88,IF(ISNUMBER(H88),H88/Assumptions!$B$8,"UNPRICED")) -> 240.9 | M88: =IF(J88=0,K88,IF(ISNUMBER(I88),I88/Assumptions!$B$9,"UNPRICED")) -> 240.9
A89: IoT Hub|S1 | B89: IoT Hub | C89: S1 | D89: Integration | E89: hub unit | F89: Usage | G89: ='Price Evidence'!I73 -> 25 | H89: UNPRICED | I89: UNPRICED | J89: 0 | K89: =IF(ISNUMBER(G89),G89,"UNPRICED") -> 25 | L89: =IF(J89=0,K89,IF(ISNUMBER(H89),H89/Assumptions!$B$8,"UNPRICED")) -> 25 | M89: =IF(J89=0,K89,IF(ISNUMBER(I89),I89/Assumptions!$B$9,"UNPRICED")) -> 25
A90: IoT Hub|S2 | B90: IoT Hub | C90: S2 | D90: Integration | E90: hub unit | F90: Usage | G90: ='Price Evidence'!I74 -> 250 | H90: UNPRICED | I90: UNPRICED | J90: 0 | K90: =IF(ISNUMBER(G90),G90,"UNPRICED") -> 250 | L90: =IF(J90=0,K90,IF(ISNUMBER(H90),H90/Assumptions!$B$8,"UNPRICED")) -> 250 | M90: =IF(J90=0,K90,IF(ISNUMBER(I90),I90/Assumptions!$B$9,"UNPRICED")) -> 250
A91: IoT Hub|S3 | B91: IoT Hub | C91: S3 | D91: Integration | E91: hub unit | F91: Usage | G91: ='Price Evidence'!I75 -> 2500 | H91: UNPRICED | I91: UNPRICED | J91: 0 | K91: =IF(ISNUMBER(G91),G91,"UNPRICED") -> 2500 | L91: =IF(J91=0,K91,IF(ISNUMBER(H91),H91/Assumptions!$B$8,"UNPRICED")) -> 2500 | M91: =IF(J91=0,K91,IF(ISNUMBER(I91),I91/Assumptions!$B$9,"UNPRICED")) -> 2500
A92: ADF data movement|Cloud | B92: ADF data movement | C92: Cloud | D92: Integration | E92: DIU-hour | F92: Usage | G92: ='Price Evidence'!I76 -> 0.25 | H92: UNPRICED | I92: UNPRICED | J92: 0 | K92: =IF(ISNUMBER(G92),G92,"UNPRICED") -> 0.25 | L92: =IF(J92=0,K92,IF(ISNUMBER(H92),H92/Assumptions!$B$8,"UNPRICED")) -> 0.25 | M92: =IF(J92=0,K92,IF(ISNUMBER(I92),I92/Assumptions!$B$9,"UNPRICED")) -> 0.25
A93: ADF orchestration|Cloud | B93: ADF orchestration | C93: Cloud | D93: Integration | E93: 1K activity runs | F93: Usage | G93: ='Price Evidence'!I77 -> 1 | H93: UNPRICED | I93: UNPRICED | J93: 0 | K93: =IF(ISNUMBER(G93),G93,"UNPRICED") -> 1 | L93: =IF(J93=0,K93,IF(ISNUMBER(H93),H93/Assumptions!$B$8,"UNPRICED")) -> 1 | M93: =IF(J93=0,K93,IF(ISNUMBER(I93),I93/Assumptions!$B$9,"UNPRICED")) -> 1
A94: Databricks DBU|Premium Jobs Compute | B94: Databricks DBU | C94: Premium Jobs Compute | D94: AI / Compute | E94: DBU-hour | F94: Usage | G94: ='Price Evidence'!I78 -> 0.3 | H94: UNPRICED | I94: UNPRICED | J94: 0 | K94: =IF(ISNUMBER(G94),G94,"UNPRICED") -> 0.3 | L94: =IF(J94=0,K94,IF(ISNUMBER(H94),H94/Assumptions!$B$8,"UNPRICED")) -> 0.3 | M94: =IF(J94=0,K94,IF(ISNUMBER(I94),I94/Assumptions!$B$9,"UNPRICED")) -> 0.3 | N94: Classic compute DBUs only. VM nodes/disks/networking are separately modeled; no DBU commitment discount assumed.
A95: Databricks DBU|Premium All-purpose Compute | B95: Databricks DBU | C95: Premium All-purpose Compute | D95: AI / Compute | E95: DBU-hour | F95: Usage | G95: ='Price Evidence'!I79 -> 0.55 | H95: UNPRICED | I95: UNPRICED | J95: 0 | K95: =IF(ISNUMBER(G95),G95,"UNPRICED") -> 0.55 | L95: =IF(J95=0,K95,IF(ISNUMBER(H95),H95/Assumptions!$B$8,"UNPRICED")) -> 0.55 | M95: =IF(J95=0,K95,IF(ISNUMBER(I95),I95/Assumptions!$B$9,"UNPRICED")) -> 0.55 | N95: Classic compute DBUs only. VM nodes/disks/networking are separately modeled; no DBU commitment discount assumed.
A96: VM compute|Standard_D2s_v5 | B96: VM compute | C96: Standard_D2s_v5 | D96: Infrastructure | E96: node | F96: Hourly | G96: ='Price Evidence'!I80 -> 0.096 | H96: ='Price Evidence'!I81 -> 519 | I96: ='Price Evidence'!I82 -> 997 | J96: 1 | K96: =IF(ISNUMBER(G96),G96*Assumptions!$B$5,"UNPRICED") -> 70.08 | L96: =IF(J96=0,K96,IF(ISNUMBER(H96),H96/Assumptions!$B$8,"UNPRICED")) -> 43.25 | M96: =IF(J96=0,K96,IF(ISNUMBER(I96),I96/Assumptions!$B$9,"UNPRICED")) -> 27.694444 | N96: Linux classic VM compute; does not include Databricks DBUs, OS/data disks, Windows, SQL licenses or network.
A97: VM compute|Standard_D4s_v5 | B97: VM compute | C97: Standard_D4s_v5 | D97: Infrastructure | E97: node | F97: Hourly | G97: ='Price Evidence'!I83 -> 0.192 | H97: ='Price Evidence'!I84 -> 1038 | I97: ='Price Evidence'!I85 -> 1993 | J97: 1 | K97: =IF(ISNUMBER(G97),G97*Assumptions!$B$5,"UNPRICED") -> 140.16 | L97: =IF(J97=0,K97,IF(ISNUMBER(H97),H97/Assumptions!$B$8,"UNPRICED")) -> 86.5 | M97: =IF(J97=0,K97,IF(ISNUMBER(I97),I97/Assumptions!$B$9,"UNPRICED")) -> 55.361111 | N97: Linux classic VM compute; does not include Databricks DBUs, OS/data disks, Windows, SQL licenses or network.
A98: VM compute|Standard_D8s_v5 | B98: VM compute | C98: Standard_D8s_v5 | D98: Infrastructure | E98: node | F98: Hourly | G98: ='Price Evidence'!I86 -> 0.384 | H98: ='Price Evidence'!I87 -> 2075 | I98: ='Price Evidence'!I88 -> 3986 | J98: 1 | K98: =IF(ISNUMBER(G98),G98*Assumptions!$B$5,"UNPRICED") -> 280.32 | L98: =IF(J98=0,K98,IF(ISNUMBER(H98),H98/Assumptions!$B$8,"UNPRICED")) -> 172.91667 | M98: =IF(J98=0,K98,IF(ISNUMBER(I98),I98/Assumptions!$B$9,"UNPRICED")) -> 110.72222 | N98: Linux classic VM compute; does not include Databricks DBUs, OS/data disks, Windows, SQL licenses or network.
A99: SQL DTU|S0 | B99: SQL DTU | C99: S0 | D99: Database | E99: database | F99: Daily | G99: ='Price Evidence'!I89 -> 0.4839 | H99: UNPRICED | I99: UNPRICED | J99: 0 | K99: =IF(ISNUMBER(G99),G99*Assumptions!$B$6,"UNPRICED") -> 14.718625 | L99: =IF(J99=0,K99,IF(ISNUMBER(H99),H99/Assumptions!$B$8,"UNPRICED")) -> 14.718625 | M99: =IF(J99=0,K99,IF(ISNUMBER(I99),I99/Assumptions!$B$9,"UNPRICED")) -> 14.718625 | N99: DTU SKU, not vCore; reservation discounts are not assumed.
A100: SQL DTU|S1 | B100: SQL DTU | C100: S1 | D100: Database | E100: database | F100: Daily | G100: ='Price Evidence'!I90 -> 0.9677 | H100: UNPRICED | I100: UNPRICED | J100: 0 | K100: =IF(ISNUMBER(G100),G100*Assumptions!$B$6,"UNPRICED") -> 29.434208 | L100: =IF(J100=0,K100,IF(ISNUMBER(H100),H100/Assumptions!$B$8,"UNPRICED")) -> 29.434208 | M100: =IF(J100=0,K100,IF(ISNUMBER(I100),I100/Assumptions!$B$9,"UNPRICED")) -> 29.434208 | N100: DTU SKU, not vCore; reservation discounts are not assumed.
A101: SQL DTU|S2 | B101: SQL DTU | C101: S2 | D101: Database | E101: database | F101: Daily | G101: ='Price Evidence'!I91 -> 2.42 | H101: UNPRICED | I101: UNPRICED | J101: 0 | K101: =IF(ISNUMBER(G101),G101*Assumptions!$B$6,"UNPRICED") -> 73.608333 | L101: =IF(J101=0,K101,IF(ISNUMBER(H101),H101/Assumptions!$B$8,"UNPRICED")) -> 73.608333 | M101: =IF(J101=0,K101,IF(ISNUMBER(I101),I101/Assumptions!$B$9,"UNPRICED")) -> 73.608333 | N101: DTU SKU, not vCore; reservation discounts are not assumed.
A102: SQL MI compute|GP Gen5 | B102: SQL MI compute | C102: GP Gen5 | D102: Database | E102: vCore | F102: Hourly | G102: ='Price Evidence'!I92 -> 0.152218 | H102: ='Price Evidence'!I93 -> 867 | I102: ='Price Evidence'!I94 -> 1800 | J102: 1 | K102: =IF(ISNUMBER(G102),G102*Assumptions!$B$5,"UNPRICED") -> 111.11914 | L102: =IF(J102=0,K102,IF(ISNUMBER(H102),H102/Assumptions!$B$8,"UNPRICED")) -> 72.25 | M102: =IF(J102=0,K102,IF(ISNUMBER(I102),I102/Assumptions!$B$9,"UNPRICED")) -> 50 | N102: vCore rate, multiply by vCore count. Database storage, backups and SQL MI licenses separate.
A103: PostgreSQL compute|Dsv3 vCore | B103: PostgreSQL compute | C103: Dsv3 vCore | D103: Database | E103: vCore | F103: Hourly | G103: ='Price Evidence'!I95 -> 0.0855 | H103: ='Price Evidence'!I96 -> 449 | I103: ='Price Evidence'!I97 -> 899 | J103: 1 | K103: =IF(ISNUMBER(G103),G103*Assumptions!$B$5,"UNPRICED") -> 62.415 | L103: =IF(J103=0,K103,IF(ISNUMBER(H103),H103/Assumptions!$B$8,"UNPRICED")) -> 37.416667 | M103: =IF(J103=0,K103,IF(ISNUMBER(I103),I103/Assumptions!$B$9,"UNPRICED")) -> 24.972222 | N103: vCore rate, multiply by vCore count. Database storage, backups and SQL MI licenses separate.
A104: MySQL compute|Dsv3 vCore | B104: MySQL compute | C104: Dsv3 vCore | D104: Database | E104: vCore | F104: Hourly | G104: ='Price Evidence'!I98 -> 0.0855 | H104: ='Price Evidence'!I99 -> 449 | I104: ='Price Evidence'!I100 -> 899 | J104: 1 | K104: =IF(ISNUMBER(G104),G104*Assumptions!$B$5,"UNPRICED") -> 62.415 | L104: =IF(J104=0,K104,IF(ISNUMBER(H104),H104/Assumptions!$B$8,"UNPRICED")) -> 37.416667 | M104: =IF(J104=0,K104,IF(ISNUMBER(I104),I104/Assumptions!$B$9,"UNPRICED")) -> 24.972222 | N104: vCore rate, multiply by vCore count. Database storage, backups and SQL MI licenses separate.
A105: PostgreSQL storage|Storage | B105: PostgreSQL storage | C105: Storage | D105: Storage | E105: GB-month | F105: Usage | G105: ='Price Evidence'!I101 -> 0.115 | H105: UNPRICED | I105: UNPRICED | J105: 0 | K105: =IF(ISNUMBER(G105),G105,"UNPRICED") -> 0.115 | L105: =IF(J105=0,K105,IF(ISNUMBER(H105),H105/Assumptions!$B$8,"UNPRICED")) -> 0.115 | M105: =IF(J105=0,K105,IF(ISNUMBER(I105),I105/Assumptions!$B$9,"UNPRICED")) -> 0.115
A106: MySQL storage|Storage | B106: MySQL storage | C106: Storage | D106: Storage | E106: GB-month | F106: Usage | G106: ='Price Evidence'!I102 -> 0.115 | H106: UNPRICED | I106: UNPRICED | J106: 0 | K106: =IF(ISNUMBER(G106),G106,"UNPRICED") -> 0.115 | L106: =IF(J106=0,K106,IF(ISNUMBER(H106),H106/Assumptions!$B$8,"UNPRICED")) -> 0.115 | M106: =IF(J106=0,K106,IF(ISNUMBER(I106),I106/Assumptions!$B$9,"UNPRICED")) -> 0.115
A107: SQL MI storage|General Purpose | B107: SQL MI storage | C107: General Purpose | D107: Storage | E107: GB-month | F107: Usage | G107: ='Price Evidence'!I103 -> 0.115 | H107: UNPRICED | I107: UNPRICED | J107: 0 | K107: =IF(ISNUMBER(G107),G107,"UNPRICED") -> 0.115 | L107: =IF(J107=0,K107,IF(ISNUMBER(H107),H107/Assumptions!$B$8,"UNPRICED")) -> 0.115 | M107: =IF(J107=0,K107,IF(ISNUMBER(I107),I107/Assumptions!$B$9,"UNPRICED")) -> 0.115
A108: MySQL compute|D2ds_v4 - quote required | B108: MySQL compute | C108: D2ds_v4 - quote required | D108: Database | E108: server | F108: Hourly | G108: UNPRICED | H108: UNPRICED | I108: UNPRICED | J108: 1 | K108: =IF(ISNUMBER(G108),G108*Assumptions!$B$5,"UNPRICED") -> UNPRICED | L108: =IF(J108=0,K108,IF(ISNUMBER(H108),H108/Assumptions!$B$8,"UNPRICED")) -> UNPRICED | M108: =IF(J108=0,K108,IF(ISNUMBER(I108),I108/Assumptions!$B$9,"UNPRICED")) -> UNPRICED | N108: Configured Standard_D2ds_v4 not matched to a current exact meter. Select supported quoted sizing; no substitution.
A109: SQL MI license|LicenseIncluded - quote required | B109: SQL MI license | C109: LicenseIncluded - quote required | D109: Database | E109: licensed vCore | F109: Usage | G109: UNPRICED | H109: UNPRICED | I109: UNPRICED | J109: 0 | K109: =IF(ISNUMBER(G109),G109,"UNPRICED") -> UNPRICED | L109: =IF(J109=0,K109,IF(ISNUMBER(H109),H109/Assumptions!$B$8,"UNPRICED")) -> UNPRICED | M109: =IF(J109=0,K109,IF(ISNUMBER(I109),I109/Assumptions!$B$9,"UNPRICED")) -> UNPRICED | N109: Compute meter alone excludes SQL licensing. Confirm license-included quote or Azure Hybrid Benefit eligibility.
A110: Cosmos throughput|Manual provisioned | B110: Cosmos throughput | C110: Manual provisioned | D110: Database | E110: 100 RU/s | F110: Hourly | G110: ='Price Evidence'!I104 -> 0.008 | H110: UNPRICED | I110: UNPRICED | J110: 0 | K110: =IF(ISNUMBER(G110),G110*Assumptions!$B$5,"UNPRICED") -> 5.84 | L110: =IF(J110=0,K110,IF(ISNUMBER(H110),H110/Assumptions!$B$8,"UNPRICED")) -> 5.84 | M110: =IF(J110=0,K110,IF(ISNUMBER(I110),I110/Assumptions!$B$9,"UNPRICED")) -> 5.84 | N110: Multiply by provisioned 100-RU/s blocks and region count. Autoscale/serverless need different meters.
A111: Redis|Basic C0 | B111: Redis | C111: Basic C0 | D111: Database | E111: cache | F111: Hourly | G111: ='Price Evidence'!I105 -> 0.022 | H111: UNPRICED | I111: UNPRICED | J111: 0 | K111: =IF(ISNUMBER(G111),G111*Assumptions!$B$5,"UNPRICED") -> 16.06 | L111: =IF(J111=0,K111,IF(ISNUMBER(H111),H111/Assumptions!$B$8,"UNPRICED")) -> 16.06 | M111: =IF(J111=0,K111,IF(ISNUMBER(I111),I111/Assumptions!$B$9,"UNPRICED")) -> 16.06 | N111: Legacy Redis SKU: verify retirement/migration timeline. No Enterprise/Azure Managed Redis substitution.
...

Sheet Price Evidence
A1: Official price evidence | retrieved 2026-10-19
A3: Evidence ID | B3: Service | C3: Product | D3: SKU | E3: Meter | F3: Region | G3: Type | H3: Term | I3: Raw USD price | J3: API unit | K3: Tier minimum | L3: Effective date | M3: Meter ID | N3: API query | O3: Retrieved UTC
A4: P0001 | B4: Microsoft Fabric | C4: Fabric Capacity | D4: Compute Pool Capacity Usage | E4: Compute Pool Capacity Usage CU | F4: eastus | G4: Consumption | I4: 0.18 | J4: 1 Hour | K4: 0 | L4: 2023-11-01T00:00:00Z | M4: 2e1c6864-e833-5731-8dd6-220bc17b5566 | N4: https://prices.azure.com/api/retail/prices?%24filter=serviceName+eq+%27Microsoft+Fabric%27+and+%28armRegionName+eq+%27eastus%27+or+armRegionName+eq+%27%27+or+armRegionName+eq+%27global%27%29&currencyCode=%27USD%27&api-version=2023-01-01-preview | O4: 2026-10-19T20:20:48.622324+00:00
A5: P0002 | B5: Microsoft Fabric | C5: Fabric Capacity Reservation | D5: Fabric Capacity | E5: Fabric Capacity CU | F5: eastus | G5: Reservation | H5: 1 Year | I5: 938 | J5: 1 Hour | K5: 0 | L5: 2023-11-01T00:00:00Z | M5: 0867799b-2b02-5540-87b4-35b5ce92bdbf | N5: https://prices.azure.com/api/retail/prices?%24filter=serviceName+eq+%27Microsoft+Fabric%27+and+%28armRegionName+eq+%27eastus%27+or+armRegionName+eq+%27%27+or+armRegionName+eq+%27global%27%29&currencyCode=%27USD%27&api-version=2023-01-01-preview | O5: 2026-10-19T20:20:48.622324+00:00
A6: P0003 | B6: Microsoft Fabric | C6: Fabric Capacity Reservation | D6: Fabric Capacity | E6: Fabric Capacity CU | F6: eastus | G6: Reservation | H6: 3 Years | I6: 2814 | J6: 1 Hour | K6: 0 | L6: 2026-04-01T00:00:00Z | M6: 0867799b-2b02-5540-87b4-35b5ce92bdbf | N6: https://prices.azure.com/api/retail/prices?%24filter=serviceName+eq+%27Microsoft+Fabric%27+and+%28armRegionName+eq+%27eastus%27+or+armRegionName+eq+%27%27+or+armRegionName+eq+%27global%27%29&currencyCode=%27USD%27&api-version=2023-01-01-preview | O6: 2026-10-19T20:20:48.622324+00:00
A7: P0004 | B7: Microsoft Fabric | C7: OneLake | D7: OneLake Storage Hot | E7: OneLake Storage Hot Data Stored | F7: eastus | G7: Consumption | I7: 0.026 | J7: 1 GB/Month | K7: 0 | L7: 2023-11-01T00:00:00Z | M7: 700734cc-93b2-5b4e-a266-1cbea55d2428 | N7: https://prices.azure.com/api/retail/prices?%24filter=serviceName+eq+%27Microsoft+Fabric%27+and+%28armRegionName+eq+%27eastus%27+or+armRegionName+eq+%27%27+or+armRegionName+eq+%27global%27%29&currencyCode=%27USD%27&api-version=2023-01-01-preview | O7: 2026-10-19T20:20:48.622324+00:00
A8: P0005 | B8: Microsoft Fabric | C8: OneLake | D8: OneLake Storage Cool | E8: OneLake Storage Cool Data Stored | F8: eastus | G8: Consumption | I8: 0.019 | J8: 1 GB/Month | K8: 0 | L8: 2026-07-01T00:00:00Z | M8: 4dda280c-0ccf-5aea-ae22-25fd3e8ba5d9 | N8: https://prices.azure.com/api/retail/prices?%24filter=serviceName+eq+%27Microsoft+Fabric%27+and+%28armRegionName+eq+%27eastus%27+or+armRegionName+eq+%27%27+or+armRegionName+eq+%27global%27%29&currencyCode=%27USD%27&api-version=2023-01-01-preview | O8: 2026-10-19T20:20:48.622324+00:00
A9: P0006 | B9: Microsoft Fabric | C9: OneLake | D9: OneLake Storage Cold | E9: OneLake Storage Cold Data Stored | F9: eastus | G9: Consumption | I9: 0.004 | J9: 1 GB/Month | K9: 0 | L9: 2026-07-01T00:00:00Z | M9: 0789b970-2cb8-5b76-b552-19b31db2522b | N9: https://prices.azure.com/api/retail/prices?%24filter=serviceName+eq+%27Microsoft+Fabric%27+and+%28armRegionName+eq+%27eastus%27+or+armRegionName+eq+%27%27+or+armRegionName+eq+%27global%27%29&currencyCode=%27USD%27&api-version=2023-01-01-preview | O9: 2026-10-19T20:20:48.622324+00:00
A10: P0007 | B10: Storage | C10: General Block Blob v2 | D10: Hot LRS | E10: Hot LRS Data Stored | F10: eastus | G10: Consumption | I10: 0.0208 | J10: 1 GB/Month | K10: 0 | L10: 2017-02-03T00:00:00Z | M10: 272492b3-1c92-4a5f-bee9-52a8e10ca514 | N10: https://prices.azure.com/api/retail/prices?%24filter=serviceName+eq+%27Storage%27+and+%28armRegionName+eq+%27eastus%27+or+armRegionName+eq+%27%27+or+armRegionName+eq+%27global%27%29&currencyCode=%27USD%27&api-version=2023-01-01-preview | O10: 2026-10-19T20:20:48.622324+00:00
A11: P0008 | B11: Storage | C11: General Block Blob v2 | D11: Hot GRS | E11: Hot GRS Data Stored | F11: eastus | G11: Consumption | I11: 0.0458 | J11: 1 GB/Month | K11: 0 | L11: 2017-02-03T00:00:00Z | M11: 8375a86c-cc34-458a-aaf1-c8e2caf3ea71 | N11: https://prices.azure.com/api/retail/prices?%24filter=serviceName+eq+%27Storage%27+and+%28armRegionName+eq+%27eastus%27+or+armRegionName+eq+%27%27+or+armRegionName+eq+%27global%27%29&currencyCode=%27USD%27&api-version=2023-01-01-preview | O11: 2026-10-19T20:20:48.622324+00:00
A12: P0009 | B12: Storage | C12: General Block Blob v2 | D12: Hot ZRS | E12: Hot ZRS Data Stored | F12: eastus | G12: Consumption | I12: 0.026 | J12: 1 GB/Month | K12: 0 | L12: 2018-07-01T00:00:00Z | M12: da71cc90-624a-4006-8936-0718046ad8ab | N12: https://prices.azure.com/api/retail/prices?%24filter=serviceName+eq+%27Storage%27+and+%28armRegionName+eq+%27eastus%27+or+armRegionName+eq+%27%27+or+armRegionName+eq+%27global%27%29&currencyCode=%27USD%27&api-version=2023-01-01-preview | O12: 2026-10-19T20:20:48.622324+00:00
A13: P0010 | B13: Storage | C13: General Block Blob v2 | D13: Hot RA-GRS | E13: Hot RA-GRS Data Stored | F13: eastus | G13: Consumption | I13: 0.0589 | J13: 1 GB/Month | K13: 0 | L13: 2017-02-03T00:00:00Z | M13: 469a7d8f-36f1-4a99-a884-6eb97643be2c | N13: https://prices.azure.com/api/retail/prices?%24filter=serviceName+eq+%27Storage%27+and+%28armRegionName+eq+%27eastus%27+or+armRegionName+eq+%27%27+or+armRegionName+eq+%27global%27%29&currencyCode=%27USD%27&api-version=2023-01-01-preview | O13: 2026-10-19T20:20:48.622324+00:00
A14: P0011 | B14: Storage | C14: General Block Blob v2 | D14: Cool LRS | E14: Cool LRS Data Stored | F14: eastus | G14: Consumption | I14: 0.0152 | J14: 1 GB/Month | K14: 0 | L14: 2017-02-03T00:00:00Z | M14: 5d16be88-bfc0-4f33-bb0a-826eb941c13f | N14: https://prices.azure.com/api/retail/prices?%24filter=serviceName+eq+%27Storage%27+and+%28armRegionName+eq+%27eastus%27+or+armRegionName+eq+%27%27+or+armRegionName+eq+%27global%27%29&currencyCode=%27USD%27&api-version=2023-01-01-preview | O14: 2026-10-19T20:20:48.622324+00:00
A15: P0012 | B15: Storage | C15: General Block Blob v2 | D15: Cool GRS | E15: Cool GRS Data Stored | F15: eastus | G15: Consumption | I15: 0.0334 | J15: 1 GB/Month | K15: 0 | L15: 2017-02-03T00:00:00Z | M15: 5435d17e-896a-4d1f-aabc-8b74183f6e9e | N15: https://prices.azure.com/api/retail/prices?%24filter=serviceName+eq+%27Storage%27+and+%28armRegionName+eq+%27eastus%27+or+armRegionName+eq+%27%27+or+armRegionName+eq+%27global%27%29&currencyCode=%27USD%27&api-version=2023-01-01-preview | O15: 2026-10-19T20:20:48.622324+00:00
A16: P0013 | B16: Storage | C16: General Block Blob v2 | D16: Cool ZRS | E16: Cool ZRS Data Stored | F16: eastus | G16: Consumption | I16: 0.019 | J16: 1 GB/Month | K16: 0 | L16: 2018-07-01T00:00:00Z | M16: 2b8a2c33-5c54-412a-bbfd-fe4f34a952d5 | N16: https://prices.azure.com/api/retail/prices?%24filter=serviceName+eq+%27Storage%27+and+%28armRegionName+eq+%27eastus%27+or+armRegionName+eq+%27%27+or+armRegionName+eq+%27global%27%29&currencyCode=%27USD%27&api-version=2023-01-01-preview | O16: 2026-10-19T20:20:48.622324+00:00
A17: P0014 | B17: Storage | C17: General Block Blob v2 | D17: Cool RA-GRS | E17: Cool RA-GRS Data Stored | F17: eastus | G17: Consumption | I17: 0.0425 | J17: 1 GB/Month | K17: 0 | L17: 2016-11-01T00:00:00Z | M17: fff068af-d2b2-4ffc-895e-d2be686d9b39 | N17: https://prices.azure.com/api/retail/prices?%24filter=serviceName+eq+%27Storage%27+and+%28armRegionName+eq+%27eastus%27+or+armRegionName+eq+%27%27+or+armRegionName+eq+%27global%27%29&currencyCode=%27USD%27&api-version=2023-01-01-preview | O17: 2026-10-19T20:20:48.622324+00:00
A18: P0015 | B18: Storage | C18: General Block Blob v2 | D18: Hot LRS | E18: Hot LRS Write Operations | F18: eastus | G18: Consumption | I18: 0.05 | J18: 10K | K18: 0 | L18: 2016-11-01T00:00:00Z | M18: 14854f12-8d37-4299-842a-b0f2df82a305 | N18: https://prices.azure.com/api/retail/prices?%24filter=serviceName+eq+%27Storage%27+and+%28armRegionName+eq+%27eastus%27+or+armRegionName+eq+%27%27+or+armRegionName+eq+%27global%27%29&currencyCode=%27USD%27&api-version=2023-01-01-preview | O18: 2026-10-19T20:20:48.622324+00:00
... A48: P0045 | B48: Virtual Network | C48: Virtual Network Private Link | D48: Standard | E48: Standard Data Processed - Ingress | F48: Global | G48: Consumption | I48: 0.01 | J48: 1 GB | K48: 0 | L48: 2021-11-01T00:00:00Z | M48: 10caa28b-6479-4852-9eb7-610870cb6417 | N48: https://prices.azure.com/api/retail/prices?%24filter=serviceName+eq+%27Virtual+Network%27+and+armRegionName+eq+%27Global%27&currencyCode=%27USD%27 | O48: 2026-10-19T20:20:48.622324+00:00
A49: P0046 | B49: Azure DNS | C49: Azure DNS | D49: Private | E49: Private Zone | G49: Consumption | I49: 0.5 | J49: 1 | K49: 0 | L49: 2019-12-01T00:00:00Z | M49: 0b608a26-f611-4232-8192-ce81b6b57194 | N49: https://prices.azure.com/api/retail/prices?%24filter=serviceName+eq+%27Azure+DNS%27+and+%28armRegionName+eq+%27eastus%27+or+armRegionName+eq+%27%27+or+armRegionName+eq+%27global%27%29&currencyCode=%27USD%27&api-version=2023-01-01-preview | O49: 2026-10-19T20:20:48.622324+00:00
A50: P0047 | B50: Azure DNS | C50: Azure DNS | D50: Private | E50: Private Queries | G50: Consumption | I50: 0.4 | J50: 1M | K50: 0 | L50: 2019-12-01T00:00:00Z | M50: 46cff9cb-4b15-4af0-bf41-25143827fef8 | N50: https://prices.azure.com/api/retail/prices?%24filter=serviceName+eq+%27Azure+DNS%27+and+%28armRegionName+eq+%27eastus%27+or+armRegionName+eq+%27%27+or+armRegionName+eq+%27global%27%29&currencyCode=%27USD%27&api-version=2023-01-01-preview | O50: 2026-10-19T20:20:48.622324+00:00
A51: P0048 | B51: Azure DNS | C51: Azure DNS | D51: Public | E51: Public Zone | G51: Consumption | I51: 0.5 | J51: 1 | K51: 0 | L51: 2016-11-01T00:00:00Z | M51: 8f967c58-b144-4bd7-8882-8bf02767c839 | N51: https://prices.azure.com/api/retail/prices?%24filter=serviceName+eq+%27Azure+DNS%27+and+%28armRegionName+eq+%27eastus%27+or+armRegionName+eq+%27%27+or+armRegionName+eq+%27global%27%29&currencyCode=%27USD%27&api-version=2023-01-01-preview | O51: 2026-10-19T20:20:48.622324+00:00
A52: P0049 | B52: Azure DNS | C52: Azure DNS | D52: Public | E52: Public Queries | G52: Consumption | I52: 0.4 | J52: 1M | K52: 0 | L52: 2016-11-01T00:00:00Z | M52: d54686f0-77ff-43f3-9e7c-2099030d32a7 | N52: https://prices.azure.com/api/retail/prices?%24filter=serviceName+eq+%27Azure+DNS%27+and+%28armRegionName+eq+%27eastus%27+or+armRegionName+eq+%27%27+or+armRegionName+eq+%27global%27%29&currencyCode=%27USD%27&api-version=2023-01-01-preview | O52: 2026-10-19T20:20:48.622324+00:00
A53: P0050 | B53: Bandwidth | C53: Rtn Preference: MGN | D53: Standard | E53: Standard Data Transfer Out | F53: eastus | G53: Consumption | I53: 0.087 | J53: 1 GB | K53: 100 | L53: 2022-05-01T00:00:00Z | M53: 9995d93a-7d35-4d3f-9c69-7a7fea447ef4 | N53: https://prices.azure.com/api/retail/prices?%24filter=serviceName+eq+%27Bandwidth%27+and+%28armRegionName+eq+%27eastus%27+or+armRegionName+eq+%27%27+or+armRegionName+eq+%27global%27%29&currencyCode=%27USD%27&api-version=2023-01-01-preview | O53: 2026-10-19T20:20:48.622324+00:00
A54: P0051 | B54: Azure Firewall | C54: Azure Firewall | D54: Basic | E54: Basic Deployment | F54: eastus | G54: Consumption | I54: 0.395 | J54: 1 Hour | K54: 0 | L54: 2023-03-01T00:00:00Z | M54: 70c60dc4-0568-5d4e-839f-3c3345f46d55 | N54: https://prices.azure.com/api/retail/prices?%24filter=serviceName+eq+%27Azure+Firewall%27+and+%28armRegionName+eq+%27eastus%27+or+armRegionName+eq+%27%27+or+armRegionName+eq+%27global%27%29&currencyCode=%27USD%27&api-version=2023-01-01-preview | O54: 2026-10-19T20:20:48.622324+00:00
A55: P0052 | B55: Azure Firewall | C55: Azure Firewall | D55: Basic | E55: Basic Data Processed | F55: eastus | G55: Consumption | I55: 0.065 | J55: 1 GB | K55: 0 | L55: 2023-03-01T00:00:00Z | M55: ff9d9feb-e6a5-5070-98dd-864487cdf2a6 | N55: https://prices.azure.com/api/retail/prices?%24filter=serviceName+eq+%27Azure+Firewall%27+and+%28armRegionName+eq+%27eastus%27+or+armRegionName+eq+%27%27+or+armRegionName+eq+%27global%27%29&currencyCode=%27USD%27&api-version=2023-01-01-preview | O55: 2026-10-19T20:20:48.622324+00:00
A56: P0053 | B56: Azure Firewall | C56: Azure Firewall | D56: Standard | E56: Standard Deployment | F56: eastus | G56: Consumption | I56: 1.25 | J56: 1 Hour | K56: 0 | L56: 2018-11-01T00:00:00Z | M56: e90604a4-719b-454b-879d-b85523882c92 | N56: https://prices.azure.com/api/retail/prices?%24filter=serviceName+eq+%27Azure+Firewall%27+and+%28armRegionName+eq+%27eastus%27+or+armRegionName+eq+%27%27+or+armRegionName+eq+%27global%27%29&currencyCode=%27USD%27&api-version=2023-01-01-preview | O56: 2026-10-19T20:20:48.622324+00:00
A57: P0054 | B57: Azure Firewall | C57: Azure Firewall | D57: Standard | E57: Standard Data Processed | F57: eastus | G57: Consumption | I57: 0.016 | J57: 1 GB | K57: 0 | L57: 2019-05-01T00:00:00Z | M57: 5f492263-6ee9-488d-9b66-02332b889b03 | N57: https://prices.azure.com/api/retail/prices?%24filter=serviceName+eq+%27Azure+Firewall%27+and+%28armRegionName+eq+%27eastus%27+or+armRegionName+eq+%27%27+or+armRegionName+eq+%27global%27%29&currencyCode=%27USD%27&api-version=2023-01-01-preview | O57: 2026-10-19T20:20:48.622324+00:00
A58: P0055 | B58: Azure Firewall | C58: Azure Firewall | D58: Premium | E58: Premium Deployment | F58: eastus | G58: Consumption | I58: 1.75 | J58: 1 Hour | K58: 0 | L58: 2021-09-01T00:00:00Z | M58: 15bf80cd-28af-5664-9afd-fbf210165a80 | N58: https://prices.azure.com/api/retail/prices?%24filter=serviceName+eq+%27Azure+Firewall%27+and+%28armRegionName+eq+%27eastus%27+or+armRegionName+eq+%27%27+or+armRegionName+eq+%27global%27%29&currencyCode=%27USD%27&api-version=2023-01-01-preview | O58: 2026-10-19T20:20:48.622324+00:00
A59: P0056 | B59: Azure Firewall | C59: Azure Firewall | D59: Premium | E59: Premium Data Processed | F59: eastus | G59: Consumption | I59: 0.016 | J59: 1 GB | K59: 0 | L59: 2021-09-01T00:00:00Z | M59: a9d891ac-c48b-51f5-911d-e4392c508b6f | N59: https://prices.azure.com/api/retail/prices?%24filter=serviceName+eq+%27Azure+Firewall%27+and+%28armRegionName+eq+%27eastus%27+or+armRegionName+eq+%27%27+or+armRegionName+eq+%27global%27%29&currencyCode=%27USD%27&api-version=2023-01-01-preview | O59: 2026-10-19T20:20:48.622324+00:00
A60: P0057 | B60: Virtual Network | C60: IP Addresses | D60: Standard | E60: Standard IPv4 Static Public IP | F60: Global | G60: Consumption | I60: 0.005 | J60: 1 Hour | K60: 0 | L60: 2018-06-01T00:00:00Z | M60: 9c150bf9-2bad-430e-a53c-c213804f49ef | N60: https://prices.azure.com/api/retail/prices?%24filter=serviceName+eq+%27Virtual+Network%27+and+armRegionName+eq+%27Global%27&currencyCode=%27USD%27 | O60: 2026-10-19T20:20:48.622324+00:00
A61: P0058 | B61: VPN Gateway | C61: VPN Gateway | D61: VpnGw1 | E61: VpnGw1 | F61: eastus | G61: Consumption | I61: 0.19 | J61: 1 Hour | K61: 0 | L61: 2025-02-01T00:00:00Z | M61: 431b835b-2538-4faa-8763-8202f3fdbbb4 | N61: https://prices.azure.com/api/retail/prices?%24filter=serviceName+eq+%27VPN+Gateway%27+and+%28armRegionName+eq+%27eastus%27+or+armRegionName+eq+%27%27+or+armRegionName+eq+%27global%27%29&currencyCode=%27USD%27&api-version=2023-01-01-preview | O61: 2026-10-19T20:20:48.622324+00:00
A62: P0059 | B62: VPN Gateway | C62: VPN Gateway | D62: VpnGw2 | E62: VpnGw2 | F62: eastus | G62: Consumption | I62: 0.49 | J62: 1 Hour | K62: 0 | L62: 2025-02-01T00:00:00Z | M62: 907aacb3-4b68-4c57-9af2-3cf4505285b1 | N62: https://prices.azure.com/api/retail/prices?%24filter=serviceName+eq+%27VPN+Gateway%27+and+%28armRegionName+eq+%27eastus%27+or+armRegionName+eq+%27%27+or+armRegionName+eq+%27global%27%29&currencyCode=%27USD%27&api-version=2023-01-01-preview | O62: 2026-10-19T20:20:48.622324+00:00
A63: P0060 | B63: VPN Gateway | C63: VPN Gateway | D63: VpnGw3 | E63: VpnGw3 | F63: eastus | G63: Consumption | I63: 1.25 | J63: 1 Hour | K63: 0 | L63: 2025-02-01T00:00:00Z | M63: 5dc9b160-8b1f-4a9c-83ed-7e458511912d | N63: https://prices.azure.com/api/retail/prices?%24filter=serviceName+eq+%27VPN+Gateway%27+and+%28armRegionName+eq+%27eastus%27+or+armRegionName+eq+%27%27+or+armRegionName+eq+%27global%27%29&currencyCode=%27USD%27&api-version=2023-01-01-preview | O63: 2026-10-19T20:20:48.622324+00:00
A64: P0061 | B64: Virtual WAN | C64: Virtual WAN | D64: Routing Infrastructure Unit | E64: Routing Infrastructure Unit | F64: eastus | G64: Consumption | I64: 0.1 | J64: 1 Hour | K64: 0 | L64: 2021-07-01T00:00:00Z | M64: 4130b07a-39e2-5b19-83af-5c97e9a8d1d0 | N64: https://prices.azure.com/api/retail/prices?%24filter=serviceName+eq+%27Virtual+WAN%27+and+%28armRegionName+eq+%27eastus%27+or+armRegionName+eq+%27%27+or+armRegionName+eq+%27global%27%29&currencyCode=%27USD%27&api-version=2023-01-01-preview | O64: 2026-10-19T20:20:48.622324+00:00
... A80: P0077 | B80: Virtual Machines | C80: Virtual Machines Dsv5 Series | D80: Standard_D2s_v5 | E80: D2s v5 | F80: eastus | G80: Consumption | I80: 0.096 | J80: 1 Hour | K80: 0 | L80: 2021-11-01T00:00:00Z | M80: 36cc2454-47d7-517f-884f-be4d6b7efa55 | N80: https://prices.azure.com/api/retail/prices?%24filter=serviceName+eq+%27Virtual+Machines%27+and+%28armRegionName+eq+%27eastus%27+or+armRegionName+eq+%27%27+or+armRegionName+eq+%27global%27%29&currencyCode=%27USD%27&api-version=2023-01-01-preview | O80: 2026-10-19T20:20:48.622324+00:00
A81: P0078 | B81: Virtual Machines | C81: Virtual Machines Dsv5 Series | D81: Standard_D2s_v5 | E81: D2s v5 | F81: eastus | G81: Reservation | H81: 1 Year | I81: 519 | J81: 1 Hour | K81: 0 | L81: 2026-06-01T00:00:00Z | M81: 36cc2454-47d7-517f-884f-be4d6b7efa55 | N81: https://prices.azure.com/api/retail/prices?%24filter=serviceName+eq+%27Virtual+Machines%27+and+%28armRegionName+eq+%27eastus%27+or+armRegionName+eq+%27%27+or+armRegionName+eq+%27global%27%29&currencyCode=%27USD%27&api-version=2023-01-01-preview | O81: 2026-10-19T20:20:48.622324+00:00
A82: P0079 | B82: Virtual Machines | C82: Virtual Machines Dsv5 Series | D82: Standard_D2s_v5 | E82: D2s v5 | F82: eastus | G82: Reservation | H82: 3 Years | I82: 997 | J82: 1 Hour | K82: 0 | L82: 2026-06-01T00:00:00Z | M82: 36cc2454-47d7-517f-884f-be4d6b7efa55 | N82: https://prices.azure.com/api/retail/prices?%24filter=serviceName+eq+%27Virtual+Machines%27+and+%28armRegionName+eq+%27eastus%27+or+armRegionName+eq+%27%27+or+armRegionName+eq+%27global%27%29&currencyCode=%27USD%27&api-version=2023-01-01-preview | O82: 2026-10-19T20:20:48.622324+00:00
A83: P0080 | B83: Virtual Machines | C83: Virtual Machines Dsv5 Series | D83: Standard_D4s_v5 | E83: D4s v5 | F83: eastus | G83: Consumption | I83: 0.192 | J83: 1 Hour | K83: 0 | L83: 2021-11-01T00:00:00Z | M83: db8c0962-f3f8-5b44-99aa-f3c7c1e668c8 | N83: https://prices.azure.com/api/retail/prices?%24filter=serviceName+eq+%27Virtual+Machines%27+and+%28armRegionName+eq+%27eastus%27+or+armRegionName+eq+%27%27+or+armRegionName+eq+%27global%27%29&currencyCode=%27USD%27&api-version=2023-01-01-preview | O83: 2026-10-19T20:20:48.622324+00:00
A84: P0081 | B84: Virtual Machines | C84: Virtual Machines Dsv5 Series | D84: Standard_D4s_v5 | E84: D4s v5 | F84: eastus | G84: Reservation | H84: 1 Year | I84: 1038 | J84: 1 Hour | K84: 0 | L84: 2026-06-01T00:00:00Z | M84: db8c0962-f3f8-5b44-99aa-f3c7c1e668c8 | N84: https://prices.azure.com/api/retail/prices?%24filter=serviceName+eq+%27Virtual+Machines%27+and+%28armRegionName+eq+%27eastus%27+or+armRegionName+eq+%27%27+or+armRegionName+eq+%27global%27%29&currencyCode=%27USD%27&api-version=2023-01-01-preview | O84: 2026-10-19T20:20:48.622324+00:00
A85: P0082 | B85: Virtual Machines | C85: Virtual Machines Dsv5 Series | D85: Standard_D4s_v5 | E85: D4s v5 | F85: eastus | G85: Reservation | H85: 3 Years | I85: 1993 | J85: 1 Hour | K85: 0 | L85: 2026-06-01T00:00:00Z | M85: db8c0962-f3f8-5b44-99aa-f3c7c1e668c8 | N85: https://prices.azure.com/api/retail/prices?%24filter=serviceName+eq+%27Virtual+Machines%27+and+%28armRegionName+eq+%27eastus%27+or+armRegionName+eq+%27%27+or+armRegionName+eq+%27global%27%29&currencyCode=%27USD%27&api-version=2023-01-01-preview | O85: 2026-10-19T20:20:48.622324+00:00
A86: P0083 | B86: Virtual Machines | C86: Virtual Machines Dsv5 Series | D86: Standard_D8s_v5 | E86: D8s v5 | F86: eastus | G86: Consumption | I86: 0.384 | J86: 1 Hour | K86: 0 | L86: 2021-11-01T00:00:00Z | M86: 17a4cba9-d983-5344-a8ef-ac7c8e0d34af | N86: https://prices.azure.com/api/retail/prices?%24filter=serviceName+eq+%27Virtual+Machines%27+and+%28armRegionName+eq+%27eastus%27+or+armRegionName+eq+%27%27+or+armRegionName+eq+%27global%27%29&currencyCode=%27USD%27&api-version=2023-01-01-preview | O86: 2026-10-19T20:20:48.622324+00:00
A87: P0084 | B87: Virtual Machines | C87: Virtual Machines Dsv5 Series | D87: Standard_D8s_v5 | E87: D8s v5 | F87: eastus | G87: Reservation | H87: 1 Year | I87: 2075 | J87: 1 Hour | K87: 0 | L87: 2026-06-01T00:00:00Z | M87: 17a4cba9-d983-5344-a8ef-ac7c8e0d34af | N87: https://prices.azure.com/api/retail/prices?%24filter=serviceName+eq+%27Virtual+Machines%27+and+%28armRegionName+eq+%27eastus%27+or+armRegionName+eq+%27%27+or+armRegionName+eq+%27global%27%29&currencyCode=%27USD%27&api-version=2023-01-01-preview | O87: 2026-10-19T20:20:48.622324+00:00
A88: P0085 | B88: Virtual Machines | C88: Virtual Machines Dsv5 Series | D88: Standard_D8s_v5 | E88: D8s v5 | F88: eastus | G88: Reservation | H88: 3 Years | I88: 3986 | J88: 1 Hour | K88: 0 | L88: 2026-06-01T00:00:00Z | M88: 17a4cba9-d983-5344-a8ef-ac7c8e0d34af | N88: https://prices.azure.com/api/retail/prices?%24filter=serviceName+eq+%27Virtual+Machines%27+and+%28armRegionName+eq+%27eastus%27+or+armRegionName+eq+%27%27+or+armRegionName+eq+%27global%27%29&currencyCode=%27USD%27&api-version=2023-01-01-preview | O88: 2026-10-19T20:20:48.622324+00:00
A89: P0086 | B89: SQL Database | C89: SQL Database Single Standard | D89: S0 | E89: S0 DTUs | F89: eastus | G89: Consumption | I89: 0.4839 | J89: 1/Day | K89: 0 | L89: 2014-11-01T00:00:00Z | M89: a149966f-73b4-4e1d-b335-d2a572b1e6bd | N89: https://prices.azure.com/api/retail/prices?%24filter=serviceName+eq+%27SQL+Database%27+and+%28armRegionName+eq+%27eastus%27+or+armRegionName+eq+%27%27+or+armRegionName+eq+%27global%27%29&currencyCode=%27USD%27&api-version=2023-01-01-preview | O89: 2026-10-19T20:20:48.622324+00:00
A90: P0087 | B90: SQL Database | C90: SQL Database Single Standard | D90: S1 | E90: S1 DTUs | F90: eastus | G90: Consumption | I90: 0.9677 | J90: 1/Day | K90: 0 | L90: 2014-11-01T00:00:00Z | M90: 54c6bbf3-322b-406d-8411-101bc4b9443a | N90: https://prices.azure.com/api/retail/prices?%24filter=serviceName+eq+%27SQL+Database%27+and+%28armRegionName+eq+%27eastus%27+or+armRegionName+eq+%27%27+or+armRegionName+eq+%27global%27%29&currencyCode=%27USD%27&api-version=2023-01-01-preview | O90: 2026-10-19T20:20:48.622324+00:00
A91: P0088 | B91: SQL Database | C91: SQL Database Single Standard | D91: S2 | E91: S2 DTUs | F91: eastus | G91: Consumption | I91: 2.42 | J91: 1/Day | K91: 0 | L91: 2014-11-01T00:00:00Z | M91: f303a21a-05f1-4563-b2ad-7523eebc4058 | N91: https://prices.azure.com/api/retail/prices?%24filter=serviceName+eq+%27SQL+Database%27+and+%28armRegionName+eq+%27eastus%27+or+armRegionName+eq+%27%27+or+armRegionName+eq+%27global%27%29&currencyCode=%27USD%27&api-version=2023-01-01-preview | O91: 2026-10-19T20:20:48.622324+00:00
A92: P0089 | B92: SQL Managed Instance | C92: SQL Managed Instance General Purpose - Compute Gen5 | D92: vCore | E92: vCore | F92: eastus | G92: Consumption | I92: 0.152218 | J92: 1 Hour | K92: 0 | L92: 2025-06-01T00:00:00Z | M92: 3a627b99-de25-47fd-bd48-72dac0999188 | N92: https://prices.azure.com/api/retail/prices?%24filter=serviceName+eq+%27SQL+Managed+Instance%27+and+%28armRegionName+eq+%27eastus%27+or+armRegionName+eq+%27%27+or+armRegionName+eq+%27global%27%29&currencyCode=%27USD%27&api-version=2023-01-01-preview | O92: 2026-10-19T20:20:48.622324+00:00
A93: P0090 | B93: SQL Managed Instance | C93: SQL Managed Instance General Purpose - Compute Gen5 | D93: vCore | E93: vCore | F93: eastus | G93: Reservation | H93: 1 Year | I93: 867 | J93: 1 Hour | K93: 0 | L93: 2025-06-01T00:00:00Z | M93: 3a627b99-de25-47fd-bd48-72dac0999188 | N93: https://prices.azure.com/api/retail/prices?%24filter=serviceName+eq+%27SQL+Managed+Instance%27+and+%28armRegionName+eq+%27eastus%27+or+armRegionName+eq+%27%27+or+armRegionName+eq+%27global%27%29&currencyCode=%27USD%27&api-version=2023-01-01-preview | O93: 2026-10-19T20:20:48.622324+00:00
A94: P0091 | B94: SQL Managed Instance | C94: SQL Managed Instance General Purpose - Compute Gen5 | D94: vCore | E94: vCore | F94: eastus | G94: Reservation | H94: 3 Years | I94: 1800 | J94: 1 Hour | K94: 0 | L94: 2025-06-01T00:00:00Z | M94: 3a627b99-de25-47fd-bd48-72dac0999188 | N94: https://prices.azure.com/api/retail/prices?%24filter=serviceName+eq+%27SQL+Managed+Instance%27+and+%28armRegionName+eq+%27eastus%27+or+armRegionName+eq+%27%27+or+armRegionName+eq+%27global%27%29&currencyCode=%27USD%27&api-version=2023-01-01-preview | O94: 2026-10-19T20:20:48.622324+00:00
A95: P0092 | B95: Azure Database for PostgreSQL | C95: Azure Database for PostgreSQL Flexible Server General Purpose Dsv3 Series Compute | D95: vCore | E95: vCore | F95: eastus | G95: Consumption | I95: 0.0855 | J95: 1 Hour | K95: 0 | L95: 2025-07-01T00:00:00Z | M95: 5de28048-3f13-5d69-95ff-5e3287a1dba1 | N95: https://prices.azure.com/api/retail/prices?%24filter=serviceName+eq+%27Azure+Database+for+PostgreSQL%27+and+%28armRegionName+eq+%27eastus%27+or+armRegionName+eq+%27%27+or+armRegionName+eq+%27global%27%29&currencyCode=%27USD%27&api-version=2023-01-01-preview | O95: 2026-10-19T20:20:48.622324+00:00
A96: P0093 | B96: Azure Database for PostgreSQL | C96: Azure Database for PostgreSQL Flexible Server General Purpose Dsv3 Series Compute | D96: vCore | E96: vCore | F96: eastus | G96: Reservation | H96: 1 Year | I96: 449 | J96: 1 Hour | K96: 0 | L96: 2025-07-01T00:00:00Z | M96: 5de28048-3f13-5d69-95ff-5e3287a1dba1 | N96: https://prices.azure.com/api/retail/prices?%24filter=serviceName+eq+%27Azure+Database+for+PostgreSQL%27+and+%28armRegionName+eq+%27eastus%27+or+armRegionName+eq+%27%27+or+armRegionName+eq+%27global%27%29&currencyCode=%27USD%27&api-version=2023-01-01-preview | O96: 2026-10-19T20:20:48.622324+00:00
A97: P0094 | B97: Azure Database for PostgreSQL | C97: Azure Database for PostgreSQL Flexible Server General Purpose Dsv3 Series Compute | D97: vCore | E97: vCore | F97: eastus | G97: Reservation | H97: 3 Years | I97: 899 | J97: 1 Hour | K97: 0 | L97: 2025-07-01T00:00:00Z | M97: 5de28048-3f13-5d69-95ff-5e3287a1dba1 | N97: https://prices.azure.com/api/retail/prices?%24filter=serviceName+eq+%27Azure+Database+for+PostgreSQL%27+and+%28armRegionName+eq+%27eastus%27+or+armRegionName+eq+%27%27+or+armRegionName+eq+%27global%27%29&currencyCode=%27USD%27&api-version=2023-01-01-preview | O97: 2026-10-19T20:20:48.622324+00:00
A98: P0095 | B98: Azure Database for MySQL | C98: Azure Database for MySQL Flexible Server General Purpose Series Compute | D98: vCore | E98: vCore | F98: eastus | G98: Consumption | I98: 0.0855 | J98: 1 Hour | K98: 0 | L98: 2025-07-01T00:00:00Z | M98: 4afef323-21b3-5602-a359-2ba3cf898f95 | N98: https://prices.azure.com/api/retail/prices?%24filter=serviceName+eq+%27Azure+Database+for+MySQL%27+and+%28armRegionName+eq+%27eastus%27+or+armRegionName+eq+%27%27+or+armRegionName+eq+%27global%27%29&currencyCode=%27USD%27&api-version=2023-01-01-preview | O98: 2026-10-19T20:20:48.622324+00:00
A99: P0096 | B99: Azure Database for MySQL | C99: Azure Database for MySQL Flexible Server General Purpose Series Compute | D99: vCore | E99: vCore | F99: eastus | G99: Reservation | H99: 1 Year | I99: 449 | J99: 1 Hour | K99: 0 | L99: 2025-07-01T00:00:00Z | M99: 4afef323-21b3-5602-a359-2ba3cf898f95 | N99: https://prices.azure.com/api/retail/prices?%24filter=serviceName+eq+%27Azure+Database+for+MySQL%27+and+%28armRegionName+eq+%27eastus%27+or+armRegionName+eq+%27%27+or+armRegionName+eq+%27global%27%29&currencyCode=%27USD%27&api-version=2023-01-01-preview | O99: 2026-10-19T20:20:48.622324+00:00
A100: P0097 | B100: Azure Database for MySQL | C100: Azure Database for MySQL Flexible Server General Purpose Series Compute | D100: vCore | E100: vCore | F100: eastus | G100: Reservation | H100: 3 Years | I100: 899 | J100: 1 Hour | K100: 0 | L100: 2025-07-01T00:00:00Z | M100: 4afef323-21b3-5602-a359-2ba3cf898f95 | N100: https://prices.azure.com/api/retail/prices?%24filter=serviceName+eq+%27Azure+Database+for+MySQL%27+and+%28armRegionName+eq+%27eastus%27+or+armRegionName+eq+%27%27+or+armRegionName+eq+%27global%27%29&currencyCode=%27USD%27&api-version=2023-01-01-preview | O100: 2026-10-19T20:20:48.622324+00:00
A101: P0098 | B101: Azure Database for PostgreSQL | C101: Azure Database for PostgreSQL Flex Server Storage | D101: Storage | E101: Storage Data Stored | F101: eastus | G101: Consumption | I101: 0.115 | J101: 1 GB/Month | K101: 0 | L101: 2021-06-01T00:00:00Z | M101: 05116300-a5d3-5c8f-a80e-bc6bf8109556 | N101: https://prices.azure.com/api/retail/prices?%24filter=serviceName+eq+%27Azure+Database+for+PostgreSQL%27+and+%28armRegionName+eq+%27eastus%27+or+armRegionName+eq+%27%27+or+armRegionName+eq+%27global%27%29&currencyCode=%27USD%27&api-version=2023-01-01-preview | O101: 2026-10-19T20:20:48.622324+00:00
A102: P0099 | B102: Azure Database for MySQL | C102: Azure Database for MySQL Flexible Server Storage | D102: Storage | E102: Storage Data Stored | F102: eastus | G102: Consumption | I102: 0.115 | J102: 1 GB/Month | K102: 0 | L102: 2021-06-01T00:00:00Z | M102: 72be597c-31cf-528f-bede-85d568c7ef67 | N102: https://prices.azure.com/api/retail/prices?%24filter=serviceName+eq+%27Azure+Database+for+MySQL%27+and+%28armRegionName+eq+%27eastus%27+or+armRegionName+eq+%27%27+or+armRegionName+eq+%27global%27%29&currencyCode=%27USD%27&api-version=2023-01-01-preview | O102: 2026-10-19T20:20:48.622324+00:00
A103: P0100 | B103: SQL Managed Instance | C103: SQL Managed Instance General Purpose - Storage | D103: General Purpose | E103: General Purpose Data Stored | F103: eastus | G103: Consumption | I103: 0.115 | J103: 1 GB/Month | K103: 0 | L103: 2018-10-05T00:00:00Z | M103: 949523d1-a8c2-47c5-b324-1d66cc3964ce | N103: https://prices.azure.com/api/retail/prices?%24filter=serviceName+eq+%27SQL+Managed+Instance%27+and+%28armRegionName+eq+%27eastus%27+or+armRegionName+eq+%27%27+or+armRegionName+eq+%27global%27%29&currencyCode=%27USD%27&api-version=2023-01-01-preview | O103: 2026-10-19T20:20:48.622324+00:00
A104: P0101 | B104: Azure Cosmos DB | C104: Azure Cosmos DB | D104: RUs | E104: 100 RU/s | F104: eastus | G104: Consumption | I104: 0.008 | J104: 1/Hour | K104: 0 | L104: 2016-04-01T00:00:00Z | M104: 65d4ded2-41ae-43a8-bb68-3c200e1ba864 | N104: https://prices.azure.com/api/retail/prices?%24filter=serviceName+eq+%27Azure+Cosmos+DB%27+and+%28armRegionName+eq+%27eastus%27+or+armRegionName+eq+%27%27+or+armRegionName+eq+%27global%27%29&currencyCode=%27USD%27&api-version=2023-01-01-preview | O104: 2026-10-19T20:20:48.622324+00:00
A105: P0102 | B105: Redis Cache | C105: Azure Redis Cache Basic | D105: C0 | E105: C0 Cache | F105: eastus | G105: Consumption | I105: 0.022 | J105: 1 Hour | K105: 0 | L105: 2014-11-01T00:00:00Z | M105: c7107dc5-43b9-4d42-9ba8-161345a976a3 | N105: https://prices.azure.com/api/retail/prices?%24filter=serviceName+eq+%27Redis+Cache%27+and+%28armRegionName+eq+%27eastus%27+or+armRegionName+eq+%27%27+or+armRegionName+eq+%27global%27%29&currencyCode=%27USD%27&api-version=2023-01-01-preview | O105: 2026-10-19T20:20:48.622324+00:00
A106: P0103 | B106: Redis Cache | C106: Azure Redis Cache Standard | D106: C1 | E106: C1 Cache | F106: eastus | G106: Consumption | I106: 0.138 | J106: 1 Hour | K106: 0 | L106: 2014-11-01T00:00:00Z | M106: 37c8dbd7-412b-4892-a31a-915b96a66885 | N106: https://prices.azure.com/api/retail/prices?%24filter=serviceName+eq+%27Redis+Cache%27+and+%28armRegionName+eq+%27eastus%27+or+armRegionName+eq+%27%27+or+armRegionName+eq+%27global%27%29&currencyCode=%27USD%27&api-version=2023-01-01-preview | O106: 2026-10-19T20:20:48.622324+00:00
A107: P0104 | B107: Microsoft Purview | C107: Microsoft Purview Data Governance | D107: Data Catalog Standard | E107: Data Catalog Standard Asset | F107: eastus | G107: Consumption | I107: 0.0165 | J107: 1/Day | K107: 0 | L107: 2024-11-01T00:00:00Z | M107: 31e14497-95e2-5af1-9ff4-346342d03e28 | N107: https://prices.azure.com/api/retail/prices?%24filter=serviceName+eq+%27Microsoft+Purview%27+and+%28armRegionName+eq+%27eastus%27+or+armRegionName+eq+%27%27+or+armRegionName+eq+%27global%27%29&currencyCode=%27USD%27&api-version=2023-01-01-preview | O107: 2026-10-19T20:20:48.622324+00:00
A108: P0105 | B108: Microsoft Purview | C108: Microsoft Purview Data Governance | D108: Data Management Basic | E108: Data Management Basic Data Governance Processing Unit | F108: eastus | G108: Consumption | I108: 15 | J108: 1 | K108: 0 | L108: 2024-11-01T00:00:00Z | M108: 0b068e02-e364-5fc1-830c-6524db51407a | N108: https://prices.azure.com/api/retail/prices?%24filter=serviceName+eq+%27Microsoft+Purview%27+and+%28armRegionName+eq+%27eastus%27+or+armRegionName+eq+%27%27+or+armRegionName+eq+%27global%27%29&currencyCode=%27USD%27&api-version=2023-01-01-preview | O108: 2026-10-19T20:20:48.622324+00:00
A109: P0106 | B109: Foundry Tools | C109: Azure Video Indexer | D109: Standard Video Indexing Analysis | E109: Standard Video Indexing Analysis Input Content Minutes | F109: eastus | G109: Consumption | I109: 0.09 | J109: 1 | K109: 0 | L109: 2023-02-01T00:00:00Z | M109: bd41dacc-1a62-5c33-9619-090fc799c91b | N109: https://prices.azure.com/api/retail/prices?%24filter=%28contains%28productName%2C%27Private+Link%27%29+or+contains%28productName%2C%27DDoS%27%29+or+contains%28productName%2C%27Load+Testing%27%29+or+contains%28productName%2C%27Video+Indexer%27%29%29+and+%28armRegionName+eq+%27eastus%27+or+armRegionName+eq+%27%27+or+armRegionName+eq+%27global%27%29&currencyCode=%27USD%27 | O109: 2026-10-19T20:20:48.622324+00:00

Sheet YAML Inventory
A1: Complete configuration inventory | all targets
A3: Scenario | B3: Target | C3: Type / section | D3: Resource / setting | E3: Configured SKU | F3: YAML path | G3: Source file | H3: Effective properties (truncated) | I3: BOM sheet | J3: Treatment
A4: Base udp.yml | B4: prod | C4: tenant_settings | D4: PublishToWeb | F4: admin.tenant_settings.PublishToWeb | G4: scripts\udp.yml | H4: {"enabled": false} | I4: Base udp.yml | J4: No direct settings fee
A5: Base udp.yml | B5: prod | C5: tenant_settings | D5: DevelopmentTenantSettings | F5: admin.tenant_settings.DevelopmentTenantSettings | G5: scripts\udp.yml | H5: {"enabled": true, "enabled_security_groups": [{"graph_id": "${var.data_eng_group_id}", "name": "Data Engineers"}], "excluded_security_groups": [{"graph_id": "${var.contractors_group_id}", "name": "Contractors"}]} | I5: Base udp.yml | J5: No direct settings fee
A6: Base udp.yml | B6: prod | C6: tenant_settings | D6: UsageMetricsSettings | F6: admin.tenant_settings.UsageMetricsSettings | G6: scripts\udp.yml | H6: {"enabled": true, "delegate_to_capacity": true, "delegate_to_domain": false, "delegate_to_workspace": true, "enabled_security_groups": [{"graph_id": "${var.bi_admins_group_id}", "name": "BI Admins"}]} | I6: Base udp.yml | J6: No direct settings fee
A7: Base udp.yml | B7: prod | C7: tenant_settings | D7: ExportToCsvSettings | F7: admin.tenant_settings.ExportToCsvSettings | G7: scripts\udp.yml | H7: {"enabled": true, "delegate_to_workspace": true, "properties": [{"name": "WatermarkText", "value": "Internal use only", "type": "FreeText"}, {"name": "PolicyUrl", "value": "https://contoso.com/data-policy", "type": "Url"}, {"name": "RequireApproval", "value": "true", "type": "Boolean"}, {"name": "ApproversGroup", "value": "${var.bi_admins_group_id}", "type": "MailEnabledSecurityGroup"}, {"name": "MaxRows", "value": "1000000", "type": "Integer"}]} | I7: Base udp.yml | J7: No direct settings fee
A8: BOM 00-default | B8: dev | C8: environments | D8: spark_env | F8: resources.environments.spark_env | G8: examples\00-default\udp.yml | H8: {"conda_dependencies": ["numpy=1.26"], "description": "Shared Spark runtime 1.3 with libraries", "libraries": ["semantic-link-labs", "great-expectations>=0.18.0", "delta-spark>=3.0"], "runtime": "1.3", "spark_properties": {"spark.databricks.delta.autoCompact.enabled": "true", "spark.sql.shuffle.partitions": "200"}} | I8: BOM 00-default | J8: See BOM
A9: BOM 00-default | B9: dev | C9: environments | D9: spark_env_legacy | F9: resources.environments.spark_env_legacy | G9: examples\00-default\udp.yml | H9: {"description": "Spark runtime 1.2 (the other supported runtime)", "libraries": ["azure-storage-blob"], "runtime": "1.2"} | I9: BOM 00-default | J9: See BOM
A10: BOM 00-default | B10: dev | C10: lakehouses | D10: raw_lakehouse | F10: resources.lakehouses.raw_lakehouse | G10: examples\00-default\udp.yml | H10: {"description": "Raw landing zone with every shortcut flavour", "enable_schemas": true, "schemas": ["./schemas/raw.json"], "shortcuts": [{"connection_id": "${var.adls_connection_id}", "name": "external_sales", "path": "Files", "target": "adls://stdatalakedev01.dfs.core.windows.net/sales/daily/*.csv", "transformation": {"destination_table": "raw_sales", "source_format": "csv", "sync": true, "type": "file"}}, {"connection_id": "${var.adls_connection_id}", "name": "api_events", "path": "Files", "target": "adls://stdatalakedev01.dfs.core.windows.net/events/*.json.gz", "transformation": {"compression": "gzip", "destination_table": "raw_events", "flatten": true, "source_format": "json", "sync": true, "type": "file"}}, {"name": "partner_products", "path": "Files", "target": "s3://partner-bucket/shared/products/", "transformation": {"destination_table": "partner_products", "source_format": "parquet", "type": "file"}}, {"connection_id": "${var.adls_connection_id}", "name": "finance_reports", "path": "Files", "target": "adls://stdatalakedev01.dfs.core.windows.net/finance/monthly/*.xlsx", "transformation": {"destination_table": "finance_monthly", "source_format": "excel", "type": "file"}}, {"name": "azure_sales_tables", "path": "Tables", "target": "adls://stdatalakedev01.dfs.core.windows.net/sales/tables"}, {"name": "partner_feed", "path": "Files", "target": "s3://partner-data-bucket/daily-feed"}, {"name": "shared_dimensions", "path": "Tables", "target": "onelake://00000000-0000-0000-0000-000000000001/00000000-0000-0000-0000-000000000002/Tables/dim_customer"}], "sql_endpoint_enabled": true} | I10: BOM 00-default | J10: See BOM
A11: BOM 00-default | B11: dev | C11: lakehouses | D11: curated_lakehouse | F11: resources.lakehouses.curated_lakehouse | G11: examples\00-default\udp.yml | H11: {"description": "Curated, business-ready datasets", "tables": {"customers": {"description": "Customer dimension"}, "sales": {"description": "Curated sales fact table", "partition_by": ["order_date"], "schema_path": "./schemas/sales.json"}}} | I11: BOM 00-default | J11: See BOM
A12: BOM 00-default | B12: dev | C12: lakehouses | D12: ai_lakehouse | F12: resources.lakehouses.ai_lakehouse | G12: examples\00-default\udp.yml | H12: {"description": "Unstructured data processed by AI shortcut transformations", "shortcuts": [{"connection_id": "${var.adls_connection_id}", "name": "support_tickets", "path": "Files", "target": "adls://stdatalakedev01.dfs.core.windows.net/support/tickets/*.json", "transformation": {"ai_model": "gpt-4o", "ai_skill": "summarize", "destination_table": "ticket_summaries", "type": "ai"}}, {"connection_id": "${var.adls_connection_id}", "name": "global_feedback", "path": "Files", "target": "adls://stdatalakedev01.dfs.core.windows.net/feedback/*.json", "transformation": {"ai_prompt": "Translate to English, preserve sentiment", "ai_skill": "translate", "destination_table": "feedback_english", "type": "ai"}}, {"connection_id": "${var.adls_connection_id}", "name": "customer_emails", "path": "Files", "target": "adls://stdatalakedev01.dfs.core.windows.net/emails/inbox/*.json", "transformation": {"ai_prompt": "Classify as: complaint, inquiry, feedback, urgent, spam", "ai_skill": "classify", "destination_table": "classified_emails", "type": "ai"}}]} | I12: BOM 00-default | J12: See BOM
A13: BOM 00-default | B13: dev | C13: lakehouses | D13: telemetry_lakehouse | F13: resources.lakehouses.telemetry_lakehouse | G13: examples\00-default\udp.yml | H13: {"description": "Device telemetry (schemas and SQL endpoint explicitly disabled)", "enable_schemas": false, "sql_endpoint_enabled": false} | I13: BOM 00-default | J13: See BOM
A14: BOM 00-default | B14: dev | C14: notebooks | D14: ingest_notebook | F14: resources.notebooks.ingest_notebook | G14: examples\00-default\udp.yml | H14: {"default_lakehouse": "raw_lakehouse", "description": "Ingest raw data into the lakehouse", "environment": "spark_env", "folder": "ETL/Bronze", "parameters": {"batch_size": 1000, "full_refresh": false, "source_path": "Files/landing"}, "path": "./notebooks/ingest.py", "spark_properties": {"spark.sql.shuffle.partitions": "400"}} | I14: BOM 00-default | J14: See BOM
A15: BOM 00-default | B15: dev | C15: notebooks | D15: transform_notebook | F15: resources.notebooks.transform_notebook | G15: examples\00-default\udp.yml | H15: {"default_lakehouse": "curated_lakehouse", "description": "Transform raw data into curated tables", "environment": "spark_env", "folder": "ETL/Gold", "path": "./notebooks/transform.py"} | I15: BOM 00-default | J15: See BOM
... A85: BOM 00-default | B85: dev | C85: azure_resource_groups | D85: rg-ai | F85: resources.azure_resource_groups.rg-ai | G85: examples\00-default\udp.yml | H85: {"location": "eastus2", "tags": {"env": "${var.environment}", "workload": "ai"}} | I85: BOM 00-default | J85: See BOM
A86: BOM 00-default | B86: dev | C86: azure_storage_accounts | D86: stdataplatformdev01 | E86: Standard_GRS | F86: resources.azure_storage_accounts.stdataplatformdev01 | G86: examples\00-default\udp.yml | H86: {"access_tier": "Cool", "https_only": true, "kind": "StorageV2", "location": "eastus", "resource_group": "rg-data-platform", "sku": "Standard_GRS", "subscription": "${var.subscription_id}", "tags": {"env": "${var.environment}", "tier": "archive"}} | I86: BOM 00-default | J86: See BOM
A87: BOM 00-default | B87: dev | C87: azure_deployments | D87: purview-governance | F87: resources.azure_deployments.purview-governance | G87: examples\00-default\udp.yml | H87: {"location": "eastus", "parameters": {"logAnalyticsWorkspaceId": "/subscriptions/${var.subscription_id}/resourceGroups/rg-observability/providers/Microsoft.OperationalInsights/workspaces/law-analytics", "purviewAccountName": "purview-analytics"}, "resource_group": "rg-governance", "scope": "group", "template_file": "./bicep/purview-governance.bicep"} | I87: BOM 00-default | J87: See BOM
A88: BOM 00-default | B88: dev | C88: azure_deployments | D88: subscription-policy-baseline | F88: resources.azure_deployments.subscription-policy-baseline | G88: examples\00-default\udp.yml | H88: {"location": "eastus", "parameters": {"enableDefender": false, "requiredTagName": "data-owner"}, "scope": "subscription", "subscription": "${var.subscription_id}", "template_file": "./bicep/policy-baseline.bicep"} | I88: BOM 00-default | J88: See BOM
A89: BOM 00-default | B89: dev | C89: azure_data_factories | D89: adf-analytics | F89: resources.azure_data_factories.adf-analytics | G89: examples\00-default\udp.yml | H89: {"properties": {"publicNetworkAccess": "Enabled"}, "resource_group": "rg-data-platform"} | I89: BOM 00-default | J89: See BOM
A90: BOM 00-default | B90: dev | C90: azure_databricks_workspaces | D90: dbw-analytics | E90: premium | F90: resources.azure_databricks_workspaces.dbw-analytics | G90: examples\00-default\udp.yml | H90: {"properties": {"managedResourceGroupId": "/subscriptions/${var.subscription_id}/resourceGroups/rg-dbw-analytics-managed", "publicNetworkAccess": "Enabled", "requiredNsgRules": "AllRules"}, "resource_group": "rg-data-platform", "sku": "premium"} | I90: BOM 00-default | J90: See BOM
A91: BOM 00-default | B91: dev | C91: azure_databricks_structured_streaming | D91: dbw-streaming | E91: premium | F91: resources.azure_databricks_structured_streaming.dbw-streaming | G91: examples\00-default\udp.yml | H91: {"properties": {"managedResourceGroupId": "/subscriptions/${var.subscription_id}/resourceGroups/rg-dbw-streaming-managed"}, "resource_group": "rg-data-platform", "sku": "premium"} | I91: BOM 00-default | J91: See BOM
A92: BOM 00-default | B92: dev | C92: azure_event_hub_namespaces | D92: ehns-analytics | E92: Standard | F92: resources.azure_event_hub_namespaces.ehns-analytics | G92: examples\00-default\udp.yml | H92: {"properties": {"disableLocalAuth": true, "isAutoInflateEnabled": true, "maximumThroughputUnits": 4}, "resource_group": "rg-data-platform", "sku": "Standard"} | I92: BOM 00-default | J92: See BOM
A93: BOM 00-default | B93: dev | C93: azure_event_grid_topics | D93: egt-analytics | F93: resources.azure_event_grid_topics.egt-analytics | G93: examples\00-default\udp.yml | H93: {"properties": {"disableLocalAuth": true, "inputSchema": "CloudEventSchemaV1_0", "publicNetworkAccess": "Enabled"}, "resource_group": "rg-data-platform"} | I93: BOM 00-default | J93: See BOM
A94: BOM 00-default | B94: dev | C94: azure_stream_analytics_jobs | D94: asa-analytics | E94: {"name": "Standard"} | F94: resources.azure_stream_analytics_jobs.asa-analytics | G94: examples\00-default\udp.yml | H94: {"properties": {"dataLocale": "en-US", "eventsLateArrivalMaxDelayInSeconds": 5, "eventsOutOfOrderMaxDelayInSeconds": 0, "eventsOutOfOrderPolicy": "Adjust", "jobType": "Cloud", "outputErrorPolicy": "Stop", "sku": {"name": "Standard"}}, "resource_group": "rg-data-platform"} | I94: BOM 00-default | J94: See BOM
A95: BOM 00-default | B95: dev | C95: azure_iot_hubs | D95: iot-analytics-hub | E95: S1 | F95: resources.azure_iot_hubs.iot-analytics-hub | G95: examples\00-default\udp.yml | H95: {"properties": {"publicNetworkAccess": "Enabled"}, "resource_group": "rg-data-platform", "sku": "S1"} | I95: BOM 00-default | J95: See BOM
A96: BOM 00-default | B96: dev | C96: azure_logic_apps | D96: la-analytics | F96: resources.azure_logic_apps.la-analytics | G96: examples\00-default\udp.yml | H96: {"properties": {"definition": {"$schema": "https://schema.management.azure.com/providers/Microsoft.Logic/schemas/2016-06-01/workflowdefinition.json#", "actions": {}, "contentVersion": "1.0.0.0", "triggers": {}}, "state": "Enabled"}, "resource_group": "rg-data-platform"} | I96: BOM 00-default | J96: See BOM
A97: BOM 00-default | B97: dev | C97: azure_functions | D97: func-analytics | F97: resources.azure_functions.func-analytics | G97: examples\00-default\udp.yml | H97: {"kind": "functionapp", "properties": {"httpsOnly": true, "publicNetworkAccess": "Enabled"}, "resource_group": "rg-data-platform"} | I97: BOM 00-default | J97: See BOM
A98: BOM 00-default | B98: dev | C98: azure_blob_storage | D98: stblobanalytics01 | E98: Standard_LRS | F98: resources.azure_blob_storage.stblobanalytics01 | G98: examples\00-default\udp.yml | H98: {"kind": "StorageV2", "properties": {"allowBlobPublicAccess": false, "minimumTlsVersion": "TLS1_2", "supportsHttpsTrafficOnly": true}, "resource_group": "rg-data-platform", "sku": "Standard_LRS"} | I98: BOM 00-default | J98: See BOM
A99: BOM 00-default | B99: dev | C99: azure_data_lake_storage | D99: stadlsanalytics01 | E99: Standard_LRS | F99: resources.azure_data_lake_storage.stadlsanalytics01 | G99: examples\00-default\udp.yml | H99: {"kind": "StorageV2", "properties": {"allowBlobPublicAccess": false, "isHnsEnabled": true}, "resource_group": "rg-data-platform", "sku": "Standard_LRS"} | I99: BOM 00-default | J99: See BOM
A100: BOM 00-default | B100: dev | C100: azure_files | D100: stfilesanalytics01 | E100: Premium_LRS | F100: resources.azure_files.stfilesanalytics01 | G100: examples\00-default\udp.yml | H100: {"kind": "FileStorage", "resource_group": "rg-data-platform", "sku": "Premium_LRS"} | I100: BOM 00-default | J100: See BOM
A101: BOM 00-default | B101: dev | C101: azure_queue_storage | D101: stqueueanalytics01 | E101: Standard_LRS | F101: resources.azure_queue_storage.stqueueanalytics01 | G101: examples\00-default\udp.yml | H101: {"kind": "StorageV2", "resource_group": "rg-data-platform", "sku": "Standard_LRS"} | I101: BOM 00-default | J101: See BOM
A102: BOM 00-default | B102: dev | C102: azure_table_storage | D102: sttableanalytics01 | E102: Standard_LRS | F102: resources.azure_table_storage.sttableanalytics01 | G102: examples\00-default\udp.yml | H102: {"kind": "StorageV2", "resource_group": "rg-data-platform", "sku": "Standard_LRS"} | I102: BOM 00-default | J102: See BOM
A103: BOM 00-default | B103: dev | C103: azure_sql_databases | D103: sql-analytics-server/sqldb-analytics | E103: S0 | F103: resources.azure_sql_databases.sql-analytics-server/sqldb-analytics | G103: examples\00-default\udp.yml | H103: {"properties": {"collation": "SQL_Latin1_General_CP1_CI_AS", "zoneRedundant": false}, "resource_group": "rg-data-platform", "sku": "S0"} | I103: BOM 00-default | J103: See BOM
A104: BOM 00-default | B104: dev | C104: azure_sql_managed_instances | D104: sqlmi-analytics | E104: GP_Gen5 | F104: resources.azure_sql_managed_instances.sqlmi-analytics | G104: examples\00-default\udp.yml | H104: {"properties": {"licenseType": "LicenseIncluded", "storageSizeInGB": 32, "vCores": 4}, "resource_group": "rg-data-platform", "sku": "GP_Gen5"} | I104: BOM 00-default | J104: See BOM
A105: BOM 00-default | B105: dev | C105: azure_sql_virtual_machines | D105: sqlvm-analytics | F105: resources.azure_sql_virtual_machines.sqlvm-analytics | G105: examples\00-default\udp.yml | H105: {"properties": {"sqlManagement": "Full", "sqlServerLicenseType": "PAYG"}, "resource_group": "rg-data-platform"} | I105: BOM 00-default | J105: See BOM
A106: BOM 00-default | B106: dev | C106: azure_postgresql | D106: pg-analytics | E106: Standard_D2s_v3 | F106: resources.azure_postgresql.pg-analytics | G106: examples\00-default\udp.yml | H106: {"properties": {"authConfig": {"activeDirectoryAuth": "Enabled", "passwordAuth": "Disabled"}, "highAvailability": {"mode": "Disabled"}, "storage": {"storageSizeGB": 32}}, "resource_group": "rg-data-platform", "sku": "Standard_D2s_v3"} | I106: BOM 00-default | J106: See BOM
A107: BOM 00-default | B107: dev | C107: azure_mysql | D107: mysql-analytics | E107: Standard_D2ds_v4 | F107: resources.azure_mysql.mysql-analytics | G107: examples\00-default\udp.yml | H107: {"properties": {"highAvailability": {"mode": "Disabled"}, "storage": {"storageSizeGB": 32}}, "resource_group": "rg-data-platform", "sku": "Standard_D2ds_v4"} | I107: BOM 00-default | J107: See BOM
A108: BOM 00-default | B108: dev | C108: azure_mariadb | D108: mariadb-analytics | E108: GP_Gen5_2 | F108: resources.azure_mariadb.mariadb-analytics | G108: examples\00-default\udp.yml | H108: {"properties": {"minimalTlsVersion": "TLS1_2", "sslEnforcement": "Enabled"}, "resource_group": "rg-data-platform", "sku": "GP_Gen5_2"} | I108: BOM 00-default | J108: See BOM
A109: BOM 00-default | B109: dev | C109: azure_cosmosdb_accounts | D109: cosmos-analytics | F109: resources.azure_cosmosdb_accounts.cosmos-analytics | G109: examples\00-default\udp.yml | H109: {"kind": "GlobalDocumentDB", "properties": {"consistencyPolicy": {"defaultConsistencyLevel": "Session"}, "databaseAccountOfferType": "Standard", "disableLocalAuth": true, "locations": [{"failoverPriority": 0, "locationName": "eastus"}], "publicNetworkAccess": "Enabled"}, "resource_group": "rg-data-platform"} | I109: BOM 00-default | J109: See BOM
A110: BOM 00-default | B110: dev | C110: azure_redis_cache | D110: redis-analytics | E110: {"capacity": 1, "family": "C", "name": "Standard"} | F110: resources.azure_redis_cache.redis-analytics | G110: examples\00-default\udp.yml | H110: {"properties": {"enableNonSslPort": false, "sku": {"capacity": 1, "family": "C", "name": "Standard"}}, "resource_group": "rg-data-platform"} | I110: BOM 00-default | J110: See BOM
A111: BOM 00-default | B111: dev | C111: azure_data_box | D111: databox-analytics-job | E111: DataBox | F111: resources.azure_data_box.databox-analytics-job | G111: examples\00-default\udp.yml | H111: {"properties": {"transferType": "ImportToAzure"}, "resource_group": "rg-data-platform", "sku": "DataBox"} | I111: BOM 00-default | J111: See BOM
A112: BOM 00-default | B112: dev | C112: azure_purview_accounts | D112: purview-analytics | F112: resources.azure_purview_accounts.purview-analytics | G112: examples\00-default\udp.yml | H112: {"properties": {"managedEventHubState": "Enabled", "managedResourceGroupName": "rg-purview-analytics-managed", "managedResourcesPublicNetworkAccess": "Disabled", "publicNetworkAccess": "Disabled"}, "resource_group": "rg-governance", "tags": {"data-owner": "data-platform-team", "env": "${var.environment}", "workload": "governance"}} | I112: BOM 00-default | J112: See BOM
A113: BOM 00-default | B113: dev | C113: azure_key_vaults | D113: kv-governance | E113: {"family": "A", "name": "standard"} | F113: resources.azure_key_vaults.kv-governance | G113: examples\00-default\udp.yml | H113: {"properties": {"enablePurgeProtection": true, "enableRbacAuthorization": true, "enableSoftDelete": true, "networkAcls": {"bypass": "AzureServices", "defaultAction": "Deny"}, "publicNetworkAccess": "Disabled", "sku": {"family": "A", "name": "standard"}, "softDeleteRetentionInDays": 90, "tenantId": "${var.tenant_id}"}, "resource_group": "rg-governance"} | I113: BOM 00-default | J113: See BOM
A114: BOM 00-default | B114: dev | C114: azure_policy_assignments | D114: require-data-owner-tag | F114: resources.azure_policy_assignments.require-data-owner-tag | G114: examples\00-default\udp.yml | H114: {"properties": {"displayName": "Require a data-owner tag on resources", "enforcementMode": "DoNotEnforce", "parameters": {"tagName": {"value": "data-owner"}}, "policyDefinitionId": "/providers/Microsoft.Authorization/policyDefinitions/871b6d14-10aa-478d-b590-94f262ecfa99"}, "resource_group": "rg-data-platform"} | I114: BOM 00-default | J114: See BOM
A115: BOM 00-default | B115: dev | C115: azure_defender_plans | D115: VirtualMachines | F115: resources.azure_defender_plans.VirtualMachines | G115: examples\00-default\udp.yml | H115: {"properties": {"pricingTier": "Standard", "subPlan": "P2"}, "resource_group": "rg-governance"} | I115: BOM 00-default | J115: See BOM
A116: BOM 00-default | B116: dev | C116: azure_machine_learning_workspaces | D116: mlw-analytics | F116: resources.azure_machine_learning_workspaces.mlw-analytics | G116: examples\00-default\udp.yml | H116: {"kind": "Default", "properties": {"friendlyName": "Analytics ML workspace", "publicNetworkAccess": "Disabled"}, "resource_group": "rg-ai"} | I116: BOM 00-default | J116: See BOM
A117: BOM 00-default | B117: dev | C117: azure_ai_foundry | D117: foundry-hub | F117: resources.azure_ai_foundry.foundry-hub | G117: examples\00-default\udp.yml | H117: {"kind": "Hub", "properties": {"friendlyName": "Analytics AI Foundry hub", "publicNetworkAccess": "Disabled"}, "resource_group": "rg-ai"} | I117: BOM 00-default | J117: See BOM
A118: BOM 00-default | B118: dev | C118: azure_ai_foundry | D118: foundry-project | F118: resources.azure_ai_foundry.foundry-project | G118: examples\00-default\udp.yml | H118: {"kind": "Project", "properties": {"friendlyName": "Analytics AI Foundry project"}, "resource_group": "rg-ai"} | I118: BOM 00-default | J118: See BOM
A119: BOM 00-default | B119: dev | C119: azure_sentinel | D119: sentinel-onboard | F119: resources.azure_sentinel.sentinel-onboard | G119: examples\00-default\udp.yml | H119: {"resource_group": "rg-observability"} | I119: BOM 00-default | J119: See BOM
A120: BOM 00-default | B120: dev | C120: azure_video_indexer | D120: vi-analytics | F120: resources.azure_video_indexer.vi-analytics | G120: examples\00-default\udp.yml | H120: {"resource_group": "rg-ai"} | I120: BOM 00-default | J120: See BOM
A121: BOM 00-default | B121: dev | C121: azure_openai | D121: aoai-analytics | E121: S0 | F121: resources.azure_openai.aoai-analytics | G121: examples\00-default\udp.yml | H121: {"kind": "OpenAI", "location": "eastus2", "properties": {"customSubDomainName": "aoai-analytics-default", "disableLocalAuth": true, "publicNetworkAccess": "Enabled"}, "resource_group": "rg-ai", "sku": "S0", "subscription": "${var.subscription_id}", "tags": {"env": "${var.environment}", "workload": "ai"}} | I121: BOM 00-default | J121: See BOM
A122: BOM 00-default | B122: dev | C122: azure_load_testing | D122: lt-analytics | F122: resources.azure_load_testing.lt-analytics | G122: examples\00-default\udp.yml | H122: {"properties": {"description": "Load tests for the analytics APIs"}, "resource_group": "rg-observability"} | I122: BOM 00-default | J122: See BOM
A123: BOM 00-default | B123: dev | C123: azure_agent_ids | D123: agent-ingest | F123: resources.azure_agent_ids.agent-ingest | G123: examples\00-default\udp.yml | H123: {"resource_group": "rg-ai"} | I123: BOM 00-default | J123: See BOM
A124: BOM 00-default | B124: dev | C124: azure_service_groups | D124: sg-platform | F124: resources.azure_service_groups.sg-platform | G124: examples\00-default\udp.yml | H124: {"resource_group": "rg-governance"} | I124: BOM 00-default | J124: See BOM
A125: BOM 00-default | B125: dev | C125: azure_log_analytics_workspaces | D125: law-analytics | E125: {"name": "PerGB2018"} | F125: resources.azure_log_analytics_workspaces.law-analytics | G125: examples\00-default\udp.yml | H125: {"properties": {"publicNetworkAccessForIngestion": "Enabled", "publicNetworkAccessForQuery": "Enabled", "retentionInDays": 90, "sku": {"name": "PerGB2018"}}, "resource_group": "rg-observability"} | I125: BOM 00-default | J125: See BOM
A126: BOM 00-default | B126: dev | C126: azure_monitor_components | D126: appi-analytics | F126: resources.azure_monitor_components.appi-analytics | G126: examples\00-default\udp.yml | H126: {"kind": "web", "properties": {"Application_Type": "web", "Flow_Type": "Bluefield", "IngestionMode": "LogAnalytics", "RetentionInDays": 90, "WorkspaceResourceId": "/subscriptions/${var.subscription_id}/resourceGroups/rg-observability/providers/Microsoft.OperationalInsights/workspaces/law-analytics"}, "resource_group": "rg-observability"} | I126: BOM 00-default | J126: See BOM
A127: BOM 00-default | B127: dev | C127: azure_alerts | D127: alert-high-cpu | F127: resources.azure_alerts.alert-high-cpu | G127: examples\00-default\udp.yml | H127: {"location": "global", "properties": {"criteria": {"allOf": [{"criterionType": "StaticThresholdCriterion", "metricName": "Percentage CPU", "metricNamespace": "Microsoft.Compute/virtualMachines", "name": "HighCpu", "operator": "GreaterThan", "threshold": 80, "timeAggregation": "Average"}], "odata.type": "Microsoft.Azure.Monitor.MultipleResourceMultipleMetricCriteria"}, "description": "CPU above 80% for 15 minutes", "enabled": true, "evaluationFrequency": "PT5M", "scopes": ["/subscriptions/${var.subscription_id}/resourceGroups/rg-data-platform"], "severity": 2, "windowSize": "PT15M"}, "resource_group": "rg-observability"} | I127: BOM 00-default | J127: See BOM
A128: BOM 00-default | B128: dev | C128: azure_diagnostic_settings | D128: diag-purview | F128: resources.azure_diagnostic_settings.diag-purview | G128: examples\00-default\udp.yml | H128: {"properties": {"logs": [{"categoryGroup": "allLogs", "enabled": true}], "metrics": [{"category": "AllMetrics", "enabled": true}], "workspaceId": "/subscriptions/${var.subscription_id}/resourceGroups/rg-observability/providers/Microsoft.OperationalInsights/workspaces/law-analytics"}, "resource_group": "rg-governance"} | I128: BOM 00-default | J128: See BOM
A129: BOM 00-default | B129: dev | C129: azure_metrics | D129: dcr-metrics | F129: resources.azure_metrics.dcr-metrics | G129: examples\00-default\udp.yml | H129: {"kind": "Linux", "properties": {"description": "Platform metrics collection"}, "resource_group": "rg-observability"} | I129: BOM 00-default | J129: See BOM
A130: BOM 00-default | B130: dev | C130: azure_workbooks | D130: 6f1d5c2e-3b7a-4c9e-8d21-5a9b7c4e1f30 | F130: resources.azure_workbooks.6f1d5c2e-3b7a-4c9e-8d21-5a9b7c4e1f30 | G130: examples\00-default\udp.yml | H130: {"kind": "shared", "properties": {"category": "workbook", "displayName": "Data platform overview", "serializedData": "{\"version\":\"Notebook/1.0\",\"items\":[]}", "sourceId": "Azure Monitor"}, "resource_group": "rg-observability"} | I130: BOM 00-default | J130: See BOM
A131: BOM 00-default | B131: dev | C131: azure_activity_logs | D131: activity-export | F131: resources.azure_activity_logs.activity-export | G131: examples\00-default\udp.yml | H131: {"properties": {"logs": [{"category": "Administrative", "enabled": true}], "workspaceId": "/subscriptions/${var.subscription_id}/resourceGroups/rg-observability/providers/Microsoft.OperationalInsights/workspaces/law-analytics"}, "resource_group": "rg-observability"} | I131: BOM 00-default | J131: See BOM
A132: BOM 00-default | B132: dev | C132: azure_database_watchers | D132: dbwatcher-sql | F132: resources.azure_database_watchers.dbwatcher-sql | G132: examples\00-default\udp.yml | H132: {"resource_group": "rg-observability"} | I132: BOM 00-default | J132: See BOM
A133: BOM 00-default | B133: dev | C133: azure_network_watchers | D133: nw-eastus | F133: resources.azure_network_watchers.nw-eastus | G133: examples\00-default\udp.yml | H133: {"resource_group": "rg-networking"} | I133: BOM 00-default | J133: See BOM
A134: BOM 00-default | B134: dev | C134: azure_dns_zones | D134: contoso.example.com | F134: resources.azure_dns_zones.contoso.example.com | G134: examples\00-default\udp.yml | H134: {"location": "global", "properties": {"zoneType": "Public"}, "resource_group": "rg-networking"} | I134: BOM 00-default | J134: See BOM
A135: BOM 00-default | B135: dev | C135: azure_private_dns_zones | D135: privatelink.purview.azure.com | F135: resources.azure_private_dns_zones.privatelink.purview.azure.com | G135: examples\00-default\udp.yml | H135: {"location": "global", "resource_group": "rg-networking"} | I135: BOM 00-default | J135: See BOM
A136: BOM 00-default | B136: dev | C136: azure_private_dns_zones | D136: privatelink.purviewstudio.azure.com | F136: resources.azure_private_dns_zones.privatelink.purviewstudio.azure.com | G136: examples\00-default\udp.yml | H136: {"location": "global", "resource_group": "rg-networking"} | I136: BOM 00-default | J136: See BOM
A137: BOM 00-default | B137: dev | C137: azure_private_dns_zones | D137: privatelink.blob.core.windows.net | F137: resources.azure_private_dns_zones.privatelink.blob.core.windows.net | G137: examples\00-default\udp.yml | H137: {"location": "global", "resource_group": "rg-networking"} | I137: BOM 00-default | J137: See BOM
... A141: BOM 00-default | B141: dev | C141: azure_network_interfaces | D141: nic-app01 | F141: resources.azure_network_interfaces.nic-app01 | G141: examples\00-default\udp.yml | H141: {"properties": {"ipConfigurations": [{"name": "ipconfig1", "properties": {"privateIPAllocationMethod": "Dynamic"}}]}, "resource_group": "rg-networking"} | I141: BOM 00-default | J141: See BOM
A142: BOM 00-default | B142: dev | C142: azure_public_ip_addresses | D142: pip-agw | E142: Standard | F142: resources.azure_public_ip_addresses.pip-agw | G142: examples\00-default\udp.yml | H142: {"properties": {"publicIPAddressVersion": "IPv4", "publicIPAllocationMethod": "Static"}, "resource_group": "rg-networking", "sku": "Standard"} | I142: BOM 00-default | J142: See BOM
A143: BOM 00-default | B143: dev | C143: azure_route_tables | D143: rt-spoke | F143: resources.azure_route_tables.rt-spoke | G143: examples\00-default\udp.yml | H143: {"properties": {"disableBgpRoutePropagation": true}, "resource_group": "rg-networking"} | I143: BOM 00-default | J143: See BOM
A144: BOM 00-default | B144: dev | C144: azure_virtual_networks | D144: vnet-hub | F144: resources.azure_virtual_networks.vnet-hub | G144: examples\00-default\udp.yml | H144: {"properties": {"addressSpace": {"addressPrefixes": ["10.0.0.0/16"]}, "subnets": [{"name": "snet-private-endpoints", "properties": {"addressPrefix": "10.0.1.0/24"}}, {"name": "snet-data", "properties": {"addressPrefix": "10.0.2.0/24"}}]}, "resource_group": "rg-networking"} | I144: BOM 00-default | J144: See BOM
A145: BOM 00-default | B145: dev | C145: azure_local_network_gateways | D145: lng-onprem | F145: resources.azure_local_network_gateways.lng-onprem | G145: examples\00-default\udp.yml | H145: {"properties": {"gatewayIpAddress": "203.0.113.10", "localNetworkAddressSpace": {"addressPrefixes": ["192.168.0.0/24"]}}, "resource_group": "rg-networking"} | I145: BOM 00-default | J145: See BOM
A146: BOM 00-default | B146: dev | C146: azure_peering_services | D146: peersvc-isp | F146: resources.azure_peering_services.peersvc-isp | G146: examples\00-default\udp.yml | H146: {"resource_group": "rg-networking"} | I146: BOM 00-default | J146: See BOM
A147: BOM 00-default | B147: dev | C147: azure_peerings | D147: peer-isp | F147: resources.azure_peerings.peer-isp | G147: examples\00-default\udp.yml | H147: {"resource_group": "rg-networking"} | I147: BOM 00-default | J147: See BOM
A148: BOM 00-default | B148: dev | C148: azure_virtual_network_gateways | D148: vng-hub | F148: resources.azure_virtual_network_gateways.vng-hub | G148: examples\00-default\udp.yml | H148: {"properties": {"gatewayType": "Vpn", "vpnType": "RouteBased"}, "resource_group": "rg-networking"} | I148: BOM 00-default | J148: See BOM
A149: BOM 00-default | B149: dev | C149: azure_virtual_wans | D149: vwan-global | F149: resources.azure_virtual_wans.vwan-global | G149: examples\00-default\udp.yml | H149: {"properties": {"allowBranchToBranchTraffic": true, "type": "Standard"}, "resource_group": "rg-networking"} | I149: BOM 00-default | J149: See BOM
A150: BOM 00-default | B150: dev | C150: azure_ddos_protection_plans | D150: ddos-hub | F150: resources.azure_ddos_protection_plans.ddos-hub | G150: examples\00-default\udp.yml | H150: {"resource_group": "rg-networking"} | I150: BOM 00-default | J150: See BOM
A151: BOM 00-default | B151: dev | C151: azure_firewalls | D151: afw-hub | E151: {"name": "AZFW_VNet", "tier": "Standard"} | F151: resources.azure_firewalls.afw-hub | G151: examples\00-default\udp.yml | H151: {"properties": {"sku": {"name": "AZFW_VNet", "tier": "Standard"}, "threatIntelMode": "Alert"}, "resource_group": "rg-networking"} | I151: BOM 00-default | J151: See BOM
A152: BOM 00-default | B152: dev | C152: azure_ip_groups | D152: ipg-trusted | F152: resources.azure_ip_groups.ipg-trusted | G152: examples\00-default\udp.yml | H152: {"properties": {"ipAddresses": ["10.0.0.0/8"]}, "resource_group": "rg-networking"} | I152: BOM 00-default | J152: See BOM
A153: BOM 00-default | B153: dev | C153: azure_network_security_groups | D153: nsg-app | F153: resources.azure_network_security_groups.nsg-app | G153: examples\00-default\udp.yml | H153: {"properties": {"securityRules": [{"name": "deny-inbound-internet", "properties": {"access": "Deny", "destinationAddressPrefix": "*", "destinationPortRange": "*", "direction": "Inbound", "priority": 4000, "protocol": "*", "sourceAddressPrefix": "Internet", "sourcePortRange": "*"}}]}, "resource_group": "rg-networking"} | I153: BOM 00-default | J153: See BOM
A154: BOM 00-default | B154: dev | C154: azure_application_gateways | D154: agw-web | F154: resources.azure_application_gateways.agw-web | G154: examples\00-default\udp.yml | H154: {"resource_group": "rg-networking"} | I154: BOM 00-default | J154: See BOM
A155: BOM 00-default | B155: dev | C155: azure_application_security_groups | D155: asg-web | F155: resources.azure_application_security_groups.asg-web | G155: examples\00-default\udp.yml | H155: {"resource_group": "rg-networking"} | I155: BOM 00-default | J155: See BOM
A156: BOM 00-default | B156: dev | C156: tenant_settings | D156: FabricAddPartnerWorkload | F156: admin.tenant_settings.FabricAddPartnerWorkload | G156: examples\00-default\udp.yml | H156: {"enabled": true, "enabled_security_groups": [{"graph_id": "${var.fabric_admins_group_id}", "name": "Fabric Administrators"}], "properties": [{"name": "OnlyCapacityAdmins", "value": "true", "type": "Boolean"}]} | I156: BOM 00-default | J156: No direct settings fee
A157: BOM 00-default | B157: dev | C157: tenant_settings | D157: FabricAddWorkloadToWorkspace | F157: admin.tenant_settings.FabricAddWorkloadToWorkspace | G157: examples\00-default\udp.yml | H157: {"enabled": false} | I157: BOM 00-default | J157: No direct settings fee
A158: BOM 00-default | B158: dev | C158: tenant_settings | D158: FabricThirdPartyWorkloads | F158: admin.tenant_settings.FabricThirdPartyWorkloads | G158: examples\00-default\udp.yml | H158: {"enabled": false} | I158: BOM 00-default | J158: No direct settings fee
A159: BOM 00-default | B159: dev | C159: tenant_settings | D159: ThirdPartyPrivateWorkloads | F159: admin.tenant_settings.ThirdPartyPrivateWorkloads | G159: examples\00-default\udp.yml | H159: {"enabled": false} | I159: BOM 00-default | J159: No direct settings fee
A160: BOM 00-default | B160: dev | C160: tenant_settings | D160: AdminApisIncludeDetailedMetadata | F160: admin.tenant_settings.AdminApisIncludeDetailedMetadata | G160: examples\00-default\udp.yml | H160: {"enabled": true, "enabled_security_groups": [{"graph_id": "${var.fabric_automation_group_id}", "name": "Fabric Automation"}]} | I160: BOM 00-default | J160: No direct settings fee
A161: BOM 00-default | B161: dev | C161: tenant_settings | D161: AdminApisIncludeExpressions | F161: admin.tenant_settings.AdminApisIncludeExpressions | G161: examples\00-default\udp.yml | H161: {"enabled": true, "enabled_security_groups": [{"graph_id": "${var.fabric_automation_group_id}", "name": "Fabric Automation"}]} | I161: BOM 00-default | J161: No direct settings fee
A162: BOM 00-default | B162: dev | C162: tenant_settings | D162: AllowServicePrincipalsUseReadAdminAPIs | F162: admin.tenant_settings.AllowServicePrincipalsUseReadAdminAPIs | G162: examples\00-default\udp.yml | H162: {"enabled": true, "enabled_security_groups": [{"graph_id": "${var.fabric_automation_group_id}", "name": "Fabric Automation"}]} | I162: BOM 00-default | J162: No direct settings fee
A163: BOM 00-default | B163: dev | C163: tenant_settings | D163: AllowServicePrincipalsUseWriteAdminAPIs | F163: admin.tenant_settings.AllowServicePrincipalsUseWriteAdminAPIs | G163: examples\00-default\udp.yml | H163: {"enabled": false} | I163: BOM 00-default | J163: No direct settings fee
... A416: BOM 00-default | B416: staging | C416: azure_resource_groups | D416: rg-ai | F416: resources.azure_resource_groups.rg-ai | G416: examples\00-default\udp.yml | H416: {"location": "eastus2", "tags": {"env": "${var.environment}", "workload": "ai"}} | I416: BOM 00-default | J416: See BOM
A417: BOM 00-default | B417: staging | C417: azure_storage_accounts | D417: stdataplatformdev01 | E417: Standard_GRS | F417: resources.azure_storage_accounts.stdataplatformdev01 | G417: examples\00-default\udp.yml | H417: {"access_tier": "Cool", "https_only": true, "kind": "StorageV2", "location": "eastus", "resource_group": "rg-data-platform", "sku": "Standard_GRS", "subscription": "${var.subscription_id}", "tags": {"env": "${var.environment}", "tier": "archive"}} | I417: BOM 00-default | J417: See BOM
A418: BOM 00-default | B418: staging | C418: azure_deployments | D418: purview-governance | F418: resources.azure_deployments.purview-governance | G418: examples\00-default\udp.yml | H418: {"location": "eastus", "parameters": {"logAnalyticsWorkspaceId": "/subscriptions/${var.subscription_id}/resourceGroups/rg-observability/providers/Microsoft.OperationalInsights/workspaces/law-analytics", "purviewAccountName": "purview-analytics"}, "resource_group": "rg-governance", "scope": "group", "template_file": "./bicep/purview-governance.bicep"} | I418: BOM 00-default | J418: See BOM
A419: BOM 00-default | B419: staging | C419: azure_deployments | D419: subscription-policy-baseline | F419: resources.azure_deployments.subscription-policy-baseline | G419: examples\00-default\udp.yml | H419: {"location": "eastus", "parameters": {"enableDefender": false, "requiredTagName": "data-owner"}, "scope": "subscription", "subscription": "${var.subscription_id}", "template_file": "./bicep/policy-baseline.bicep"} | I419: BOM 00-default | J419: See BOM
A420: BOM 00-default | B420: staging | C420: azure_data_factories | D420: adf-analytics | F420: resources.azure_data_factories.adf-analytics | G420: examples\00-default\udp.yml | H420: {"properties": {"publicNetworkAccess": "Enabled"}, "resource_group": "rg-data-platform"} | I420: BOM 00-default | J420: See BOM
A421: BOM 00-default | B421: staging | C421: azure_databricks_workspaces | D421: dbw-analytics | E421: premium | F421: resources.azure_databricks_workspaces.dbw-analytics | G421: examples\00-default\udp.yml | H421: {"properties": {"managedResourceGroupId": "/subscriptions/${var.subscription_id}/resourceGroups/rg-dbw-analytics-managed", "publicNetworkAccess": "Enabled", "requiredNsgRules": "AllRules"}, "resource_group": "rg-data-platform", "sku": "premium"} | I421: BOM 00-default | J421: See BOM
A422: BOM 00-default | B422: staging | C422: azure_databricks_structured_streaming | D422: dbw-streaming | E422: premium | F422: resources.azure_databricks_structured_streaming.dbw-streaming | G422: examples\00-default\udp.yml | H422: {"properties": {"managedResourceGroupId": "/subscriptions/${var.subscription_id}/resourceGroups/rg-dbw-streaming-managed"}, "resource_group": "rg-data-platform", "sku": "premium"} | I422: BOM 00-default | J422: See BOM
A423: BOM 00-default | B423: staging | C423: azure_event_hub_namespaces | D423: ehns-analytics | E423: Standard | F423: resources.azure_event_hub_namespaces.ehns-analytics | G423: examples\00-default\udp.yml | H423: {"properties": {"disableLocalAuth": true, "isAutoInflateEnabled": true, "maximumThroughputUnits": 4}, "resource_group": "rg-data-platform", "sku": "Standard"} | I423: BOM 00-default | J423: See BOM
A424: BOM 00-default | B424: staging | C424: azure_event_grid_topics | D424: egt-analytics | F424: resources.azure_event_grid_topics.egt-analytics | G424: examples\00-default\udp.yml | H424: {"properties": {"disableLocalAuth": true, "inputSchema": "CloudEventSchemaV1_0", "publicNetworkAccess": "Enabled"}, "resource_group": "rg-data-platform"} | I424: BOM 00-default | J424: See BOM
A425: BOM 00-default | B425: staging | C425: azure_stream_analytics_jobs | D425: asa-analytics | E425: {"name": "Standard"} | F425: resources.azure_stream_analytics_jobs.asa-analytics | G425: examples\00-default\udp.yml | H425: {"properties": {"dataLocale": "en-US", "eventsLateArrivalMaxDelayInSeconds": 5, "eventsOutOfOrderMaxDelayInSeconds": 0, "eventsOutOfOrderPolicy": "Adjust", "jobType": "Cloud", "outputErrorPolicy": "Stop", "sku": {"name": "Standard"}}, "resource_group": "rg-data-platform"} | I425: BOM 00-default | J425: See BOM
...

Sheet Source Manifest
A1: Source manifest | immutable input fingerprints
A3: Source | B3: SHA256 | C3: Deployment | D3: Targets | E3: Source resource count | F3: Notes
A4: scripts\udp.yml | B4: fcc8a4f5aaac7e3db82b89592d7255dcd16ce8db354b69e5723e5037afd12899 | C4: tenant-settings | D4: prod | E4: 0 | F4: Tagged base is identical to example 09.
A5: examples\00-default\udp.yml | B5: 2eadbabb1d7e50d793367ebe4c81826c772e35c14a6e9bb835f97bd162411546 | C5: default-complete | D5: dev, staging, prod, existing | E5: 148 | F5: Alternative scenario; not additive. Bicep dependencies expanded where supported.
A6: examples\01-minimal\udp.yml | B6: 6ce8a4e2802e51d968a6b134a117c823859c6ec575118649eb93c1033e6dd4e7 | C6: minimal-example | D6: dev | E6: 2 | F6: Alternative scenario; not additive. Bicep dependencies expanded where supported.
A7: examples\02-medallion-lakehouse\udp.yml | B7: 0551a5b59d6af53f41539a4426705b4c554f21811c846614844266fc0f0cd289 | C7: medallion-analytics | D7: dev, staging, prod | E7: 11 | F7: Alternative scenario; not additive. Bicep dependencies expanded where supported.
A8: examples\03-real-time-intelligence\udp.yml | B8: 66187fa6542671bdf3f61d1cd97dc56c12041b2128b047bda0a7590e85269123 | C8: realtime-analytics | D8: dev, prod | E8: 6 | F8: Alternative scenario; not additive. Bicep dependencies expanded where supported.
A9: examples\04-data-science\udp.yml | B9: c90fb79e7d70591b2290dfc1d3e6fe75a5fc011011ae2c20b0ae05abd2fe95b1 | C9: ml-pipeline | D9: dev, prod | E9: 9 | F9: Alternative scenario; not additive. Bicep dependencies expanded where supported.
A10: examples\05-multi-environment\udp.yml | B10: 70165e9eacb63349158ca64111dfb92e49533199593c0b481f0b76de1e09d255 | C10: enterprise-analytics | D10: dev, staging, prod | E10: 4 | F10: Alternative scenario; not additive. Bicep dependencies expanded where supported.
A11: examples\06-shortcuts-and-connections\udp.yml | B11: 14d678968562f34dbe87ea832383cce6ad95bf7d2d08e108b0b395da2bb69d47 | C11: external-data-hub | D11: dev | E11: 2 | F11: Alternative scenario; not additive. Bicep dependencies expanded where supported.
A12: examples\07-shortcut-transformations\udp.yml | B12: a93993e4133f29890fa83f3784d3b097bfcf4f2860eba03343df95d3e7605d0f | C12: shortcut-transformations | D12: dev | E12: 3 | F12: Alternative scenario; not additive. Bicep dependencies expanded where supported.
A13: examples\08-all-resource-types\udp.yml | B13: 6e3a99868a8429a77e36ef7b9bead9479c27d7d00733a1fff5e9f1b374879026 | C13: all-resource-types | D13: dev, prod | E13: 46 | F13: Alternative scenario; not additive. Bicep dependencies expanded where supported.
A14: examples\09-tenant-settings\udp.yml | B14: fcc8a4f5aaac7e3db82b89592d7255dcd16ce8db354b69e5723e5037afd12899 | C14: tenant-settings | D14: prod | E14: 0 | F14: Alternative scenario; not additive. Bicep dependencies expanded where supported.
A15: examples\10-azure-and-entra\udp.yml | B15: de7f843a4c83efbe2e3eb28abf89925db9737272a29737dcf14cffa3e123db20 | C15: azure-and-entra-example | D15: dev | E15: 6 | F15: Alternative scenario; not additive. Bicep dependencies expanded where supported.
... A19: examples\14-streaming-lakehouse-governance\udp.yml | B19: 8789de5965d3c75c2909439bce804ce44d7855fd1e6426350716d647d1babaf8 | C19: streaming-lakehouse-governance-example | D19: dev | E19: 10 | F19: Alternative scenario; not additive. Bicep dependencies expanded where supported.
A20: examples\00-default\bicep\policy-baseline.bicep | B20: ed305a1c6686fb9fa11233fbb1cb26787de9f5c163c015834109aa1c2dcc6e62 | F20: Referenced Bicep inspected for conditional resources and existing declarations.
A21: examples\00-default\bicep\purview-governance.bicep | B21: facdbd0dc92a75b1251cc8cd7cf1c48239d760a3e4ad828c2136c1d149b7f595 | F21: Referenced Bicep inspected for conditional resources and existing declarations.
A22: examples\10-azure-and-entra\bicep\keyvault.bicep | B22: fbba981160f51f07ceb7d3db17d289bb9a7bd80f3974376d5335c879f64328dd | F22: Referenced Bicep inspected for conditional resources and existing declarations.

Sheet Lists
A1: Covered | B1: Control plane | C1: Review | D1: Fabric capacity | E1: OneLake storage | F1: Blob storage | G1: Blob storage writes | H1: Blob storage reads | I1: ADLS storage | J1: ADLS storage writes | K1: ADLS storage reads | L1: File storage | M1: Queue storage | N1: Table storage | O1: Key Vault | P1: Logs | Q1: Log retention | R1: Sentinel | S1: Defender servers | T1: Defender storage | U1: Defender Key Vault | V1: OpenAI input | W1: OpenAI output | X1: AI Search | Y1: Private endpoint | Z1: Private endpoint traffic | AA1: DNS | AB1: DNS queries | AC1: Egress | AD1: Firewall | AE1: Firewall traffic | AF1: Public IP | AG1: VPN Gateway | AH1: Virtual WAN | AI1: Application Gateway | AJ1: Application Gateway capacity | AK1: Event Hubs | AL1: Event Hubs events | AM1: Event Grid | AN1: Stream Analytics | AO1: IoT Hub | AP1: ADF data movement | AQ1: ADF orchestration | AR1: Databricks DBU | AS1: VM compute | AT1: SQL DTU | AU1: SQL MI compute | AV1: PostgreSQL compute | AW1: MySQL compute | AX1: PostgreSQL storage | AY1: MySQL storage | AZ1: SQL MI storage | BA1: SQL MI license | BB1: Cosmos throughput | BC1: Redis | BD1: Purview map | BE1: Purview catalog | BF1: Purview processing | BG1: Video Indexer
A2: Included / no separate meter | B2: No direct provisioning charge | C2: REVIEW REQUIRED | D2: SELECT SKU | E2: Hot | F2: Hot LRS | G2: Hot LRS | H2: Hot LRS | I2: Hot LRS | J2: Hot LRS | K2: Hot LRS | L2: Hot LRS | M2: Standard LRS | N2: Standard LRS | O2: Standard | P2: Analytics Logs | Q2: Analytics Logs | R2: Pay-as-you-go | S2: Standard v2 | T2: Standard | U2: Per node Std | V2: GPT-4o-mini global | W2: GPT-4o-mini global | X2: Basic | Y2: Standard | Z2: Standard | AA2: Private | AB2: Private | AC2: Internet first paid band | AD2: Basic | AE2: Basic | AF2: Standard IPv4 | AG2: VpnGw1 | AH2: Routing Infrastructure Unit | AI2: Standard v2 | AJ2: Standard v2 | AK2: Standard | AL2: Standard | AM2: Basic topic / Standard operations meter | AN2: Standard | AO2: S1 | AP2: Cloud | AQ2: Cloud | AR2: Premium Jobs Compute | AS2: Standard_D2s_v5 | AT2: S0 | AU2: GP Gen5 | AV2: Dsv3 vCore | AW2: Dsv3 vCore | AX2: Storage | AY2: Storage | AZ2: General Purpose | BA2: LicenseIncluded - quote required | BB2: Manual provisioned | BC2: Basic C0 | BD2: Standard capacity unit | BE2: Data Catalog Standard | BF2: Data Management Basic | BG2: Standard Video Indexing Analysis
D3: F2 | E3: Cool | F3: Hot GRS | I3: Hot GRS | L3: Premium LRS - quote required | T3: V2 per account - quote required | V3: GPT-4o global | W3: GPT-4o global | X3: Standard S1 | AA3: Public | AB3: Public | AD3: Standard | AE3: Standard | AG3: VpnGw2 | AK3: Basic | AN3: Standard V2 | AO3: S2 | AR3: Premium All-purpose Compute | AS3: Standard_D4s_v5 | AT3: S1 | AW3: D2ds_v4 - quote required | BC3: Standard C1
D4: F4 | E4: Cold | F4: Hot ZRS | I4: Hot ZRS | X4: Standard S2 | AD4: Premium | AE4: Premium | AG4: VpnGw3 | AO4: S3 | AS4: Standard_D8s_v5 | AT4: S2
D5: F8 | F5: Hot RA-GRS | I5: Hot RA-GRS
D6: F16 | F6: Cool LRS | I6: Cool LRS
D7: F32 | F7: Cool GRS | I7: Cool GRS
D8: F64 | F8: Cool ZRS | I8: Cool ZRS
D9: F128 | F9: Cool RA-GRS | I9: Cool RA-GRS
D10: F256
D11: F512
D12: F1024
D13: F2048
D14: F4096
D15: F8192

Sheet Base udp.yml
A1: Base udp.yml | dynamic bill of material
A2: Selected target | B2: prod | D2: Plan default | E2: =Assumptions!B7 -> PAYG | G2: Known monthly USD | H2: =SUM(O6:O26) -> 330.434 | J2: Unpriced lines | K2: =COUNTIFS(A6:A26,B2,Q6:Q26,"UNPRICED*") -> 3 | M2: Estimate status | N2: =IF(K2>0,"INCOMPLETE","COMPLETE") -> INCOMPLETE
A3: Filter Target to the selected value for a compact view. Quantity=0 disables a line. Yellow = editable; green = cross-sheet formula. SKU and units must match.
A5: Target | B5: Category | C5: Origin | D5: Resource / capability | E5: YAML key | F5: Selected SKU | G5: Quantity | H5: Size / monthly usage per resource | I5: PAYG utilization | J5: Purchase plan | K5: Manual monthly rate USD/unit | L5: Effective plan | M5: Size / usage unit | N5: Monthly rate USD/unit | O5: Monthly cost USD | P5: Annual run rate USD | Q5: Pricing status | R5: Assumptions / scope | S5: Source | T5: Capability key | U5: Catalog row | V5: PAYG monthly USD | W5: 1Y monthly USD | X5: 3Y monthly USD
A6: prod | B6: Fabric | C6: Dependency | D6: Shared Fabric capacity | E6: workspace.capacity_id | F6: SELECT SKU | G6: 1 | H6: 1 | I6: 1 | J6: Default | L6: =IF(U6=0,"INVALID SKU",IF(INDEX('SKU Catalog'!$J$1:$J$116,MAX(1,U6))=0,"PAYG",IF(J6="Default",Assumptions!$B$7,J6))) -> PAYG | M6: =IF(U6=0,"Review SKU",INDEX('SKU Catalog'!$E$1:$E$116,MAX(1,U6))) -> capacity | N6: =IF(ISNUMBER(K6),K6,IF(U6=0,"UNPRICED",IF(L6="PAYG",INDEX('SKU Catalog'!$K$1:$K$116,MAX(1,U6)),IF(L6="1Y",INDEX('SKU Catalog'!$L$1:$L$116,MAX(1,U6)),INDEX('SKU Catalog'!$M$1:$M$116,MAX(1,U6)))))) -> UNPRICED | O6: =IF(NOT(AND(A6=$B$2,G6>0,H6>0,OR(C6<>"Recommended baseline",Assumptions!$B$10=1))),0,IF(ISNUMBER(N6),G6*H6*N6*IF(ISNUMBER(K6),1,IF(AND(L6="PAYG",INDEX('SKU Catalog'!$F$1:$F$116,MAX(1,U6))="Hourly"),I6,1)),"UNPRICED")) -> UNPRICED | P6: =IF(ISNUMBER(O6),O6*Assumptions!$B$8,"UNPRICED") -> UNPRICED | Q6: =IF(NOT(AND(A6=$B$2,G6>0,H6>0,OR(C6<>"Recommended baseline",Assumptions!$B$10=1))),"Inactive",IF(NOT(ISNUMBER(N6)),"UNPRICED - select SKU / quote",IF(ISNUMBER(K6),"Manual quote - verify source",IF(T6="Covered","Covered by capacity",IF(T6="Control plane","No direct fee","Priced - verify sizing"))))) -> UNPRICED - select SKU / quote | R6: Existing shared dependency, not created by this YAML. One selected target only; do not sum scenarios. Set quantity=0 for incremental-only costing. | S6: scripts\udp.yml | T6: Fabric capacity | U6: =IF(COUNTIF('SKU Catalog'!$A$4:$A$116,T6&"|"&F6)=0,0,MATCH(T6&"|"&F6,'SKU Catalog'!$A$1:$A$116,0)) -> 7 | V6: =IF(NOT(AND(A6=$B$2,G6>0,H6>0,OR(C6<>"Recommended baseline",Assumptions!$B$10=1))),0,IF(ISNUMBER(K6),G6*H6*K6,IF(U6=0,"UNPRICED",IF(ISNUMBER(INDEX('SKU Catalog'!$K$1:$K$116,MAX(1,U6))),G6*H6*INDEX('SKU Catalog'!$K$1:$K$116,MAX(1,U6))*IF(AND(INDEX('SKU Catalog'!$F$1:$F$116,MAX(1,U6))="Hourly",OR(INDEX('SKU Catalog'!$J$1:$J$116,MAX(1,U6))=0,"PAYG"="PAYG")),I6,1),"UNPRICED")))) -> UNPRICED | W6: =IF(NOT(AND(A6=$B$2,G6>0,H6>0,OR(C6<>"Recommended baseline",Assumptions!$B$10=1))),0,IF(ISNUMBER(K6),G6*H6*K6,IF(U6=0,"UNPRICED",IF(ISNUMBER(INDEX('SKU Catalog'!$L$1:$L$116,MAX(1,U6))),G6*H6*INDEX('SKU Catalog'!$L$1:$L$116,MAX(1,U6))*IF(AND(INDEX('SKU Catalog'!$F$1:$F$116,MAX(1,U6))="Hourly",OR(INDEX('SKU Catalog'!$J$1:$J$116,MAX(1,U6))=0,"1Y"="PAYG")),I6,1),"UNPRICED")))) -> UNPRICED | X6: =IF(NOT(AND(A6=$B$2,G6>0,H6>0,OR(C6<>"Recommended baseline",Assumptions!$B$10=1))),0,IF(ISNUMBER(K6),G6*H6*K6,IF(U6=0,"UNPRICED",IF(ISNUMBER(INDEX('SKU Catalog'!$M$1:$M$116,MAX(1,U6))),G6*H6*INDEX('SKU Catalog'!$M$1:$M$116,MAX(1,U6))*IF(AND(INDEX('SKU Catalog'!$F$1:$F$116,MAX(1,U6))="Hourly",OR(INDEX('SKU Catalog'!$J$1:$J$116,MAX(1,U6))=0,"3Y"="PAYG")),I6,1),"UNPRICED")))) -> UNPRICED
A7: prod | B7: Governance | C7: YAML | D7: PublishToWeb | E7: admin.tenant_settings.PublishToWeb | F7: No direct provisioning charge | G7: 1 | H7: 1 | I7: 1 | J7: Default | L7: =IF(U7=0,"INVALID SKU",IF(INDEX('SKU Catalog'!$J$1:$J$116,MAX(1,U7))=0,"PAYG",IF(J7="Default",Assumptions!$B$7,J7))) -> PAYG | M7: =IF(U7=0,"Review SKU",INDEX('SKU Catalog'!$E$1:$E$116,MAX(1,U7))) -> resource | N7: =IF(ISNUMBER(K7),K7,IF(U7=0,"UNPRICED",IF(L7="PAYG",INDEX('SKU Catalog'!$K$1:$K$116,MAX(1,U7)),IF(L7="1Y",INDEX('SKU Catalog'!$L$1:$L$116,MAX(1,U7)),INDEX('SKU Catalog'!$M$1:$M$116,MAX(1,U7)))))) -> 0 | O7: =IF(NOT(AND(A7=$B$2,G7>0,H7>0,OR(C7<>"Recommended baseline",Assumptions!$B$10=1))),0,IF(ISNUMBER(N7),G7*H7*N7*IF(ISNUMBER(K7),1,IF(AND(L7="PAYG",INDEX('SKU Catalog'!$F$1:$F$116,MAX(1,U7))="Hourly"),I7,1)),"UNPRICED")) -> 0 | P7: =IF(ISNUMBER(O7),O7*Assumptions!$B$8,"UNPRICED") -> 0 | Q7: =IF(NOT(AND(A7=$B$2,G7>0,H7>0,OR(C7<>"Recommended baseline",Assumptions!$B$10=1))),"Inactive",IF(NOT(ISNUMBER(N7)),"UNPRICED - select SKU / quote",IF(ISNUMBER(K7),"Manual quote - verify source",IF(T7="Covered","Covered by capacity",IF(T7="Control plane","No direct fee","Priced - verify sizing"))))) -> No direct fee | R7: Tenant setting has no separate per-setting charge. Enabling a feature may cause usage/licensing costs. | S7: scripts\udp.yml | T7: Control plane | U7: =IF(COUNTIF('SKU Catalog'!$A$4:$A$116,T7&"|"&F7)=0,0,MATCH(T7&"|"&F7,'SKU Catalog'!$A$1:$A$116,0)) -> 5 | V7: =IF(NOT(AND(A7=$B$2,G7>0,H7>0,OR(C7<>"Recommended baseline",Assumptions!$B$10=1))),0,IF(ISNUMBER(K7),G7*H7*K7,IF(U7=0,"UNPRICED",IF(ISNUMBER(INDEX('SKU Catalog'!$K$1:$K$116,MAX(1,U7))),G7*H7*INDEX('SKU Catalog'!$K$1:$K$116,MAX(1,U7))*IF(AND(INDEX('SKU Catalog'!$F$1:$F$116,MAX(1,U7))="Hourly",OR(INDEX('SKU Catalog'!$J$1:$J$116,MAX(1,U7))=0,"PAYG"="PAYG")),I7,1),"UNPRICED")))) -> 0 | W7: =IF(NOT(AND(A7=$B$2,G7>0,H7>0,OR(C7<>"Recommended baseline",Assumptions!$B$10=1))),0,IF(ISNUMBER(K7),G7*H7*K7,IF(U7=0,"UNPRICED",IF(ISNUMBER(INDEX('SKU Catalog'!$L$1:$L$116,MAX(1,U7))),G7*H7*INDEX('SKU Catalog'!$L$1:$L$116,MAX(1,U7))*IF(AND(INDEX('SKU Catalog'!$F$1:$F$116,MAX(1,U7))="Hourly",OR(INDEX('SKU Catalog'!$J$1:$J$116,MAX(1,U7))=0,"1Y"="PAYG")),I7,1),"UNPRICED")))) -> 0 | X7: =IF(NOT(AND(A7=$B$2,G7>0,H7>0,OR(C7<>"Recommended baseline",Assumptions!$B$10=1))),0,IF(ISNUMBER(K7),G7*H7*K7,IF(U7=0,"UNPRICED",IF(ISNUMBER(INDEX('SKU Catalog'!$M$1:$M$116,MAX(1,U7))),G7*H7*INDEX('SKU Catalog'!$M$1:$M$116,MAX(1,U7))*IF(AND(INDEX('SKU Catalog'!$F$1:$F$116,MAX(1,U7))="Hourly",OR(INDEX('SKU Catalog'!$J$1:$J$116,MAX(1,U7))=0,"3Y"="PAYG")),I7,1),"UNPRICED")))) -> 0
A8: prod | B8: Governance | C8: YAML | D8: DevelopmentTenantSettings | E8: admin.tenant_settings.DevelopmentTenantSettings | F8: No direct provisioning charge | G8: 1 | H8: 1 | I8: 1 | J8: Default | L8: =IF(U8=0,"INVALID SKU",IF(INDEX('SKU Catalog'!$J$1:$J$116,MAX(1,U8))=0,"PAYG",IF(J8="Default",Assumptions!$B$7,J8))) -> PAYG | M8: =IF(U8=0,"Review SKU",INDEX('SKU Catalog'!$E$1:$E$116,MAX(1,U8))) -> resource | N8: =IF(ISNUMBER(K8),K8,IF(U8=0,"UNPRICED",IF(L8="PAYG",INDEX('SKU Catalog'!$K$1:$K$116,MAX(1,U8)),IF(L8="1Y",INDEX('SKU Catalog'!$L$1:$L$116,MAX(1,U8)),INDEX('SKU Catalog'!$M$1:$M$116,MAX(1,U8)))))) -> 0 | O8: =IF(NOT(AND(A8=$B$2,G8>0,H8>0,OR(C8<>"Recommended baseline",Assumptions!$B$10=1))),0,IF(ISNUMBER(N8),G8*H8*N8*IF(ISNUMBER(K8),1,IF(AND(L8="PAYG",INDEX('SKU Catalog'!$F$1:$F$116,MAX(1,U8))="Hourly"),I8,1)),"UNPRICED")) -> 0 | P8: =IF(ISNUMBER(O8),O8*Assumptions!$B$8,"UNPRICED") -> 0 | Q8: =IF(NOT(AND(A8=$B$2,G8>0,H8>0,OR(C8<>"Recommended baseline",Assumptions!$B$10=1))),"Inactive",IF(NOT(ISNUMBER(N8)),"UNPRICED - select SKU / quote",IF(ISNUMBER(K8),"Manual quote - verify source",IF(T8="Covered","Covered by capacity",IF(T8="Control plane","No direct fee","Priced - verify sizing"))))) -> No direct fee | R8: Tenant setting has no separate per-setting charge. Enabling a feature may cause usage/licensing costs. | S8: scripts\udp.yml | T8: Control plane | U8: =IF(COUNTIF('SKU Catalog'!$A$4:$A$116,T8&"|"&F8)=0,0,MATCH(T8&"|"&F8,'SKU Catalog'!$A$1:$A$116,0)) -> 5 | V8: =IF(NOT(AND(A8=$B$2,G8>0,H8>0,OR(C8<>"Recommended baseline",Assumptions!$B$10=1))),0,IF(ISNUMBER(K8),G8*H8*K8,IF(U8=0,"UNPRICED",IF(ISNUMBER(INDEX('SKU Catalog'!$K$1:$K$116,MAX(1,U8))),G8*H8*INDEX('SKU Catalog'!$K$1:$K$116,MAX(1,U8))*IF(AND(INDEX('SKU Catalog'!$F$1:$F$116,MAX(1,U8))="Hourly",OR(INDEX('SKU Catalog'!$J$1:$J$116,MAX(1,U8))=0,"PAYG"="PAYG")),I8,1),"UNPRICED")))) -> 0 | W8: =IF(NOT(AND(A8=$B$2,G8>0,H8>0,OR(C8<>"Recommended baseline",Assumptions!$B$10=1))),0,IF(ISNUMBER(K8),G8*H8*K8,IF(U8=0,"UNPRICED",IF(ISNUMBER(INDEX('SKU Catalog'!$L$1:$L$116,MAX(1,U8))),G8*H8*INDEX('SKU Catalog'!$L$1:$L$116,MAX(1,U8))*IF(AND(INDEX('SKU Catalog'!$F$1:$F$116,MAX(1,U8))="Hourly",OR(INDEX('SKU Catalog'!$J$1:$J$116,MAX(1,U8))=0,"1Y"="PAYG")),I8,1),"UNPRICED")))) -> 0 | X8: =IF(NOT(AND(A8=$B$2,G8>0,H8>0,OR(C8<>"Recommended baseline",Assumptions!$B$10=1))),0,IF(ISNUMBER(K8),G8*H8*K8,IF(U8=0,"UNPRICED",IF(ISNUMBER(INDEX('SKU Catalog'!$M$1:$M$116,MAX(1,U8))),G8*H8*INDEX('SKU Catalog'!$M$1:$M$116,MAX(1,U8))*IF(AND(INDEX('SKU Catalog'!$F$1:$F$116,MAX(1,U8))="Hourly",OR(INDEX('SKU Catalog'!$J$1:$J$116,MAX(1,U8))=0,"3Y"="PAYG")),I8,1),"UNPRICED")))) -> 0
A9: prod | B9: Governance | C9: YAML | D9: UsageMetricsSettings | E9: admin.tenant_settings.UsageMetricsSettings | F9: No direct provisioning charge | G9: 1 | H9: 1 | I9: 1 | J9: Default | L9: =IF(U9=0,"INVALID SKU",IF(INDEX('SKU Catalog'!$J$1:$J$116,MAX(1,U9))=0,"PAYG",IF(J9="Default",Assumptions!$B$7,J9))) -> PAYG | M9: =IF(U9=0,"Review SKU",INDEX('SKU Catalog'!$E$1:$E$116,MAX(1,U9))) -> resource | N9: =IF(ISNUMBER(K9),K9,IF(U9=0,"UNPRICED",IF(L9="PAYG",INDEX('SKU Catalog'!$K$1:$K$116,MAX(1,U9)),IF(L9="1Y",INDEX('SKU Catalog'!$L$1:$L$116,MAX(1,U9)),INDEX('SKU Catalog'!$M$1:$M$116,MAX(1,U9)))))) -> 0 | O9: =IF(NOT(AND(A9=$B$2,G9>0,H9>0,OR(C9<>"Recommended baseline",Assumptions!$B$10=1))),0,IF(ISNUMBER(N9),G9*H9*N9*IF(ISNUMBER(K9),1,IF(AND(L9="PAYG",INDEX('SKU Catalog'!$F$1:$F$116,MAX(1,U9))="Hourly"),I9,1)),"UNPRICED")) -> 0 | P9: =IF(ISNUMBER(O9),O9*Assumptions!$B$8,"UNPRICED") -> 0 | Q9: =IF(NOT(AND(A9=$B$2,G9>0,H9>0,OR(C9<>"Recommended baseline",Assumptions!$B$10=1))),"Inactive",IF(NOT(ISNUMBER(N9)),"UNPRICED - select SKU / quote",IF(ISNUMBER(K9),"Manual quote - verify source",IF(T9="Covered","Covered by capacity",IF(T9="Control plane","No direct fee","Priced - verify sizing"))))) -> No direct fee | R9: Tenant setting has no separate per-setting charge. Enabling a feature may cause usage/licensing costs. | S9: scripts\udp.yml | T9: Control plane | U9: =IF(COUNTIF('SKU Catalog'!$A$4:$A$116,T9&"|"&F9)=0,0,MATCH(T9&"|"&F9,'SKU Catalog'!$A$1:$A$116,0)) -> 5 | V9: =IF(NOT(AND(A9=$B$2,G9>0,H9>0,OR(C9<>"Recommended baseline",Assumptions!$B$10=1))),0,IF(ISNUMBER(K9),G9*H9*K9,IF(U9=0,"UNPRICED",IF(ISNUMBER(INDEX('SKU Catalog'!$K$1:$K$116,MAX(1,U9))),G9*H9*INDEX('SKU Catalog'!$K$1:$K$116,MAX(1,U9))*IF(AND(INDEX('SKU Catalog'!$F$1:$F$116,MAX(1,U9))="Hourly",OR(INDEX('SKU Catalog'!$J$1:$J$116,MAX(1,U9))=0,"PAYG"="PAYG")),I9,1),"UNPRICED")))) -> 0 | W9: =IF(NOT(AND(A9=$B$2,G9>0,H9>0,OR(C9<>"Recommended baseline",Assumptions!$B$10=1))),0,IF(ISNUMBER(K9),G9*H9*K9,IF(U9=0,"UNPRICED",IF(ISNUMBER(INDEX('SKU Catalog'!$L$1:$L$116,MAX(1,U9))),G9*H9*INDEX('SKU Catalog'!$L$1:$L$116,MAX(1,U9))*IF(AND(INDEX('SKU Catalog'!$F$1:$F$116,MAX(1,U9))="Hourly",OR(INDEX('SKU Catalog'!$J$1:$J$116,MAX(1,U9))=0,"1Y"="PAYG")),I9,1),"UNPRICED")))) -> 0 | X9: =IF(NOT(AND(A9=$B$2,G9>0,H9>0,OR(C9<>"Recommended baseline",Assumptions!$B$10=1))),0,IF(ISNUMBER(K9),G9*H9*K9,IF(U9=0,"UNPRICED",IF(ISNUMBER(INDEX('SKU Catalog'!$M$1:$M$116,MAX(1,U9))),G9*H9*INDEX('SKU Catalog'!$M$1:$M$116,MAX(1,U9))*IF(AND(INDEX('SKU Catalog'!$F$1:$F$116,MAX(1,U9))="Hourly",OR(INDEX('SKU Catalog'!$J$1:$J$116,MAX(1,U9))=0,"3Y"="PAYG")),I9,1),"UNPRICED")))) -> 0
A10: prod | B10: Governance | C10: YAML | D10: ExportToCsvSettings | E10: admin.tenant_settings.ExportToCsvSettings | F10: No direct provisioning charge | G10: 1 | H10: 1 | I10: 1 | J10: Default | L10: =IF(U10=0,"INVALID SKU",IF(INDEX('SKU Catalog'!$J$1:$J$116,MAX(1,U10))=0,"PAYG",IF(J10="Default",Assumptions!$B$7,J10))) -> PAYG | M10: =IF(U10=0,"Review SKU",INDEX('SKU Catalog'!$E$1:$E$116,MAX(1,U10))) -> resource | N10: =IF(ISNUMBER(K10),K10,IF(U10=0,"UNPRICED",IF(L10="PAYG",INDEX('SKU Catalog'!$K$1:$K$116,MAX(1,U10)),IF(L10="1Y",INDEX('SKU Catalog'!$L$1:$L$116,MAX(1,U10)),INDEX('SKU Catalog'!$M$1:$M$116,MAX(1,U10)))))) -> 0 | O10: =IF(NOT(AND(A10=$B$2,G10>0,H10>0,OR(C10<>"Recommended baseline",Assumptions!$B$10=1))),0,IF(ISNUMBER(N10),G10*H10*N10*IF(ISNUMBER(K10),1,IF(AND(L10="PAYG",INDEX('SKU Catalog'!$F$1:$F$116,MAX(1,U10))="Hourly"),I10,1)),"UNPRICED")) -> 0 | P10: =IF(ISNUMBER(O10),O10*Assumptions!$B$8,"UNPRICED") -> 0 | Q10: =IF(NOT(AND(A10=$B$2,G10>0,H10>0,OR(C10<>"Recommended baseline",Assumptions!$B$10=1))),"Inactive",IF(NOT(ISNUMBER(N10)),"UNPRICED - select SKU / quote",IF(ISNUMBER(K10),"Manual quote - verify source",IF(T10="Covered","Covered by capacity",IF(T10="Control plane","No direct fee","Priced - verify sizing"))))) -> No direct fee | R10: Tenant setting has no separate per-setting charge. Enabling a feature may cause usage/licensing costs. | S10: scripts\udp.yml | T10: Control plane | U10: =IF(COUNTIF('SKU Catalog'!$A$4:$A$116,T10&"|"&F10)=0,0,MATCH(T10&"|"&F10,'SKU Catalog'!$A$1:$A$116,0)) -> 5 | V10: =IF(NOT(AND(A10=$B$2,G10>0,H10>0,OR(C10<>"Recommended baseline",Assumptions!$B$10=1))),0,IF(ISNUMBER(K10),G10*H10*K10,IF(U10=0,"UNPRICED",IF(ISNUMBER(INDEX('SKU Catalog'!$K$1:$K$116,MAX(1,U10))),G10*H10*INDEX('SKU Catalog'!$K$1:$K$116,MAX(1,U10))*IF(AND(INDEX('SKU Catalog'!$F$1:$F$116,MAX(1,U10))="Hourly",OR(INDEX('SKU Catalog'!$J$1:$J$116,MAX(1,U10))=0,"PAYG"="PAYG")),I10,1),"UNPRICED")))) -> 0 | W10: =IF(NOT(AND(A10=$B$2,G10>0,H10>0,OR(C10<>"Recommended baseline",Assumptions!$B$10=1))),0,IF(ISNUMBER(K10),G10*H10*K10,IF(U10=0,"UNPRICED",IF(ISNUMBER(INDEX('SKU Catalog'!$L$1:$L$116,MAX(1,U10))),G10*H10*INDEX('SKU Catalog'!$L$1:$L$116,MAX(1,U10))*IF(AND(INDEX('SKU Catalog'!$F$1:$F$116,MAX(1,U10))="Hourly",OR(INDEX('SKU Catalog'!$J$1:$J$116,MAX(1,U10))=0,"1Y"="PAYG")),I10,1),"UNPRICED")))) -> 0 | X10: =IF(NOT(AND(A10=$B$2,G10>0,H10>0,OR(C10<>"Recommended baseline",Assumptions!$B$10=1))),0,IF(ISNUMBER(K10),G10*H10*K10,IF(U10=0,"UNPRICED",IF(ISNUMBER(INDEX('SKU Catalog'!$M$1:$M$116,MAX(1,U10))),G10*H10*INDEX('SKU Catalog'!$M$1:$M$116,MAX(1,U10))*IF(AND(INDEX('SKU Catalog'!$F$1:$F$116,MAX(1,U10))="Hourly",OR(INDEX('SKU Catalog'!$J$1:$J$116,MAX(1,U10))=0,"3Y"="PAYG")),I10,1),"UNPRICED")))) -> 0
A11: prod | B11: Storage | C11: Recommended baseline | D11: ADLS storage | E11: Not deployed by YAML | F11: Hot LRS | G11: 1 | H11: =Assumptions!$B$15 -> 1024 | I11: 1 | J11: Default | L11: =IF(U11=0,"INVALID SKU",IF(INDEX('SKU Catalog'!$J$1:$J$116,MAX(1,U11))=0,"PAYG",IF(J11="Default",Assumptions!$B$7,J11))) -> PAYG | M11: =IF(U11=0,"Review SKU",INDEX('SKU Catalog'!$E$1:$E$116,MAX(1,U11))) -> GB-month | N11: =IF(ISNUMBER(K11),K11,IF(U11=0,"UNPRICED",IF(L11="PAYG",INDEX('SKU Catalog'!$K$1:$K$116,MAX(1,U11)),IF(L11="1Y",INDEX('SKU Catalog'!$L$1:$L$116,MAX(1,U11)),INDEX('SKU Catalog'!$M$1:$M$116,MAX(1,U11)))))) -> 0.021 | O11: =IF(NOT(AND(A11=$B$2,G11>0,H11>0,OR(C11<>"Recommended baseline",Assumptions!$B$10=1))),0,IF(ISNUMBER(N11),G11*H11*N11*IF(ISNUMBER(K11),1,IF(AND(L11="PAYG",INDEX('SKU Catalog'!$F$1:$F$116,MAX(1,U11))="Hourly"),I11,1)),"UNPRICED")) -> 21.504 | P11: =IF(ISNUMBER(O11),O11*Assumptions!$B$8,"UNPRICED") -> 258.048 | Q11: =IF(NOT(AND(A11=$B$2,G11>0,H11>0,OR(C11<>"Recommended baseline",Assumptions!$B$10=1))),"Inactive",IF(NOT(ISNUMBER(N11)),"UNPRICED - select SKU / quote",IF(ISNUMBER(K11),"Manual quote - verify source",IF(T11="Covered","Covered by capacity",IF(T11="Control plane","No direct fee","Priced - verify sizing"))))) -> Priced - verify sizing | R11: ASSUMPTION; recommended starter cost allowance, not an architecture/SLA approval. | S11: User-approved production planning baseline | T11: ADLS storage | U11: =IF(COUNTIF('SKU Catalog'!$A$4:$A$116,T11&"|"&F11)=0,0,MATCH(T11&"|"&F11,'SKU Catalog'!$A$1:$A$116,0)) -> 34 | V11: =IF(NOT(AND(A11=$B$2,G11>0,H11>0,OR(C11<>"Recommended baseline",Assumptions!$B$10=1))),0,IF(ISNUMBER(K11),G11*H11*K11,IF(U11=0,"UNPRICED",IF(ISNUMBER(INDEX('SKU Catalog'!$K$1:$K$116,MAX(1,U11))),G11*H11*INDEX('SKU Catalog'!$K$1:$K$116,MAX(1,U11))*IF(AND(INDEX('SKU Catalog'!$F$1:$F$116,MAX(1,U11))="Hourly",OR(INDEX('SKU Catalog'!$J$1:$J$116,MAX(1,U11))=0,"PAYG"="PAYG")),I11,1),"UNPRICED")))) -> 21.504 | W11: =IF(NOT(AND(A11=$B$2,G11>0,H11>0,OR(C11<>"Recommended baseline",Assumptions!$B$10=1))),0,IF(ISNUMBER(K11),G11*H11*K11,IF(U11=0,"UNPRICED",IF(ISNUMBER(INDEX('SKU Catalog'!$L$1:$L$116,MAX(1,U11))),G11*H11*INDEX('SKU Catalog'!$L$1:$L$116,MAX(1,U11))*IF(AND(INDEX('SKU Catalog'!$F$1:$F$116,MAX(1,U11))="Hourly",OR(INDEX('SKU Catalog'!$J$1:$J$116,MAX(1,U11))=0,"1Y"="PAYG")),I11,1),"UNPRICED")))) -> 21.504 | X11: =IF(NOT(AND(A11=$B$2,G11>0,H11>0,OR(C11<>"Recommended baseline",Assumptions!$B$10=1))),0,IF(ISNUMBER(K11),G11*H11*K11,IF(U11=0,"UNPRICED",IF(ISNUMBER(INDEX('SKU Catalog'!$M$1:$M$116,MAX(1,U11))),G11*H11*INDEX('SKU Catalog'!$M$1:$M$116,MAX(1,U11))*IF(AND(INDEX('SKU Catalog'!$F$1:$F$116,MAX(1,U11))="Hourly",OR(INDEX('SKU Catalog'!$J$1:$J$116,MAX(1,U11))=0,"3Y"="PAYG")),I11,1),"UNPRICED")))) -> 21.504
A12: prod | B12: Storage | C12: Recommended baseline | D12: ADLS storage writes | E12: Not deployed by YAML | F12: Hot LRS | G12: 1 | H12: 10 | I12: 1 | J12: Default | L12: =IF(U12=0,"INVALID SKU",IF(INDEX('SKU Catalog'!$J$1:$J$116,MAX(1,U12))=0,"PAYG",IF(J12="Default",Assumptions!$B$7,J12))) -> PAYG | M12: =IF(U12=0,"Review SKU",INDEX('SKU Catalog'!$E$1:$E$116,MAX(1,U12))) -> 10K operations | N12: =IF(ISNUMBER(K12),K12,IF(U12=0,"UNPRICED",IF(L12="PAYG",INDEX('SKU Catalog'!$K$1:$K$116,MAX(1,U12)),IF(L12="1Y",INDEX('SKU Catalog'!$L$1:$L$116,MAX(1,U12)),INDEX('SKU Catalog'!$M$1:$M$116,MAX(1,U12)))))) -> 0.065 | O12: =IF(NOT(AND(A12=$B$2,G12>0,H12>0,OR(C12<>"Recommended baseline",Assumptions!$B$10=1))),0,IF(ISNUMBER(N12),G12*H12*N12*IF(ISNUMBER(K12),1,IF(AND(L12="PAYG",INDEX('SKU Catalog'!$F$1:$F$116,MAX(1,U12))="Hourly"),I12,1)),"UNPRICED")) -> 0.65 | P12: =IF(ISNUMBER(O12),O12*Assumptions!$B$8,"UNPRICED") -> 7.8 | Q12: =IF(NOT(AND(A12=$B$2,G12>0,H12>0,OR(C12<>"Recommended baseline",Assumptions!$B$10=1))),"Inactive",IF(NOT(ISNUMBER(N12)),"UNPRICED - select SKU / quote",IF(ISNUMBER(K12),"Manual quote - verify source",IF(T12="Covered","Covered by capacity",IF(T12="Control plane","No direct fee","Priced - verify sizing"))))) -> Priced - verify sizing | R12: ASSUMPTION; recommended starter cost allowance, not an architecture/SLA approval. | S12: User-approved production planning baseline | T12: ADLS storage writes | U12: =IF(COUNTIF('SKU Catalog'!$A$4:$A$116,T12&"|"&F12)=0,0,MATCH(T12&"|"&F12,'SKU Catalog'!$A$1:$A$116,0)) -> 42 | V12: =IF(NOT(AND(A12=$B$2,G12>0,H12>0,OR(C12<>"Recommended baseline",Assumptions!$B$10=1))),0,IF(ISNUMBER(K12),G12*H12*K12,IF(U12=0,"UNPRICED",IF(ISNUMBER(INDEX('SKU Catalog'!$K$1:$K$116,MAX(1,U12))),G12*H12*INDEX('SKU Catalog'!$K$1:$K$116,MAX(1,U12))*IF(AND(INDEX('SKU Catalog'!$F$1:$F$116,MAX(1,U12))="Hourly",OR(INDEX('SKU Catalog'!$J$1:$J$116,MAX(1,U12))=0,"PAYG"="PAYG")),I12,1),"UNPRICED")))) -> 0.65 | W12: =IF(NOT(AND(A12=$B$2,G12>0,H12>0,OR(C12<>"Recommended baseline",Assumptions!$B$10=1))),0,IF(ISNUMBER(K12),G12*H12*K12,IF(U12=0,"UNPRICED",IF(ISNUMBER(INDEX('SKU Catalog'!$L$1:$L$116,MAX(1,U12))),G12*H12*INDEX('SKU Catalog'!$L$1:$L$116,MAX(1,U12))*IF(AND(INDEX('SKU Catalog'!$F$1:$F$116,MAX(1,U12))="Hourly",OR(INDEX('SKU Catalog'!$J$1:$J$116,MAX(1,U12))=0,"1Y"="PAYG")),I12,1),"UNPRICED")))) -> 0.65 | X12: =IF(NOT(AND(A12=$B$2,G12>0,H12>0,OR(C12<>"Recommended baseline",Assumptions!$B$10=1))),0,IF(ISNUMBER(K12),G12*H12*K12,IF(U12=0,"UNPRICED",IF(ISNUMBER(INDEX('SKU Catalog'!$M$1:$M$116,MAX(1,U12))),G12*H12*INDEX('SKU Catalog'!$M$1:$M$116,MAX(1,U12))*IF(AND(INDEX('SKU Catalog'!$F$1:$F$116,MAX(1,U12))="Hourly",OR(INDEX('SKU Catalog'!$J$1:$J$116,MAX(1,U12))=0,"3Y"="PAYG")),I12,1),"UNPRICED")))) -> 0.65
A13: prod | B13: Storage | C13: Recommended baseline | D13: ADLS storage reads | E13: Not deployed by YAML | F13: Hot LRS | G13: 1 | H13: 10 | I13: 1 | J13: Default | L13: =IF(U13=0,"INVALID SKU",IF(INDEX('SKU Catalog'!$J$1:$J$116,MAX(1,U13))=0,"PAYG",IF(J13="Default",Assumptions!$B$7,J13))) -> PAYG | M13: =IF(U13=0,"Review SKU",INDEX('SKU Catalog'!$E$1:$E$116,MAX(1,U13))) -> 10K operations | N13: =IF(ISNUMBER(K13),K13,IF(U13=0,"UNPRICED",IF(L13="PAYG",INDEX('SKU Catalog'!$K$1:$K$116,MAX(1,U13)),IF(L13="1Y",INDEX('SKU Catalog'!$L$1:$L$116,MAX(1,U13)),INDEX('SKU Catalog'!$M$1:$M$116,MAX(1,U13)))))) -> 0.005 | O13: =IF(NOT(AND(A13=$B$2,G13>0,H13>0,OR(C13<>"Recommended baseline",Assumptions!$B$10=1))),0,IF(ISNUMBER(N13),G13*H13*N13*IF(ISNUMBER(K13),1,IF(AND(L13="PAYG",INDEX('SKU Catalog'!$F$1:$F$116,MAX(1,U13))="Hourly"),I13,1)),"UNPRICED")) -> 0.05 | P13: =IF(ISNUMBER(O13),O13*Assumptions!$B$8,"UNPRICED") -> 0.6 | Q13: =IF(NOT(AND(A13=$B$2,G13>0,H13>0,OR(C13<>"Recommended baseline",Assumptions!$B$10=1))),"Inactive",IF(NOT(ISNUMBER(N13)),"UNPRICED - select SKU / quote",IF(ISNUMBER(K13),"Manual quote - verify source",IF(T13="Covered","Covered by capacity",IF(T13="Control plane","No direct fee","Priced - verify sizing"))))) -> Priced - verify sizing | R13: ASSUMPTION; recommended starter cost allowance, not an architecture/SLA approval. | S13: User-approved production planning baseline | T13: ADLS storage reads | U13: =IF(COUNTIF('SKU Catalog'!$A$4:$A$116,T13&"|"&F13)=0,0,MATCH(T13&"|"&F13,'SKU Catalog'!$A$1:$A$116,0)) -> 43 | V13: =IF(NOT(AND(A13=$B$2,G13>0,H13>0,OR(C13<>"Recommended baseline",Assumptions!$B$10=1))),0,IF(ISNUMBER(K13),G13*H13*K13,IF(U13=0,"UNPRICED",IF(ISNUMBER(INDEX('SKU Catalog'!$K$1:$K$116,MAX(1,U13))),G13*H13*INDEX('SKU Catalog'!$K$1:$K$116,MAX(1,U13))*IF(AND(INDEX('SKU Catalog'!$F$1:$F$116,MAX(1,U13))="Hourly",OR(INDEX('SKU Catalog'!$J$1:$J$116,MAX(1,U13))=0,"PAYG"="PAYG")),I13,1),"UNPRICED")))) -> 0.05 | W13: =IF(NOT(AND(A13=$B$2,G13>0,H13>0,OR(C13<>"Recommended baseline",Assumptions!$B$10=1))),0,IF(ISNUMBER(K13),G13*H13*K13,IF(U13=0,"UNPRICED",IF(ISNUMBER(INDEX('SKU Catalog'!$L$1:$L$116,MAX(1,U13))),G13*H13*INDEX('SKU Catalog'!$L$1:$L$116,MAX(1,U13))*IF(AND(INDEX('SKU Catalog'!$F$1:$F$116,MAX(1,U13))="Hourly",OR(INDEX('SKU Catalog'!$J$1:$J$116,MAX(1,U13))=0,"1Y"="PAYG")),I13,1),"UNPRICED")))) -> 0.05 | X13: =IF(NOT(AND(A13=$B$2,G13>0,H13>0,OR(C13<>"Recommended baseline",Assumptions!$B$10=1))),0,IF(ISNUMBER(K13),G13*H13*K13,IF(U13=0,"UNPRICED",IF(ISNUMBER(INDEX('SKU Catalog'!$M$1:$M$116,MAX(1,U13))),G13*H13*INDEX('SKU Catalog'!$M$1:$M$116,MAX(1,U13))*IF(AND(INDEX('SKU Catalog'!$F$1:$F$116,MAX(1,U13))="Hourly",OR(INDEX('SKU Catalog'!$J$1:$J$116,MAX(1,U13))=0,"3Y"="PAYG")),I13,1),"UNPRICED")))) -> 0.05
A14: prod | B14: Security | C14: Recommended baseline | D14: Key Vault | E14: Not deployed by YAML | F14: Standard | G14: 1 | H14: =Assumptions!$B$23 -> 10 | I14: 1 | J14: Default | L14: =IF(U14=0,"INVALID SKU",IF(INDEX('SKU Catalog'!$J$1:$J$116,MAX(1,U14))=0,"PAYG",IF(J14="Default",Assumptions!$B$7,J14))) -> PAYG | M14: =IF(U14=0,"Review SKU",INDEX('SKU Catalog'!$E$1:$E$116,MAX(1,U14))) -> 10K operations | N14: =IF(ISNUMBER(K14),K14,IF(U14=0,"UNPRICED",IF(L14="PAYG",INDEX('SKU Catalog'!$K$1:$K$116,MAX(1,U14)),IF(L14="1Y",INDEX('SKU Catalog'!$L$1:$L$116,MAX(1,U14)),INDEX('SKU Catalog'!$M$1:$M$116,MAX(1,U14)))))) -> 0.03 | O14: =IF(NOT(AND(A14=$B$2,G14>0,H14>0,OR(C14<>"Recommended baseline",Assumptions!$B$10=1))),0,IF(ISNUMBER(N14),G14*H14*N14*IF(ISNUMBER(K14),1,IF(AND(L14="PAYG",INDEX('SKU Catalog'!$F$1:$F$116,MAX(1,U14))="Hourly"),I14,1)),"UNPRICED")) -> 0.3 | P14: =IF(ISNUMBER(O14),O14*Assumptions!$B$8,"UNPRICED") -> 3.6 | Q14: =IF(NOT(AND(A14=$B$2,G14>0,H14>0,OR(C14<>"Recommended baseline",Assumptions!$B$10=1))),"Inactive",IF(NOT(ISNUMBER(N14)),"UNPRICED - select SKU / quote",IF(ISNUMBER(K14),"Manual quote - verify source",IF(T14="Covered","Covered by capacity",IF(T14="Control plane","No direct fee","Priced - verify sizing"))))) -> Priced - verify sizing | R14: ASSUMPTION; recommended starter cost allowance, not an architecture/SLA approval. | S14: User-approved production planning baseline | T14: Key Vault | U14: =IF(COUNTIF('SKU Catalog'!$A$4:$A$116,T14&"|"&F14)=0,0,MATCH(T14&"|"&F14,'SKU Catalog'!$A$1:$A$116,0)) -> 48 | V14: =IF(NOT(AND(A14=$B$2,G14>0,H14>0,OR(C14<>"Recommended baseline",Assumptions!$B$10=1))),0,IF(ISNUMBER(K14),G14*H14*K14,IF(U14=0,"UNPRICED",IF(ISNUMBER(INDEX('SKU Catalog'!$K$1:$K$116,MAX(1,U14))),G14*H14*INDEX('SKU Catalog'!$K$1:$K$116,MAX(1,U14))*IF(AND(INDEX('SKU Catalog'!$F$1:$F$116,MAX(1,U14))="Hourly",OR(INDEX('SKU Catalog'!$J$1:$J$116,MAX(1,U14))=0,"PAYG"="PAYG")),I14,1),"UNPRICED")))) -> 0.3 | W14: =IF(NOT(AND(A14=$B$2,G14>0,H14>0,OR(C14<>"Recommended baseline",Assumptions!$B$10=1))),0,IF(ISNUMBER(K14),G14*H14*K14,IF(U14=0,"UNPRICED",IF(ISNUMBER(INDEX('SKU Catalog'!$L$1:$L$116,MAX(1,U14))),G14*H14*INDEX('SKU Catalog'!$L$1:$L$116,MAX(1,U14))*IF(AND(INDEX('SKU Catalog'!$F$1:$F$116,MAX(1,U14))="Hourly",OR(INDEX('SKU Catalog'!$J$1:$J$116,MAX(1,U14))=0,"1Y"="PAYG")),I14,1),"UNPRICED")))) -> 0.3 | X14: =IF(NOT(AND(A14=$B$2,G14>0,H14>0,OR(C14<>"Recommended baseline",Assumptions!$B$10=1))),0,IF(ISNUMBER(K14),G14*H14*K14,IF(U14=0,"UNPRICED",IF(ISNUMBER(INDEX('SKU Catalog'!$M$1:$M$116,MAX(1,U14))),G14*H14*INDEX('SKU Catalog'!$M$1:$M$116,MAX(1,U14))*IF(AND(INDEX('SKU Catalog'!$F$1:$F$116,MAX(1,U14))="Hourly",OR(INDEX('SKU Catalog'!$J$1:$J$116,MAX(1,U14))=0,"3Y"="PAYG")),I14,1),"UNPRICED")))) -> 0.3
